Workbook

Sheet CAJA
C3: CAJA MES DE FEBRERO DEL 2026
A6: FECHA | B6: INGRESO RECIBOS | C6: INGRESOS VARIABLES | D6: GRIFO DE AGUA | E6: INGRESOS MULTAS | F6: VENTA DE ACCESORIOS | G6: MOVILIDAD PETAR | H6: EGRESO TOTAL | I6: SALDO TOTAL
A7: 46054 | B7: =SUMIFS(RECIBOS!$L$4:$L$1057,RECIBOS!$A$4:$A$1057,CAJA!A7) -> 0 | C7: =SUMIFS(INGRESOS!$F$13:$F$37,INGRESOS!$B$13:$B$37,CAJA!A7) -> 0 | D7: =SUMIFS(INGRESOS!$F$43:$F$181,INGRESOS!$B$43:$B$181,CAJA!A7) -> 320 | E7: =SUMIFS(INGRESOS!$F$187:$F$194,INGRESOS!$B$187:$B$194,CAJA!A7) -> 0 | F7: {=SUMIFS(INGRESOS!F201:F204,INGRESOS!B201:B204,CAJA!A7:A37)} -> 0 | G7: =SUMIFS(EGRESOS!$F$46:$F$59,EGRESOS!$B$46:$B$59,CAJA!A7) -> 0 | H7: =SUMIFS(EGRESOS!$F$4:$F$38,EGRESOS!$B$4:$B$38,CAJA!A7) -> 0 | I7: =(B7+C7+D7+F7)-H7 -> 320
A8: 46055 | B8: =SUMIFS(RECIBOS!$L$4:$L$1057,RECIBOS!$A$4:$A$1057,CAJA!A8) -> 707 | C8: =SUMIFS(INGRESOS!$F$13:$F$37,INGRESOS!$B$13:$B$37,CAJA!A8) -> 0 | D8: =SUMIFS(INGRESOS!$F$43:$F$181,INGRESOS!$B$43:$B$181,CAJA!A8) -> 630 | E8: =SUMIFS(INGRESOS!$F$187:$F$194,INGRESOS!$B$187:$B$194,CAJA!A8) -> 100 | F8: 0 | G8: =SUMIFS(EGRESOS!$F$46:$F$59,EGRESOS!$B$46:$B$59,CAJA!A8) -> 0 | H8: =SUMIFS(EGRESOS!$F$4:$F$38,EGRESOS!$B$4:$B$38,CAJA!A8) -> 0 | I8: =(I7+B8+C8+D8+H8+F8)-H8 -> 1657
A9: 46056 | B9: =SUMIFS(RECIBOS!$L$4:$L$1057,RECIBOS!$A$4:$A$1057,CAJA!A9) -> 78 | C9: =SUMIFS(INGRESOS!$F$13:$F$37,INGRESOS!$B$13:$B$37,CAJA!A9) -> 0 | D9: =SUMIFS(INGRESOS!$F$43:$F$181,INGRESOS!$B$43:$B$181,CAJA!A9) -> 330 | E9: =SUMIFS(INGRESOS!$F$187:$F$194,INGRESOS!$B$187:$B$194,CAJA!A9) -> 0 | F9: 0 | G9: =SUMIFS(EGRESOS!$F$46:$F$59,EGRESOS!$B$46:$B$59,CAJA!A9) -> 0 | H9: =SUMIFS(EGRESOS!$F$4:$F$38,EGRESOS!$B$4:$B$38,CAJA!A9) -> 0 | I9: =(I8+B9+C9+D9+H9+F9)-H9 -> 2065
A10: 46057 | B10: =SUMIFS(RECIBOS!$L$4:$L$1057,RECIBOS!$A$4:$A$1057,CAJA!A10) -> 0 | C10: =SUMIFS(INGRESOS!$F$13:$F$37,INGRESOS!$B$13:$B$37,CAJA!A10) -> 0 | D10: =SUMIFS(INGRESOS!$F$43:$F$181,INGRESOS!$B$43:$B$181,CAJA!A10) -> 250 | E10: =SUMIFS(INGRESOS!$F$187:$F$194,INGRESOS!$B$187:$B$194,CAJA!A10) -> 0 | F10: 0 | G10: =SUMIFS(EGRESOS!$F$46:$F$59,EGRESOS!$B$46:$B$59,CAJA!A10) -> 0 | H10: =SUMIFS(EGRESOS!$F$4:$F$38,EGRESOS!$B$4:$B$38,CAJA!A10) -> 0 | I10: =(I9+B10+C10+D10+F10)-H10 -> 2315
A11: 46058 | B11: =SUMIFS(RECIBOS!$L$4:$L$1057,RECIBOS!$A$4:$A$1057,CAJA!A11) -> 44.5 | C11: =SUMIFS(INGRESOS!$F$13:$F$37,INGRESOS!$B$13:$B$37,CAJA!A11) -> 0 | D11: =SUMIFS(INGRESOS!$F$43:$F$181,INGRESOS!$B$43:$B$181,CAJA!A11) -> 140 | E11: =SUMIFS(INGRESOS!$F$187:$F$194,INGRESOS!$B$187:$B$194,CAJA!A11) -> 0 | F11: 0 | G11: =SUMIFS(EGRESOS!$F$46:$F$59,EGRESOS!$B$46:$B$59,CAJA!A11) -> 0 | H11: =SUMIFS(EGRESOS!$F$4:$F$38,EGRESOS!$B$4:$B$38,CAJA!A11) -> 0 | I11: =(I10+B11+C11+D11+F11)-H11 -> 2499.5
A12: 46059 | B12: =SUMIFS(RECIBOS!$L$4:$L$1057,RECIBOS!$A$4:$A$1057,CAJA!A12) -> 0 | C12: =SUMIFS(INGRESOS!$F$13:$F$37,INGRESOS!$B$13:$B$37,CAJA!A12) -> 0 | D12: =SUMIFS(INGRESOS!$F$43:$F$181,INGRESOS!$B$43:$B$181,CAJA!A12) -> 350 | E12: =SUMIFS(INGRESOS!$F$187:$F$194,INGRESOS!$B$187:$B$194,CAJA!A12) -> 0 | F12: 0 | G12: =SUMIFS(EGRESOS!$F$46:$F$59,EGRESOS!$B$46:$B$59,CAJA!A12) -> 0 | H12: =SUMIFS(EGRESOS!$F$4:$F$38,EGRESOS!$B$4:$B$38,CAJA!A12) -> 379 | I12: =(I11+B12+C12+D12+F12)-H12 -> 2470.5
A13: 46060 | B13: =SUMIFS(RECIBOS!$L$4:$L$1057,RECIBOS!$A$4:$A$1057,CAJA!A13) -> 411 | C13: =SUMIFS(INGRESOS!$F$13:$F$37,INGRESOS!$B$13:$B$37,CAJA!A13) -> 0 | D13: =SUMIFS(INGRESOS!$F$43:$F$181,INGRESOS!$B$43:$B$181,CAJA!A13) -> 180 | E13: =SUMIFS(INGRESOS!$F$187:$F$194,INGRESOS!$B$187:$B$194,CAJA!A13) -> 0 | F13: 0 | G13: =SUMIFS(EGRESOS!$F$46:$F$59,EGRESOS!$B$46:$B$59,CAJA!A13) -> 0 | H13: =SUMIFS(EGRESOS!$F$4:$F$38,EGRESOS!$B$4:$B$38,CAJA!A13) -> 0 | I13: =(I12+B13+C13+D13+F13)-H13 -> 3061.5
A14: 46061 | B14: =SUMIFS(RECIBOS!$L$4:$L$1057,RECIBOS!$A$4:$A$1057,CAJA!A14) -> 0 | C14: =SUMIFS(INGRESOS!$F$13:$F$37,INGRESOS!$B$13:$B$37,CAJA!A14) -> 0 | D14: =SUMIFS(INGRESOS!$F$43:$F$181,INGRESOS!$B$43:$B$181,CAJA!A14) -> 150 | E14: =SUMIFS(INGRESOS!$F$187:$F$194,INGRESOS!$B$187:$B$194,CAJA!A14) -> 0 | F14: 0 | G14: =SUMIFS(EGRESOS!$F$46:$F$59,EGRESOS!$B$46:$B$59,CAJA!A14) -> 0 | H14: =SUMIFS(EGRESOS!$F$4:$F$38,EGRESOS!$B$4:$B$38,CAJA!A14) -> 0 | I14: =(I13+B14+C14+D14+F14)-H14 -> 3211.5
A15: 46062 | B15: =SUMIFS(RECIBOS!$L$4:$L$1057,RECIBOS!$A$4:$A$1057,CAJA!A15) -> 247 | C15: =SUMIFS(INGRESOS!$F$13:$F$37,INGRESOS!$B$13:$B$37,CAJA!A15) -> 0 | D15: =SUMIFS(INGRESOS!$F$43:$F$181,INGRESOS!$B$43:$B$181,CAJA!A15) -> 410 | E15: =SUMIFS(INGRESOS!$F$187:$F$194,INGRESOS!$B$187:$B$194,CAJA!A15) -> 0 | F15: 0 | G15: =SUMIFS(EGRESOS!$F$46:$F$59,EGRESOS!$B$46:$B$59,CAJA!A15) -> 0 | H15: =SUMIFS(EGRESOS!$F$4:$F$38,EGRESOS!$B$4:$B$38,CAJA!A15) -> 0 | I15: =(I14+B15+C15+D15+F15)-H15 -> 3868.5
A16: 46063 | B16: =SUMIFS(RECIBOS!$L$4:$L$1057,RECIBOS!$A$4:$A$1057,CAJA!A16) -> 220 | C16: =SUMIFS(INGRESOS!$F$13:$F$37,INGRESOS!$B$13:$B$37,CAJA!A16) -> 0 | D16: =SUMIFS(INGRESOS!$F$43:$F$181,INGRESOS!$B$43:$B$181,CAJA!A16) -> 130 | E16: =SUMIFS(INGRESOS!$F$187:$F$194,INGRESOS!$B$187:$B$194,CAJA!A16) -> 0 | F16: 0 | G16: =SUMIFS(EGRESOS!$F$46:$F$59,EGRESOS!$B$46:$B$59,CAJA!A16) -> 0 | H16: =SUMIFS(EGRESOS!$F$4:$F$38,EGRESOS!$B$4:$B$38,CAJA!A16) -> 762 | I16: =(I15+B16+C16+D16+F16)-H16 -> 3456.5
A17: 46064 | B17: =SUMIFS(RECIBOS!$L$4:$L$1057,RECIBOS!$A$4:$A$1057,CAJA!A17) -> 552.5 | C17: =SUMIFS(INGRESOS!$F$13:$F$37,INGRESOS!$B$13:$B$37,CAJA!A17) -> 0 | D17: =SUMIFS(INGRESOS!$F$43:$F$181,INGRESOS!$B$43:$B$181,CAJA!A17) -> 160 | E17: =SUMIFS(INGRESOS!$F$187:$F$194,INGRESOS!$B$187:$B$194,CAJA!A17) -> 0 | F17: 0 | G17: =SUMIFS(EGRESOS!$F$46:$F$59,EGRESOS!$B$46:$B$59,CAJA!A17) -> 0 | H17: =SUMIFS(EGRESOS!$F$4:$F$38,EGRESOS!$B$4:$B$38,CAJA!A17) -> 0 | I17: =(I16+B17+C17+D17+F17)-H17 -> 4169
A18: 46065 | B18: =SUMIFS(RECIBOS!$L$4:$L$1057,RECIBOS!$A$4:$A$1057,CAJA!A18) -> 558.5 | C18: =SUMIFS(INGRESOS!$F$13:$F$37,INGRESOS!$B$13:$B$37,CAJA!A18) -> 0 | D18: =SUMIFS(INGRESOS!$F$43:$F$181,INGRESOS!$B$43:$B$181,CAJA!A18) -> 60 | E18: =SUMIFS(INGRESOS!$F$187:$F$194,INGRESOS!$B$187:$B$194,CAJA!A18) -> 450 | F18: 0 | G18: =SUMIFS(EGRESOS!$F$46:$F$59,EGRESOS!$B$46:$B$59,CAJA!A18) -> 0 | H18: =SUMIFS(EGRESOS!$F$4:$F$38,EGRESOS!$B$4:$B$38,CAJA!A18) -> 1550 | I18: =(I17+B18+C18+D18+F18)-H18 -> 3237.5
A19: 46066 | B19: =SUMIFS(RECIBOS!$L$4:$L$1057,RECIBOS!$A$4:$A$1057,CAJA!A19) -> 468 | C19: =SUMIFS(INGRESOS!$F$13:$F$37,INGRESOS!$B$13:$B$37,CAJA!A19) -> 0 | D19: =SUMIFS(INGRESOS!$F$43:$F$181,INGRESOS!$B$43:$B$181,CAJA!A19) -> 200 | E19: =SUMIFS(INGRESOS!$F$187:$F$194,INGRESOS!$B$187:$B$194,CAJA!A19) -> 0 | F19: 0 | G19: =SUMIFS(EGRESOS!$F$46:$F$59,EGRESOS!$B$46:$B$59,CAJA!A19) -> 0 | H19: =SUMIFS(EGRESOS!$F$4:$F$38,EGRESOS!$B$4:$B$38,CAJA!A19) -> 0 | I19: =(I18+B19+C19+D19+F19)-H19 -> 3905.5
A20: 46067 | B20: =SUMIFS(RECIBOS!$L$4:$L$1057,RECIBOS!$A$4:$A$1057,CAJA!A20) -> 104.5 | C20: =SUMIFS(INGRESOS!$F$13:$F$37,INGRESOS!$B$13:$B$37,CAJA!A20) -> 0 | D20: =SUMIFS(INGRESOS!$F$43:$F$181,INGRESOS!$B$43:$B$181,CAJA!A20) -> 90 | E20: =SUMIFS(INGRESOS!$F$187:$F$194,INGRESOS!$B$187:$B$194,CAJA!A20) -> 0 | F20: 0 | G20: =SUMIFS(EGRESOS!$F$46:$F$59,EGRESOS!$B$46:$B$59,CAJA!A20) -> 0 | H20: =SUMIFS(EGRESOS!$F$4:$F$38,EGRESOS!$B$4:$B$38,CAJA!A20) -> 0 | I20: =(I19+B20+C20+D20+F20)-H20 -> 4100
A21: 46068 | B21: =SUMIFS(RECIBOS!$L$4:$L$1057,RECIBOS!$A$4:$A$1057,CAJA!A21) -> 0 | C21: =SUMIFS(INGRESOS!$F$13:$F$37,INGRESOS!$B$13:$B$37,CAJA!A21) -> 0 | D21: =SUMIFS(INGRESOS!$F$43:$F$181,INGRESOS!$B$43:$B$181,CAJA!A21) -> 120 | E21: =SUMIFS(INGRESOS!$F$187:$F$194,INGRESOS!$B$187:$B$194,CAJA!A21) -> 0 | F21: 0 | G21: =SUMIFS(EGRESOS!$F$46:$F$59,EGRESOS!$B$46:$B$59,CAJA!A21) -> 0 | H21: =SUMIFS(EGRESOS!$F$4:$F$38,EGRESOS!$B$4:$B$38,CAJA!A21) -> 0 | I21: =(I20+B21+C21+D21+F21)-H21 -> 4220
... A34: 46081 | B34: =SUMIFS(RECIBOS!$L$4:$L$1057,RECIBOS!$A$4:$A$1057,CAJA!A34) -> 512.5 | C34: =SUMIFS(INGRESOS!$F$13:$F$37,INGRESOS!$B$13:$B$37,CAJA!A34) -> 0 | D34: =SUMIFS(INGRESOS!$F$43:$F$181,INGRESOS!$B$43:$B$181,CAJA!A34) -> 60 | E34: =SUMIFS(INGRESOS!$F$187:$F$194,INGRESOS!$B$187:$B$194,CAJA!A34) -> 0 | F34: 0 | G34: =SUMIFS(EGRESOS!$F$46:$F$59,EGRESOS!$B$46:$B$59,CAJA!A34) -> 0 | H34: =SUMIFS(EGRESOS!$F$4:$F$38,EGRESOS!$B$4:$B$38,CAJA!A34) -> 1800 | I34: =(I33+B34+C34+D34+F34)-H34 -> 6464.3
B35: =SUMIFS(RECIBOS!$L$4:$L$1057,RECIBOS!$A$4:$A$1057,CAJA!A35) -> 0 | C35: =SUMIFS(INGRESOS!$F$13:$F$37,INGRESOS!$B$13:$B$37,CAJA!A35) -> 0 | D35: =SUMIFS(INGRESOS!$F$43:$F$181,INGRESOS!$B$43:$B$181,CAJA!A35) -> 0 | E35: =SUMIFS(INGRESOS!$F$187:$F$194,INGRESOS!$B$187:$B$194,CAJA!A35) -> 0 | F35: 0 | G35: =SUMIFS(EGRESOS!$F$46:$F$59,EGRESOS!$B$46:$B$59,CAJA!A35) -> 0 | H35: =SUMIFS(EGRESOS!$F$4:$F$38,EGRESOS!$B$4:$B$38,CAJA!A35) -> 0 | I35: =(I34+B35+C35+D35+F35)-H35 -> 6464.3
B36: =SUMIFS(RECIBOS!$L$4:$L$1057,RECIBOS!$A$4:$A$1057,CAJA!A36) -> 0 | C36: =SUMIFS(INGRESOS!$F$13:$F$37,INGRESOS!$B$13:$B$37,CAJA!A36) -> 0 | D36: =SUMIFS(INGRESOS!$F$43:$F$181,INGRESOS!$B$43:$B$181,CAJA!A36) -> 0 | E36: =SUMIFS(INGRESOS!$F$187:$F$194,INGRESOS!$B$187:$B$194,CAJA!A36) -> 0 | F36: 0 | G36: =SUMIFS(EGRESOS!$F$46:$F$59,EGRESOS!$B$46:$B$59,CAJA!A36) -> 0 | H36: =SUMIFS(EGRESOS!$F$4:$F$38,EGRESOS!$B$4:$B$38,CAJA!A36) -> 0 | I36: =(I35+B36+C36+D36+F36)-H36 -> 6464.3
B37: =SUMIFS(RECIBOS!$L$4:$L$1057,RECIBOS!$A$4:$A$1057,CAJA!A37) -> 0 | C37: =SUMIFS(INGRESOS!$F$13:$F$37,INGRESOS!$B$13:$B$37,CAJA!A37) -> 0 | D37: =SUMIFS(INGRESOS!$F$43:$F$181,INGRESOS!$B$43:$B$181,CAJA!A37) -> 0 | E37: =SUMIFS(INGRESOS!$F$187:$F$194,INGRESOS!$B$187:$B$194,CAJA!A37) -> 0 | F37: 0 | G37: =SUMIFS(EGRESOS!$F$46:$F$59,EGRESOS!$B$46:$B$59,CAJA!A37) -> 0 | H37: =SUMIFS(EGRESOS!$F$4:$F$38,EGRESOS!$B$4:$B$38,CAJA!A37) -> 0 | I37: =(I36+B37+C37+D37+F37)-H37 -> 6464.3
A38: SUMA TOTAL | B38: =SUM(B7:B37) -> 5276.5 | C38: =SUM(C7:C37) -> 0 | D38: =SUM(D7:D37) -> 7860 | E38: =SUM(E7:E37) -> 700 | F38: =SUM(F7:F37) -> 496.3 | G38: =SUM(G7:G37) -> 0 | H38: =SUM(H7:H37) -> 7168.5 | I38: =I37 -> 6464.3
A40: COPIAS/IMPRESIONES | C40: 5 | K40: CAJA DE | L40: COPIAS | M40: 1 | N40: 2 | O40: 2
C42: =B38+C38+D38+E38+F38+C40 -> 14337.8 | G42: =G38 -> 0 | H42: =H38 -> 7168.5 | I42: =C42-H42-G42 -> 7169.3
C43: INGRESO TOTAL | H43: EGRESO TOTAL | I43: SALDO FINAL
A46: CAJA INICIAL DEL MES | I46: 58.2
H48: TOTAL | I48: =I42+I46 -> 7227.5

Sheet RECIBOS
A3: FECHA DE PAGO | C3: N° MEDIDOR | D3: BARRIO | E3: BENEFICIARIO | F3: Dirección | G3: lect. Ant | I3: lect. Actual | J3: MESES | K3: CANT. MES | L3: MONTO | M3: TOTAL - DIA
A4: 46055 | B4: 000772 | C4: 22260480 | D4: PACHAYZA | E4: HUAMANI CORIMANYA ANYELA | F4: PACHAYZA - PARTE BAJA | J4: OCTUBRE/ENERO | K4: 4 | L4: 83
A5: 46055 | B5: 000149 | C5: 6587898 | D5: PACHAYZA | E5: HUAMANI CORIMANYA, ANYELA MARIA | F5: SECTOR PACHAYZA- PARTE BAJA | J5: OCTUBRE/ENERO | K5: 4 | L5: 20 | P5: 000527 | Q5: 2001887 | R5: AYACUCHO | S5: CHAUCAYANQUI ALVAREZ,CARLOS ALEJO | T5: S/N
A6: 46055 | B6: 000628 | C6: 2004080 | D6: PACHAYZA | E6: HUAMANI CORIMANYA, ANYELA MARIA | F6: PACHAYZA - ALTA | J6: OCTUBRE/ENERO | K6: 4 | L6: 43 | P6: 000528 | Q6: 6593681 | R6: AYACUCHO | S6: CHAUCAYANQUI ALVAREZ,CLEMENTE | T6: S/N
A7: 46055 | B7: 000464 | C7: 6562246 | D7: CHAUPI | E7: ROMERO MANCILLA ,YENY MARCELA | F7: CALLE 05 DE AGOSTO S/N | J7: OCTUBRE/ENERO | K7: 4 | L7: 55 | P7: 000529 | Q7: 220014925 | R7: AYACUCHO | S7: SURCO VILLENA,SUSY BETTY | T7: S/N
A8: 46055 | B8: 000154 | C8: 6659603 | D8: PACHAYZA | E8: HUAMANI HUAMANI , JULIO CESAR | F8: SECTOR PACHAYZA -PARTE ALTA | J8: OCTUBRE/ENERO | K8: 4 | L8: 109.5 | P8: 000530 | Q8: 6563926 | R8: AYACUCHO | S8: TORRES COA,CILA CAMILA | T8: S/N
A9: 46055 | B9: 000125 | C9: 6585990 | D9: PACHAYZA | E9: CHUQUIYANQUI URDAY ,LUIS ALBERTO | F9: SECTOR PACHAYZA - PARTE ALTA | J9: NOVIEMBRE-DICIEMBRE-ENERO | K9: 3 | L9: 58 | P9: 000531 | Q9: 6563939 | R9: AYACUCHO | S9: TORRES HUAMANI,AMELIA BENITA | T9: S/N
A10: 46055 | B10: 000715 | C10: 22392664 | D10: CHAUPI | E10: VALDIVIA NEIRA FILOMENA MERY | F10: CALLE LUCMANI S/N | J10: NOVIEMBRE-DICIEMBRE-ENERO | K10: 3 | L10: 15 | P10: 000704 | Q10: 220017513 | R10: CHAUPICERCA | S10: CASTRO USCAMAYTA ELIANA | T10: CHAUPICERCA S/N
A11: 46055 | B11: 000757 | C11: 22393043 | D11: PACHAYZA | E11: VERA HUAMANI , NORMA FILOMENA | F11: PAMPA | J11: NOVIEMBRE-DICIEMBRE-ENERO | K11: 3 | L11: 19 | P11: 000534 | Q11: 6593461 | R11: CHAUPICERCA | S11: NEYRA DE USCAMAYTA,MANUELA ANA | T11: CHAUPI CERCA S/N
A12: 46055 | B12: 000705 | C12: 23013263 | D12: CHAUPI | E12: MANCILLA VERA SUSY MARIBEL | F12: CALLE 5 DE AGOSTO S/N | J12: NOVIEMBRE-DICIEMBRE-ENERO | K12: 3 | L12: 15 | P12: 000533 | Q12: 6593433 | R12: CHAUPICERCA | S12: ROMERO CHAUCAYANQUI JUSTO MARCELO | T12: CHAUPI CERCA S/N
A13: 46055 | B13: 000210 | C13: 19003893 | D13: PACHAYZA | E13: QUISPE CHAUCAYANQUI, BERNA | F13: SECTOR PACHAYZA - PARTE ALTA | J13: NOVIEMBRE-DICIEMBRE-ENERO | K13: 3 | L13: 49 | P13: 000535 | Q13: 6563916 | R13: CHAUPICERCA | S13: USCAMAYTA ALCA ,CILA | T13: CHAUPI CERCA S/N
A14: 46055 | B14: 000729 | C14: 220017506 | D14: CHAUPI | E14: USCAMAYTA MONTALVO, MARITA BERNA | F14: CALLE JUAN USCAMAYTA S/N | J14: OCTUBRE-NOVIEMBRE | K14: 2 | L14: 60.5 | P14: 000536 | Q14: 6593726 | R14: CHAUPICERCA | S14: USCAMAYTA NEYRA,DAVID JESUS | T14: CHAUPI CERCA S/N
A15: 46055 | B15: 000393 | C15: 60062523 | D15: CHAUPI | E15: HUAMANI USCAMAYTA ,SIMEON OSCAR | F15: CALLE 05 DE AGOSTO S/N | J15: DICIEMBRE-ENERO | K15: 2 | L15: 43 | P15: 000537 | Q15: 6593657 | R15: CHAUPICERCA | S15: VERA REVILLA ,MANUEL | T15: CHAUPI CERCA S/N
A16: 46055 | B16: 000190 | C16: 6587891 | D16: PACHAYZA | E16: MONTALVO REVILLA,ESTANISLAO FLAVIO | F16: SECTOR PACHAYZA - TARAPATA | J16: DICIEMBRE-ENERO | K16: 2 | L16: 10 | P16: 000796 | Q16: 22392996 | R16: LUCMANI | S16: ALVAREZ CHUQUIYANQUI, MARIBEL NAYELI | T16: AUCAYPATA S/N
... A27: 46055 | B27: 000624 | C27: 20102277 | D27: CHAUPI | E27: HUAMANI GUTIERRERZ ESTELA RUFINA | F27: CALLE LUCMANI | J27: ENERO | K27: 1 | L27: 11.5 | P27: 000009 | Q27: 6593255 | R27: LUCMANI | S27: CASTRO HUAMANI,AGUSTINA JUSTA | T27: LUCMANI S/N
A28: 46055 | B28: 000374 | C28: 6590267 | D28: CHAUPI | E28: HUAMANI GUTIERREZ ,TEODORO FRANCISCO | F28: CALLE LOS ESTUDIANTES S/N | J28: ENERO | K28: 1 | L28: 11.5 | M28: =SUM(L4:L28) -> 707 | P28: 000010 | Q28: 6659780 | R28: LUCMANI | S28: CHALCO ESCOBAR,REYNA | T28: LUCMANI S/N
A29: 46056 | B29: 000552 | C29: 9090710 | D29: CHAUPI | E29: DEL CARPIO MANCILLA KATHERINE | F29: CALLE 28 DE JULIO S/N | J29: OCTUBRE/ENERO | K29: 4 | L29: 20 | P29: 000011 | Q29: 6659782 | R29: LUCMANI | S29: CHALCO ESCOBAR,TOMAS | T29: LUCMANI S/N
A30: 46056 | B30: 000599 | C30: 19003898 | D30: CHAUPI | E30: USCAMAITA CHAVEZ, OTO LUDWIN | F30: CHAUPI | J30: ENERO | K30: 1 | L30: 7.5 | P30: 000669 | Q30: 21003048 | R30: LUCMANI | S30: CHAVEZ ANTACHOQUE HENRRY | T30: SECTOR JENCHO
A31: 46056 | B31: 000129 | C31: 240000344 | D31: PACHAYZA | E31: TORRES VERA LEONARDO SALOMON | F31: SECTOR PACHAYZA - PARTE ALTA | J31: ENERO | K31: 1 | L31: 10.5 | P31: 000012 | Q31: 21130894 | R31: LUCMANI | S31: CHUQUIYANQUI CHALCO,ELIDA | T31: LUCMANI S/N
A32: 46056 | B32: 000528 | C32: 6593681 | D32: AYACUCHO | E32: CHAUCAYANQUI ALVAREZ,CLEMENTE | F32: S/N | J32: ENERO | K32: 1 | L32: 6.5 | P32: 000013 | Q32: 21003043 | R32: LUCMANI | S32: CHUQUIYANQUI HUAMANI,ETELVINA VILMA | T32: LUCMANI S/N
A33: 46056 | B33: 000116 | C33: 220017305 | D33: PACHAYZA | E33: CHAVEZ ARUTAYPE ,SEGUNDO | F33: SECTOR PACHAYZA- PARTE BAJA | J33: ENERO | K33: 1 | L33: 23.5 | P33: 000014 | Q33: 6578450 | R33: LUCMANI | S33: CORIMANYA DE ARUTAYPE ,SUNILDA MAGDALENA | T33: LUCMANI S/N
A34: 46056 | B34: 000073 | C34: 23015476 | D34: HUAQUILLO | E34: HUAMANI MONTALVO,ROSARIO RUPERTA | F34: HUAQUILLO S/N | J34: ENERO | K34: 1 | L34: 5 | P34: 000686 | Q34: 200031259 | R34: LUCMANI | S34: ESCOBAR ANTACHOQUE SOLEDAD | T34: LUCMANI S/N
A35: 46056 | B35: 000368 | C35: 6590207 | D35: CHAUPI | E35: HUAMANI COA ,ANDRES PEDRO | F35: CALLE LOS ESTUDIANTES S/N | J35: ENERO | K35: 1 | L35: 5 | M35: =SUM(L29:L35) -> 78 | P35: 000684 | Q35: 200031254 | R35: LUCMANI | S35: ESCOBAR CHUQUIYANQUI LISBET NATALI | T35: SECTOR GABINAYOC
A36: 46058 | B36: 000761 | C36: 22392838 | D36: PACHAYZA | E36: MENESES ANTACHOQUE , DAMARIS THAID | F36: JARACHINE | J36: ENERO | K36: 1 | L36: 5 | P36: 000548 | Q36: 09092433 | R36: LUCMANI | S36: ESCOBAR MANCILLA WALTER | T36: AUCAYPATA
A37: 46058 | B37: 000548 | C37: 09092433 | D37: LUCMANI | E37: ESCOBAR MANCILLA WALTER | F37: AUCAYPATA | J37: ENERO | K37: 1 | L37: 19.5 | P37: 000017 | Q37: 6582818 | R37: LUCMANI | S37: ESCOBAR MONTALVO CELSO CELESTINO | T37: LUCMANI S/N
A38: 46058 | B38: 000506 | C38: 60062522 | D38: CHAUPI | E38: USCAMAYTA CHAVEZ ,LIBIA ROXANA | F38: CALLE 05 DE AGOSTO S/N | J38: ENERO | K38: 1 | L38: 13.5 | P38: 000685 | Q38: 200031244 | R38: LUCMANI | S38: FLORES QUISPE ROSA | T38: SECTOR GABINAYOC
A39: 46058 | B39: 000488 | C39: 60062080 | D39: CHAUPI | E39: TORRES MONTALVO ,NEMECIO LINDON | F39: PASAJE EL OLVIDO S/N | J39: ENERO | K39: 1 | L39: 6.5 | M39: =SUM(L36:L39) -> 44.5 | P39: 000631 | Q39: 200039369 | R39: LUCMANI | S39: GUTIERREZ CHALCO RANULFO | T39: CALLE LUCMANI
A40: 46060 | B40: 000058 | C40: 6580442 | D40: HUAQUILLO | E40: AYMARA ALFARO FROILAN A. | F40: HUAQUILLO S/N | J40: OCTUBRE/ENERO | K40: 4 | L40: 20 | P40: 000691 | Q40: 21000863 | R40: LUCMANI | S40: GUTIERREZ CHALCO REYNALDO ROBERTO | T40: LUCMANI S/N
A41: 46060 | B41: 000406 | C41: 60061415 | D41: CHAUPI | E41: MANCILLA ALLCA ,JESUS CEBASTIAN | F41: CALLE 28 DE JULIO S/N | J41: NOVIEMBRE-DICIEMBRE-ENERO | K41: 3 | L41: 33.5 | P41: 000019 | Q41: 6590708 | R41: LUCMANI | S41: GUZMAN CHAUCAYANQUI ,NANCY | T41: LUCMANI S/N
A42: 46060 | B42: 000411 | C42: 220017520 | D42: CHAUPI | E42: MANSILLA NAVINTA ,EUSEBIA JUANA | F42: AVENIDA AVIACION S/N | J42: NOVIEMBRE-DICIEMBRE-ENERO | K42: 3 | L42: 36.5 | P42: 000020 | Q42: 6579093 | R42: LUCMANI | S42: HUAMANI CANDELARIA | T42: LUCMANI S/N
A43: 46060 | B43: 000463 | C43: 6590220 | D43: CHAUPI | E43: ROMERO CHAUCAYANQUI ,JUSTO MARCELO | F43: CALLE 05 DE AGOSTO S/N | J43: DICIEMBRE-ENERO | K43: 2 | L43: 20 | P43: 000021 | Q43: 6579096 | R43: LUCMANI | S43: HUAMANI CARPIO,CIRILO | T43: LUCMANI S/N
A44: 46060 | B44: 000533 | C44: 6593433 | D44: CHAUPICERCA | E44: ROMERO CHAUCAYANQUI JUSTO MARCELO | F44: CHAUPI CERCA S/N | J44: DICIEMBRE-ENERO | K44: 2 | L44: 10 | P44: 000022 | Q44: 6590942 | R44: LUCMANI | S44: HUAMANI COA ,FIDELA CARMEN | T44: LUCMANI S/N
A45: 46060 | B45: 000718 | C45: 22392657 | D45: CHAUPI | E45: CHAVEZ HUAMANI, JESSICA DORIS | F45: CALLE CUYO CUYO | J45: DICIEMBRE-ENERO | K45: 2 | L45: 52 | P45: 000023 | Q45: 21000864 | R45: LUCMANI | S45: HUAMANI COA,LUCIO INGNACIO | T45: LUCMANI S/N
A46: 46060 | B46: 000282 | C46: 60062457 | D46: CHAUPI | E46: TORRES LOPEZ ELVIRA | F46: PASAJE SAN ISIDRO S/N | J46: DICIEMBRE-ENERO | K46: 2 | L46: 71 | P46: 000589 | Q46: 200005311 | R46: LUCMANI | S46: HUAMANI LUQUE CLEDY | T46: LUCMANI S/N
A47: 46060 | B47: 000546 | C47: 60062456 | D47: CHAUPI | E47: AYMARA ALFARO ,FROILAN ANDRES | F47: PASAJE SAN ISIDRO | J47: DICIEMBRE-ENERO | K47: 2 | L47: 45 | P47: 000703 | Q47: 23015475 | R47: LUCMANI | S47: HUAMANI MALVA MARIA | T47: LUCMANI S/N
A48: 46060 | B48: 000102 | C48: 6584514 | D48: PACHAYZA | E48: CASTRO CORIMANYA,ESTANISLAO FLAVIO | F48: SECTOR PACHAYZA - PARTE BAJA | J48: ENERO | K48: 1 | L48: 9.5 | P48: 000025 | Q48: 6593473 | R48: LUCMANI | S48: HUAMANI TORRES CORINA VALERIANA | T48: LUCMANI S/N
A49: 46060 | B49: 000086 | C49: 6582217 | D49: HUAQUILLO | E49: TORRES VERA, JHON ADALID | F49: HUAQUILLO S/N | J49: ENERO | K49: 1 | L49: 7.5 | P49: 000027 | Q49: 6587948 | R49: LUCMANI | S49: HUAMANI USCAMAYTA,MELITON GABRIEL | T49: LUCMANI S/N
A50: 46060 | B50: 000244 | C50: 6578308 | D50: PACHAYZA | E50: TORRES VERA,JHON ADALID | F50: SECTOR PACHAYZA | J50: ENERO | K50: 1 | L50: 34.5 | P50: 000035 | Q50: 6585587 | R50: LUCMANI | S50: ILATAYPE MANSILLA ABEL MARCO | T50: LUCMANI S/N
A51: 46060 | B51: 000283 | C51: 6562501 | D51: CHAUPI | E51: AYMARA ALFARO ,FROILAN ANDRES | F51: CALLE 28 DE JULIO S/N | J51: ENERO | K51: 1 | L51: 32.5 | P51: 000028 | Q51: 23015478 | R51: LUCMANI | S51: LOPEZ CHALCO,BETTY MARIA | T51: LUCMANI S/N
... A55: 46060 | B55: 000151 | C55: 6585733 | D55: PACHAYZA | E55: HUAMANI CORIMANYA, RAFO AQUILES | F55: SECTOR PACHAYZA -TARAPATA | J55: ENERO | K55: 1 | L55: 13.5 | P55: 000032 | Q55: 6572092 | R55: LUCMANI | S55: LUQUE VERA,ELISA LURDES | T55: LUCMANI S/N
A56: 46060 | B56: 000390 | C56: 6577445 | D56: CHAUPI | E56: HUAMANI USCAMAITA ,HIPOLITO | F56: CALLE LOS ESTUDIANTES S/N | J56: ENERO | K56: 1 | L56: 10.5 | M56: =SUM(L40:L56) -> 411 | P56: 000033 | Q56: 21130890 | R56: LUCMANI | S56: LUQUE VERA,URCLANIEL JANIOR | T56: LUCMANI S/N
A57: 46062 | B57: 000509 | C57: 60061389 | D57: CHAUPI | E57: USCAMAITA HUAMANI ELISEO BACILIO | F57: CALLE 28 DE JULIO S/N | J57: NOVIEMBRE-DICIEMBRE-ENERO | K57: 3 | L57: 167.5 | P57: 000762 | Q57: 22392844 | R57: LUCMANI | S57: LYNDA KEYVI , USCAMAYTA CHALCO | T57: CARRETERA PRINCIPAL S/N
A58: 46062 | B58: 000407 | C58: 6588729 | D58: CHAUPI | E58: MANCILLA CHALCO DE RAMIREZ ,CELESTINA PRUDENCIA | F58: CALLE 05 DE AGOSTO S/N | J58: DICIEMBRE-ENERO | K58: 2 | L58: 10 | P58: 000034 | Q58: 6593296 | R58: LUCMANI | S58: MANCILLA CASTRO,MIGUEL | T58: LUCMANI S/N
A59: 46062 | B59: 000180 | C59: 22393044 | D59: PACHAYZA | E59: MONTALVO ARUTAYPE,ISABEL CATALINA | F59: SECTOR PACHAYZA - TARAPATA | J59: ENERO | K59: 1 | L59: 9.5 | P59: 000036 | Q59: 200039366 | R59: LUCMANI | S59: MONTALVO ARUTAYPE,MARIA FELICIANA | T59: LUCMANI S/N
A60: 46062 | B60: 000595 | C60: 19003886 | D60: LUCMANI | E60: NEYRA HUAMANI, BETTY PETRONILA | F60: LUCMANI S/N | J60: ENERO | K60: 1 | L60: 12.5 | P60: 000037 | Q60: 6571879 | R60: LUCMANI | S60: MONTALVO HUAMANI,FORTUNATO YGNACIO | T60: LUCMANI S/N
A61: 46062 | B61: 000693 | C61: 21130888 | D61: CHAUPI | E61: CHAVEZ TORRES RONAL | F61: CALLE 5 DE AGOSTO S/N | J61: ENERO | K61: 1 | L61: 11.5 | P61: 000038 | Q61: 6585795 | R61: LUCMANI | S61: MONTALVO HUAMANI,NELLY PAULA | T61: LUCMANI S/N
A62: 46062 | B62: 000035 | C62: 6585587 | D62: LUCMANI | E62: ILATAYPE MANSILLA ABEL MARCO | F62: LUCMANI S/N | J62: ENERO | K62: 1 | L62: 10 | P62: 000620 | Q62: 2001885 | R62: LUCMANI | S62: MONTALVO NEIRA MARTINA DEFILIA | T62: LUCMANI S/N
A63: 46062 | B63: 000797 | C63: 23020875 | D63: CHAUPI | E63: SILLOCA HUAMANI,MARLENY ELIANA | F63: CALLE LUCMANI S/N | J63: ENERO | K63: 1 | L63: 6.5 | P63: 000039 | Q63: 6660649 | R63: LUCMANI | S63: MONTALVO TORRES,JUAN BAUTISTA | T63: LUCMANI S/N
A64: 46062 | B64: 000462 | C64: 60062024 | D64: CHAUPI | E64: ROCA MAMANI ,ESTEBAN | F64: LUCMANI S/N | J64: ENERO | K64: 1 | L64: 19.5 | M64: =SUM(L57:L64) -> 247 | P64: 000040 | Q64: 20102672 | R64: LUCMANI | S64: MONTALVO TORRES,MANUELA | T64: LUCMANI S/N
A65: 46063 | B65: 000740 | C65: 23022182 | D65: PACHAYZA | E65: VERA SIVINCHA, ANDRES PEDRO | F65: AHUINTA-PACHAYZA | J65: OCTUBRE/ENERO | K65: 4 | L65: 90 | P65: 000041 | Q65: 6571820 | R65: LUCMANI | S65: NAVINTA VDA DE ANTACHOQUE,JULIA | T65: LUCMANI S/N
A66: 46063 | B66: 000664 | C66: 200011838 | D66: PACHAYZA | E66: HUAMANI URDAY VICTOR VICENTE | F66: PACHAYZA-PARTE BAJA | J66: DICIEMBRE-ENERO | K66: 2 | L66: 10
A67: 46063 | B67: 000198 | C67: 6586849 | D67: PACHAYZA | E67: MOTTA NEYRA,ABELINA AGEDA | F67: SECTOR PACHAYZA - PUCRO | J67: DICIEMBRE-ENERO | K67: 2 | L67: 30 | P67: 000043 | Q67: 6578514 | R67: LUCMANI | S67: NEIRA DE ROMERO,EDUARDA FERNANDINA | T67: LUCMANI S/N
A68: 46063 | B68: 000103 | C68: 6584505 | D68: PACHAYZA | E68: CASTRO DE BEDOYA, GUILLERMINA | F68: SECTOR PACHAYZA - PARTE BAJA | J68: ENERO | K68: 1 | L68: 33.5 | P68: 000044 | Q68: 200039368 | R68: LUCMANI | S68: NEYRA DE USCAMAYTA,NOLASCA JULIA | T68: LUCMANI S/N
A69: 46063 | B69: 000379 | C69: 6562548 | D69: CHAUPI | E69: HUAMANI NAVINTA ,SANTOS JULIAN | F69: LUCMANI S/N | J69: ENERO | K69: 1 | L69: 16.5 | P69: 000045 | Q69: 200031260 | R69: LUCMANI | S69: NEYRA GUTIERREZ,ENRIQUE REY | T69: LUCMANI S/N
A70: 46063 | B70: 000038 | C70: 6585795 | D70: LUCMANI | E70: MONTALVO HUAMANI,NELLY PAULA | F70: LUCMANI S/N | J70: ENERO | K70: 1 | L70: 17.5 | P70: 000595 | Q70: 19003886 | R70: LUCMANI | S70: NEYRA HUAMANI, BETTY PETRONILA | T70: LUCMANI S/N
A71: 46063 | B71: 000274 | C71: 09174 | D71: CHAUPI | E71: ALVAREZ VERA LELIS SOLNA | F71: PASAJE EL OLVIDO S/N | J71: ENERO | K71: 1 | L71: 5 | P71: 000047 | Q71: 6660664 | R71: LUCMANI | S71: PALOMINO NEYRA,JUSTINA LUZ | T71: LUCMANI S/N
A72: 46063 | B72: 000712 | C72: 220017320 | D72: CHAUPI | E72: CHUQUIYANQUI DURAN NATTY LUZ | F72: CALLE ELOLVIDO | J72: ENERO | K72: 1 | L72: 17.5 | M72: =SUM(L65:L72) -> 220 | P72: 000048 | Q72: 6571643 | R72: LUCMANI | S72: QUISPE ARUTAYPE,ISABEL | T72: LUCMANI S/N
A73: 46064 | B73: 000178 | C73: 6593627 | D73: PACHAYZA | E73: MANSILLA CASTRO, EULOGIA LEANDRA | F73: SECTOR PACHAYZA - HUAYCHA | J73: OCTUBRE/FEBRERO | K73: 5 | L73: 25 | P73: 000024 | Q73: 6572073 | R73: LUCMANI | S73: QUISPE HUAMANI,CLEMENTE EMILIO | T73: LUCMANI S/N
A74: 46064 | B74: 000320 | C74: 200005301 | D74: CHAUPI | E74: CHUQUIYANQUI DURAN ,JUAN | F74: PASAJE SAN ISIDRO S/N | J74: NOVIEMBRE/FEBRERO | K74: 4 | L74: 69 | P74: 000049 | Q74: 6591593 | R74: LUCMANI | S74: RAMIREZ HUAMANI,MARIA LETICIA | T74: LUCMANI S/N
A75: 46064 | B75: 000044 | C75: 200039368 | D75: LUCMANI | E75: NEYRA DE USCAMAYTA,NOLASCA JULIA | F75: LUCMANI S/N | J75: DICIEMBRE-ENERO-FEBRERO | K75: 3 | L75: 129.5 | P75: 000050 | Q75: 6593289 | R75: LUCMANI | S75: SIVINCHA DE CHAVEZ,MARIA SANTOS | T75: LUCMANI S/N
A76: 46064 | B76: 000225 | C76: 6570854 | D76: PACHAYZA | E76: TICONA SUAQUITA ,ELVIO ROBERT | F76: SECTOR PACHAYZA - PARTE ALTA | J76: DICIEMBRE-ENERO-FEBRERO | K76: 3 | L76: 43.5 | P76: 000651 | Q76: 22392656 | R76: LUCMANI | S76: TORRES CABRERA, ROSMEL VICTOR | T76: CALLE LUCMANI S/N
A77: 46064 | B77: 000537 | C77: 6593657 | D77: CHAUPICERCA | E77: VERA REVILLA ,MANUEL | F77: CHAUPI CERCA S/N | J77: DICIEMBRE-ENERO-FEBRERO | K77: 3 | L77: 17.5 | P77: 000051 | Q77: 6659885 | R77: LUCMANI | S77: TORRES LOPEZ,JULIANA | T77: LUCMANI S/N
A78: 46064 | B78: 000353 | C78: 6562669 | D78: CHAUPI | E78: GONZALES SUPA GLADYS NORMA | F78: LUCMANI S/N | J78: DICIEMBRE-ENERO-FEBRERO | K78: 3 | L78: 25.5 | P78: 000630 | Q78: 200011823 | R78: LUCMANI | S78: USCAMAYTA NAVINTA YSAURO SABINO | T78: CALLE LUCMANI
A79: 46064 | B79: 000520 | C79: 6558359 | D79: CHAUPI | E79: VERA REVILLA ,MANUEL | F79: CALLE LOS ESTUDIANTES S/N | J79: DICIEMBRE-ENERO-FEBRERO | K79: 3 | L79: 15 | P79: 000052 | Q79: 6580285 | R79: LUCMANI | S79: USCAMAYTA NEYRA,MIJAIL GUSMAN | T79: LUCMANI S/N
A80: 46064 | B80: 000754 | C80: 22393040 | D80: CHAUPI | E80: HUAMANI , LUZ HAYDE | F80: PSJ VIRGEN DE LAS NIEVES | J80: ENERO-FERBRERO | K80: 2 | L80: 11.5 | P80: 000053 | Q80: 6571989 | R80: LUCMANI | S80: VERA DE LUQUE,REYNA PETRONILA | T80: LUCMANI S/N
A81: 46064 | B81: 000359 | C81: 23013265 | D81: CHAUPI | E81: HUAMANI ,LUZ HAYDEE | F81: CALLE VIRGEN DE LAS NIEVES S/N | J81: ENERO-FERBRERO | K81: 2 | L81: 31 | P81: 000054 | Q81: 6591590 | R81: LUCMANI | S81: VERA REVILLA ,FIDELISA | T81: LUCMANI S/N
A82: 46064 | B82: 000020 | C82: 6579093 | D82: LUCMANI | E82: HUAMANI CANDELARIA | F82: LUCMANI S/N | J82: ENERO-FERBRERO | K82: 2 | L82: 40 | P82: 000756 | Q82: 22393037 | R82: LUCMANI | S82: ZAPANA MANSILLA , GUSTAVO RAUL | T82: AUCAYPATA
A83: 46064 | B83: 000351 | C83: 6581489 | D83: CHAUPI | E83: CHALCO ,LORENZA GLORIA | F83: PASAJE EL OLVIDO S/N | J83: ENERO-FERBRERO | K83: 2 | L83: 35 | P83: 000498 | Q83: 60062505 | R83: CHAUPI | S83: ALFARO NEYRA DE CHUQUIYANQUI LUCIA POMPEYA | T83: PASAJE SAN ISIDRO S/N
A84: 46064 | B84: 000117 | C84: 220017566 | D84: PACHAYZA | E84: CORIMANYA CHAVEZ, LEYDI FLOR | F84: SECTOR PACHAYZA - PARTE BAJA | J84: ENERO-FERBRERO | K84: 2 | L84: 37 | P84: 000308 | Q84: 60062454 | R84: CHAUPI | S84: ALFARO TORREZ, TATIANA PAOLA | T84: pasaje VIRGEN DE LAS NIEVES
... A89: 46064 | B89: 000069 | C89: 6589759 | D89: HUAQUILLO | E89: GONZALES SOLOISOLO,JUAN | F89: HUAQUILLO S/N | J89: FEBRERO | K89: 1 | L89: 5 | P89: 000276 | Q89: 60062119 | R89: CHAUPI | S89: ANTACHOQUE ESCOBAR ,AMELIA | T89: LUCMANI S/N
A90: 46064 | B90: 000471 | C90: 60062066 | D90: CHAUPI | E90: SIVINCHA MANCILLA ,JUANA | F90: LUCMANI S/N | J90: FEBRERO | K90: 1 | L90: 5 | M90: =SUM(L73:L90) -> 552.5 | P90: 000586 | Q90: 09093268 | R90: CHAUPI | S90: ANTACHOQUE ESCOBAR, FANY KELIDA | T90: LUCMANI S/N
A91: 46065 | B91: 000408 | C91: 6562535 | D91: CHAUPI | E91: MANCILLA HILATAIPE ,BERNARDINA LORENZA | F91: CALLE 28 DE JULIO S/N | J91: OCTUBRE/FEBRERO | K91: 5 | L91: 165.5 | P91: 000672 | Q91: 21003054 | R91: CHAUPI | S91: ANTACHOQUE HERENCIA GENESIS | T91: CALLE 28 DE JULIO
A92: 46065 | B92: 000470 | C92: 6562521 | D92: CHAUPI | E92: SIVINCHA DE CHAVEZ ,MARIA | F92: PASAJE EL OLVIDO S/N | J92: SETIEMBRE/ENERO | K92: 5 | L92: 97.5 | P92: 000277 | Q92: 21133410 | R92: CHAUPI | S92: ANTACHOQUE MANCILLA JUANA | T92: LUCMANI S/N
A93: 46065 | B93: 000002 | C93: 6659764 | D93: LUCMANI | E93: ANTACHOQUE MOTA,JUANA HILDA | F93: LUCMANI S/N | J93: NOVIEMBRE/FEBERO | K93: 4 | L93: 20 | P93: 000275 | Q93: 6590170 | R93: CHAUPI | S93: ANTACHOQUE MANCILLA,ANTONIO MARCELINO | T93: CALLE VIRGEN DEL CARMEN S/N
A94: 46065 | B94: 000775 | C94: 21140812 | D94: PACHAYZA | E94: HUAMANI CHAVEZ, NOHELIA GUISSEL | F94: SECTOR PACHAYZA - AWINTA | J94: OCTUBRE/ENERO | K94: 4 | L94: 53 | P94: 000278 | Q94: 60062464 | R94: CHAUPI | S94: ANTACHOQUE NAVINTA ,LETDY EVANIA | T94: CALLE CUYO CUYO S/N
A95: 46065 | B95: 000017 | C95: 6582818 | D95: LUCMANI | E95: ESCOBAR MONTALVO CELSO CELESTINO | F95: LUCMANI S/N | J95: DICIEMBRE-ENERO-FEBRERO | K95: 3 | L95: 31.5 | P95: 000551 | Q95: 9090209 | R95: CHAUPI | S95: APFATA MONTALVO JAIME RAUL | T95: PASAJE SAN ISIDRO S/N
A96: 46065 | B96: 000391 | C96: 6577452 | D96: CHAUPI | E96: HUAMANI USCAMAITA ,JUAN ROSA | F96: CALLE CUYO CUYO S/N | J96: DICIEMBRE-ENERO-FEBRERO | K96: 3 | L96: 81.5 | P96: 000279 | Q96: 20102295 | R96: CHAUPI | S96: ARROYO CARPIO ,JUAN | T96: LUCMANI S/N
A97: 46065 | B97: 000500 | C97: 60062460 | D97: CHAUPI | E97: USCAMAITA HUAMANI ,EUSEBIA MARTA | F97: CALLE CUYO CUYO S/N | J97: DICIEMBRE-ENERO-FEBRERO | K97: 3 | L97: 15 | P97: 000280 | Q97: 60062051 | R97: CHAUPI | S97: ARUTAIPE COA ,CONCEPCION ESTEFA | T97: CALLE 28 DE JULIO S/N
A98: 46065 | B98: 000638 | C98: 200002890 | D98: CHAUPI | E98: TILLCA MENDOZA YANED | F98: CALLE AVIACION S/N | J98: ENERO-FERBRERO | K98: 2 | L98: 61 | P98: 000467 | Q98: 6581492 | R98: CHAUPI | S98: ARUTAYPE CORIMANYA GLENY | T98: LUCMANI S/N
A99: 46065 | B99: 000174 | C99: 23022179 | D99: PACHAYZA | E99: LAZARO USCAMAYTA CIRO | F99: SECTOR PACHAYZA - PARTE BAJA | J99: FEBRERO | K99: 1 | L99: 5
A100: 46065 | B100: 000454 | C100: 6577473 | D100: CHAUPI | E100: RAMIREZ CONDORI ,NORBERTO JULIAN | F100: CALLE CUYO CUYO S/N | J100: FEBRERO | K100: 1 | L100: 5 | P100: 000281 | Q100: 6577450 | R100: CHAUPI | S100: ARUTAYPE HUAMANI ,MELITON | T100: CALLE 28 DE JULIO S/N
A101: 46065 | B101: 000433 | C101: 60062469 | D101: CHAUPI | E101: NAVINTA HUAMANI ,CLETA PAULA | F101: AVENIDA AVIACION S/N | J101: FEBRERO | K101: 1 | L101: 23.5 | M101: =SUM(L91:L101) -> 558.5 | P101: 000283 | Q101: 6562501 | R101: CHAUPI | S101: AYMARA ALFARO ,FROILAN ANDRES | T101: CALLE 28 DE JULIO S/N
A102: 46066 | B102: 000606 | C102: 19005343 | D102: PACHAYZA | E102: VERA MONTALVO, ROYLITH VIKI | F102: PACHAYZA - ALTA | J102: OCTUBRE/FEBRERO | K102: 5 | L102: 119.5 | P102: 000546 | Q102: 60062456 | R102: CHAUPI | S102: AYMARA ALFARO ,FROILAN ANDRES | T102: PASAJE SAN ISIDRO
A103: 46066 | B103: 000082 | C103: 101737626 | D103: HUAQUILLO | E103: RAMIREZ VERA, BERTI | F103: HUAQUILLO S/N | J103: DICIEMBRE-ENERO-FEBRERO | K103: 3 | L103: 61.5 | P103: 000389 | Q103: 21000862 | R103: CHAUPI | S103: AYMARA ALFARO YENY VITALIA | T103: CALLE 28 DE JULIO S/N
A104: 46066 | B104: 000652 | C104: 2001835 | D104: PACHAYZA | E104: HUAMANI URDAY JOSE CALIXTO | F104: PACHAYZA-PARTE BAJA | J104: DICIEMBRE-ENERO-FEBRERO | K104: 3 | L104: 15 | P104: 000286 | Q104: 6581494 | R104: CHAUPI | S104: AYMARA ALFARO, YENY VITALIA | T104: CALLE JUAN USCAMAYTA S/N
A105: 46066 | B105: 000138 | C105: 21000869 | D105: PACHAYZA | E105: CORIMANYA MANSILLA,DINA OLINDA | F105: SECTOR PACHAYZA -PARTE ALTA | J105: DICIEMBRE-ENERO-FEBRERO | K105: 3 | L105: 99.5 | P105: 000284 | Q105: 6573777 | R105: CHAUPI | S105: AYMARA HUAMANI DE HUAMANI ,CASIMIRA ADRIANA | T105: CALLE VIRGEN DE LAS NIEVES S/N
A106: 46066 | B106: 000594 | C106: 6593539 | D106: PACHAYZA | E106: HUAYTA RAMOS, ANGEL FORTUNATO | F106: PACHAYZA-PARTE BAJA | J106: ENERO-FERBRERO | K106: 2 | L106: 28 | P106: 000583 | Q106: 19002267 | R106: CHAUPI | S106: AYMARA HUAMANI DE HUAMANI, VIVIANA ESTEFA | T106: CALLE, LOS ESTUDIANTES S/N
A107: 46066 | B107: 000591 | C107: 19003883 | D107: PACHAYZA | E107: MONTALVO ALVAREZ, MARLIT JUDY | F107: PACHAYZA-TARAPATA | J107: ENERO-FERBRERO | K107: 2 | L107: 12.5 | P107: 000285 | Q107: 6580027 | R107: CHAUPI | S107: AYMARA LOPEZ ,JUAN CANCIO | T107: CALLE 28 DE JULIO S/N
A108: 46066 | B108: 000645 | C108: 200005302 | D108: PACHAYZA | E108: MONTALVO NEYRA SUSY EVELIN | F108: PACHAYZA-PARTE BAJA | J108: ENERO-FERBRERO | K108: 2 | L108: 26.5 | P108: 000337 | Q108: 60062061 | R108: CHAUPI | S108: CACSIRE VERA CRISTINA MARILU | T108: LUCMANI S/N
A109: 46066 | B109: 000331 | C109: 6590271 | D109: CHAUPI | E109: CONDORI CHUQUIYANQUI ,MENILDA | F109: CALLE 05 DE AGOSTO S/N | J109: ENERO-FERBRERO | K109: 2 | L109: 33 | P109: 000287 | Q109: 60061416 | R109: CHAUPI | S109: CARPIO ARROYO ,BERTILDA | T109: CALLE CUYO CUYO S/N
A110: 46066 | B110: 000079 | C110: 6658956 | D110: HUAQUILLO | E110: NEYRA SIVINCHA, NORMA YSABEL | F110: HUAQUILLO S/N | J110: FEBRERO | K110: 1 | L110: 10.5 | P110: 000288 | Q110: 6580018 | R110: CHAUPI | S110: CARPIO HUAMANI ,AMELIO RUFINO | T110: CALLE 28 DE JULIO S/N
A111: 46066 | B111: 000066 | C111: 6659665 | D111: HUAQUILLO | E111: CALLA HUARSAYA ,LUIS | F111: HUAQUILLO S/N | J111: FEBRERO | K111: 1 | L111: 5 | P111: 000289 | Q111: 6558317 | R111: CHAUPI | S111: CARPIO NAVINTA ,HECTOR SIMON | T111: CALLE 28 DE JULIO S/N
A112: 46066 | B112: 000021 | C112: 6579096 | D112: LUCMANI | E112: HUAMANI CARPIO,CIRILO | F112: LUCMANI S/N | J112: FEBRERO | K112: 1 | L112: 23.5 | P112: 000745 | Q112: 23015477 | R112: CHAUPI | S112: CARPIO VERA, BERLIN | T112: CL 28 DE JULIO S/N
A113: 46066 | B113: 000779 | C113: 20209138 | D113: CHAUPI | E113: NEYRA SIVINCHA, NORMA YSABEL | F113: LUCMANI S/N | J113: FEBRERO | K113: 1 | L113: 13.5 | P113: 000292 | Q113: 6558343 | R113: CHAUPI | S113: CASQUINO MANSILLA ,MARIANO ASUNTO | T113: LUCMANI S/N
... A116: 46066 | B116: 000284 | C116: 6573777 | D116: CHAUPI | E116: AYMARA HUAMANI DE HUAMANI ,CASIMIRA ADRIANA | F116: CALLE VIRGEN DE LAS NIEVES S/N | J116: FEBRERO | K116: 1 | L116: 5 | P116: 000295 | Q116: 6590154 | R116: CHAUPI | S116: CASTRO HUAMANI ,LEONCIO | T116: CHAUPI
A117: 46066 | B117: 000076 | C117: 6563973 | D117: HUAQUILLO | E117: HUAMANI TORRES, CORINA VALERIANA | F117: HUAQUILLO S/N | J117: FEBRERO | K117: 1 | L117: 5 | M117: =SUM(L102:L117) -> 468 | P117: 000296 | Q117: 6562563 | R117: CHAUPI | S117: CASTRO HUAMANI ,MARISOL | T117: LUCMANI S/N
A118: 46067 | B118: 000457 | C118: 6588734 | D118: CHAUPI | E118: RAMIREZ LANASCA ,JUAN CARLOS | F118: LUCMANI S/N | J118: ENERO-FERBRERO | K118: 2 | L118: 10
A119: 46067 | B119: 000446 | C119: 60062060 | D119: CHAUPI | E119: PUGA HUAHUACONDO ,FRANKLIN | F119: LUCMANI S/N | J119: FEBRERO | K119: 1 | L119: 94.5 | M119: =SUM(L118:L119) -> 104.5 | P119: 000358 | Q119: 6577484 | R119: CHAUPI | S119: CASTRO HUAMANI,MIGUEL | T119: CALLE 28 DE JULIO S/N
A120: 46069 | B120: 000104 | C120: 6579755 | D120: PACHAYZA | E120: CHACONDORI ANTACHOQUE,MARITZA | F120: SECTOR PACHAYZA -PARTE ALTA | J120: DICIEMBRE-ENERO-FEBRERO | K120: 3 | L120: 34.5 | P120: 000297 | Q120: 6558319 | R120: CHAUPI | S120: CASTRO LOPEZ ,VICTORIA | T120: PASAJE EL OLVIDO S/N
A121: 46069 | B121: 000656 | C121: 21006534 | D121: PACHAYZA | E121: ALFARO ESCOBAR EDWIN YHON | F121: PACHAYZA-PARTE BAJA | J121: ENERO-FEBRERO | K121: 2 | L121: 22 | P121: 000298 | Q121: 6577456 | R121: CHAUPI | S121: CASTRO USCAMAITA ,ELIANA | T121: AVENIDA AVIACION S/N
...

Sheet INGRESOS
D1: INGRESO X COBRO DE RECIBOS DICIEMBRE 2025
D2: DESCRIPCION | F2: MONTO
B3: BARRIO | C3: =COUNTIF(RECIBOS!$D$4:$D$1057,INGRESOS!D3) -> 94 | D3: CHAUPI | F3: =SUMIF(RECIBOS!D$4:D$1057,"CHAUPI",RECIBOS!L$4:L$1057) -> 2291
B4: BARRIO | C4: =COUNTIF(RECIBOS!$D$4:$D$1057,INGRESOS!D4) -> 76 | D4: PACHAYZA | F4: =SUMIF(RECIBOS!D$4:D$1057,"PACHAYZA",RECIBOS!L$4:L$1057) -> 2237.5
B5: BARRIO | C5: =COUNTIF(RECIBOS!$D$4:$D$1057,INGRESOS!D5) -> 17 | D5: LUCMANI | F5: =SUMIF(RECIBOS!D$4:D$1057,"LUCMANI",RECIBOS!L$4:L$1057) -> 451.5
B6: BARRIO | C6: =COUNTIF(RECIBOS!$D$4:$D$1057,INGRESOS!D6) -> 15 | D6: HUAQUILLO | F6: =SUMIF(RECIBOS!D$4:D$1057,"HUAQUILLO",RECIBOS!L$4:L$1057) -> 196.5
B7: BARRIO | C7: =COUNTIF(RECIBOS!$D$4:$D$1057,INGRESOS!D7) -> 1 | D7: AYACUCHO | F7: =SUMIF(RECIBOS!D$4:D$1057,"AYACUCHO",RECIBOS!L$4:L$1057) -> 6.5
B8: BARRIO | C8: =COUNTIF(RECIBOS!$D$4:$D$1057,INGRESOS!D8) -> 5 | D8: CHAUPICERCA | F8: =SUMIF(RECIBOS!D$4:D$1057,"CHAUPICERCA",RECIBOS!L$4:L$1057) -> 93.5
C9: =SUM(C3:C8) -> 208 | D9: SUMA TOTAL | F9: =SUM(F3:F8) -> 5276.5
D11: INGRESOS VARIABLES (INSTALACION, CONSTRUCCION Y M.O.) DICIEMBRE 2025
B12: FECHA | C12: N° REC. | D12: DESCRIPCION | E12: COD | F12: MONTO
D41: INGRESOS POR GRIFO DE AGUA (FEBRERO 2026)
B42: FECHA | C42: N. REC | D42: DESCRIPCION
A43: DOMINGO | B43: 46054 | C43: 1548 | D43: SERVICIO DE AGUA POTABLE 04 CUBOS. MARTHA HUAMANI | E43: GF | F43: 40
B44: 46054 | C44: 1549 | D44: SERVICIO DE AGUA POTABLE 04 CUBOS. MINERA OREX -" PROSOL" VAA-865 | E44: GF | F44: 40
B45: 46054 | C45: 1550 | D45: SERVICIO DE AGUA POTABLE 04 CUBOS. JHONSON ARAGON | E45: GF | F45: 40
B46: 46054 | C46: 1551 | D46: SERVICIO DE AGUA POTABLE 10 CUBOS. LICACHI | E46: GF | F46: 100
B47: 46054 | C47: 1552 | D47: SERVICIO DE AGUA POTABLE 10 CUBOS. PROSOL ISPACAS | E47: GF | F47: 100 | G47: =SUM(F43:F47) -> 320
A48: LUNES | B48: 46055 | C48: 1553 | D48: SERVICIO DE AGUA POTABLE 04 CUBOS. MINERA OREX -" PROSOL" VAA-865 | E48: GF | F48: 40
B49: 46055 | C49: 1554 | D49: SERVICIO DE AGUA POTABLE 04 CUBOS. MARTHA HUAMANI | E49: GF | F49: 40
B50: 46055 | C50: 1555 | D50: SERVICIO DE AGUA POTABLE 04 CUBOS. MINERA TITAN S.R.L | E50: GF | F50: 40
B51: 46055 | C51: 1556 | D51: SERVICIO DE AGUA POTABLE 04 CUBOS. MINERA TITAN S.R.L | E51: GF | F51: 40
B52: 46055 | C52: 1557 | D52: SERVICIO DE AGUA POTABLE 09 CUBOS. ZAYDA QUISPE | E52: GF | F52: 90
B53: 46055 | C53: 1558 | D53: SERVICIO DE AGUA POTABLE 02 CUBOS. HECTOR TORRES | E53: GF | F53: 20
B54: 46055 | C54: 1559 | D54: SERVICIO DE AGUA POTABLE 11 CUBOS. ROLANDO | E54: GF | F54: 110
B55: 46055 | C55: 1560 | D55: SERVICIO DE AGUA POTABLE 04 CUBOS. JHONSON ESCOBAR | E55: GF | F55: 40
B56: 46055 | C56: 1561 | D56: SERVICIO DE AGUA POTABLE 09 CUBOS. ROLANDO | E56: GF | F56: 90
B57: 46055 | C57: 1562 | D57: SERVICIO DE AGUA POTABLE 04 CUBOS. JESUS | E57: GF | F57: 40
B58: 46055 | C58: 1563 | D58: SERVICIO DE AGUA POTABLE 06 CUBOS. VICENTE SIVINCHA | E58: GF | F58: 60
B59: 46055 | C59: 1564 | D59: SERVICIO DE AGUA POTABLE 02 CUBOS. WALTER NAVINTA | E59: GF | F59: 20 | G59: =SUM(F48:F59) -> 630
A60: MARTES | B60: 46056 | C60: 1565 | D60: SERVICIO DE AGUA POTABLE 04 CUBOS. MARTHA HUAMANI | E60: GF | F60: 40
B61: 46056 | C61: 1566 | D61: SERVICIO DE AGUA POTABLE 04 CUBOS. MINERA OREX -" PROSOL" VAA-865 | E61: GF | F61: 40
B62: 46056 | C62: 1567 | D62: SERVICIO DE AGUA POTABLE 09 CUBOS. RAMIRO | E62: GF | F62: 90
B63: 46056 | C63: 1568 | D63: SERVICIO DE AGUA POTABLE 04 CUBOS. CIMAR /OREX | E63: GF | F63: 40
B64: 46056 | C64: 1569 | D64: SERVICIO DE AGUA POTABLE 04 CUBOS. JOYER MONTALVO | E64: GF | F64: 40
B65: 46056 | C65: 1570 | D65: SERVICIO DE AGUA POTABLE 08 CUBOS. RAMIRO | E65: GF | F65: 80 | G65: =SUM(F60:F65) -> 330
A66: MIERCOLES | B66: 46057 | C66: 1571 | D66: SERVICIO DE AGUA POTABLE 04 CUBOS. MINERA TITAN DEL PERU S.R.L | E66: GF | F66: 40
B67: 46057 | C67: 1572 | D67: SERVICIO DE AGUA POTABLE 04 CUBOS. MARTHA HUAMANI | E67: GF | F67: 40
B68: 46057 | C68: 1573 | D68: SERVICIO DE AGUA POTABLE 04 CUBOS. MINERA OREX -" PROSOL" VAA-865 | E68: GF | F68: 40
B69: 46057 | C69: 1574 | D69: SERVICIO DE AGUA POTABLE 08 CUBOS. RAMIRO | E69: GF | F69: 80
B70: 46057 | C70: 1575 | D70: SERVICIO DE AGUA POTABLE 04 CUBOS. MINERA TITAN DEL PERU S.R.L | E70: GF | F70: 40
B71: 46057 | C71: 1576 | D71: SERVICIO DE AGUA POTABLE 01 CUBOS. ADAN CORIMANYA | E71: GF | F71: 10 | G71: =SUM(F66:F71) -> 250
A72: JUEVES | B72: 46058 | C72: 1577 | D72: SERVICIO DE AGUA POTABLE 04 CUBOS. MINERA TITAN DEL PERU S.R.L | E72: GF | F72: 40
B73: 46058 | C73: 1578 | D73: SERVICIO DE AGUA POTABLE 04 CUBOS. MARTHA HUAMANI | E73: GF | F73: 40
B74: 46058 | C74: 1579 | D74: SERVICIO DE AGUA POTABLE 04 CUBOS. MINERA TITAN DEL PERU S.R.L | E74: GF | F74: 40
B75: 46058 | C75: 1580 | D75: SERVICIO DE AGUA POTABLE 02 CUBOS. MINERA TITAN DEL PERU S.R.L | E75: GF | F75: 20 | G75: =SUM(F72:F75) -> 140
A76: VIERNES | B76: 46059 | C76: 1581 | D76: SERVICIO DE AGUA POTABLE 04 CUBOS. MINERA OREX -" PROSOL" VAA-865 | E76: GF | F76: 40
B77: 46059 | C77: 1582 | D77: SERVICIO DE AGUA POTABLE 02 CUBOS. HECTOR TORRES | E77: GF | F77: 20
B78: 46059 | C78: 1583 | D78: SERVICIO DE AGUA POTABLE 04 CUBOS. JHONSON ESCOBAR | E78: GF | F78: 40
B79: 46059 | C79: 1584 | D79: SERVICIO DE AGUA POTABLE 04 CUBOS. MINERA OREX - "CIMAR" X5X-913 | E79: GF | F79: 40
B80: 46059 | C80: 1585 | D80: SERVICIO DE AGUA POTABLE 13 CUBOS. RAMIRO | E80: GF | F80: 130
B81: 46059 | C81: 1586 | D81: SERVICIO DE AGUA POTABLE 08 CUBOS. RAMIRO | E81: GF | F81: 80 | G81: =SUM(F76:F81) -> 350
A82: SABADO | B82: 46060 | C82: 1587 | D82: SERVICIO DE AGUA POTABLE 04 CUBOS. MARTHA HUAMANI | E82: GF | F82: 40
B83: 46060 | C83: 1588 | D83: SERVICIO DE AGUA POTABLE 02 CUBOS. MARIA | E83: GF | F83: 20
B84: 46060 | C84: 1589 | D84: SERVICIO DE AGUA POTABLE 04 CUBOS. ROLANDO | E84: GF | F84: 50
B85: 46060 | C85: 1590 | D85: SERVICIO DE AGUA POTABLE 04 CUBOS. ROLANDO | E85: GF | F85: 70 | G85: =SUM(F82:F85) -> 180
A86: DIMINGO | B86: 46061 | C86: 1591 | D86: SERVICIO DE AGUA POTABLE 04 CUBOS. MINERA OREX -" PROSOL" VAA-865 | E86: GF | F86: 40
B87: 46061 | C87: 1592 | D87: SERVICIO DE AGUA POTABLE 04 CUBOS. ROY | E87: GF | F87: 40
B88: 46061 | C88: 1593 | D88: SERVICIO DE AGUA POTABLE 04 CUBOS. MINERA TITAN DEL PERU S.R.L | E88: GF | F88: 40
B89: 46061 | C89: 1594 | D89: SERVICIO DE AGUA POTABLE 03 CUBOS. JOYER MONTALVO | E89: GF | F89: 30 | G89: =SUM(F86:F89) -> 150 | H89: 2350
A90: LUNES | B90: 46062 | C90: 1595 | D90: SERVICIO DE AGUA POTABLE 04 CUBOS. MARTHA HUAMANI | E90: GF | F90: 40
B91: 46062 | C91: 1596 | D91: SERVICIO DE AGUA POTABLE 08 CUBOS. RAMIRO | E91: GF | F91: 80
B92: 46062 | C92: 1597 | D92: SERVICIO DE AGUA POTABLE 04 CUBOS. OREX "PROSOL" PLACA VAA-865 | E92: GF | F92: 40
B93: 46062 | C93: 1598 | D93: SERVICIO DE AGUA POTABLE 08 CUBOS. ROY | E93: GF | F93: 80
B94: 46062 | C94: 1599 | D94: SERVICIO DE AGUA POTABLE 06 CUBOS. RAMIRO | E94: GF | F94: 60
B95: 46062 | C95: 1600 | D95: SERVICIO DE AGUA POTABLE 03 CUBOS. PLANTA ORION | E95: GF | F95: 30
B96: 46062 | C96: 1601 | D96: SERVICIO DE AGUA POTABLE 06 CUBOS. LUIS | E96: GF | F96: 60
B97: 46062 | C97: 1602 | D97: SERVICIO DE AGUA POTABLE 02 CUBOS. KATY | E97: GF | F97: 20 | G97: =SUM(F90:F97) -> 410
A98: MARTES | B98: 46063 | C98: 1603 | D98: SERVICIO DE AGUA POTABLE 04 CUBOS. MINERA SOL DE ORO | E98: GF | F98: 40
B99: 46063 | C99: 1604 | D99: SERVICIO DE AGUA POTABLE 04 CUBOS. WALTER NAVINTA | E99: GF | F99: 40
B100: 46063 | C100: 1605 | D100: SERVICIO DE AGUA POTABLE 04 CUBOS. MINERA OREX VAA-865 "CIMAR" | E100: GF | F100: 40
B101: 46063 | C101: 1606 | D101: SERVICIO DE AGUA POTABLE 01 CUBOS. GERARDO MONTALVO TORRES | E101: GF | F101: 10 | G101: =SUM(F98:F101) -> 130
A102: MIERCOLES | B102: 46064 | C102: 1607 | D102: SERVICIO DE AGUA POTABLE 04 CUBOS. MARCIA | E102: GF | F102: 40
B103: 46064 | C103: 1608 | D103: SERVICIO DE AGUA POTABLE 04 CUBOS. JHONSON ESCOBAR | E103: GF | F103: 40
B104: 46064 | C104: 1609 | D104: SERVICIO DE AGUA POTABLE 04 CUBOS. MINERA TITAN DEL PERU S.R.L | E104: GF | F104: 40
B105: 46064 | C105: 1610 | D105: SERVICIO DE AGUA POTABLE 04 CUBOS. GRUPO ALIAGA | E105: GF | F105: 40 | G105: =SUM(F102:F105) -> 160
A106: JUEVES | B106: 46065 | C106: 1611 | D106: SERVICIO DE AGUA POTABLE 01 CUBOS. MARCOS | E106: GF | F106: 10
B107: 46065 | C107: 1612 | D107: SERVICIO DE AGUA POTABLE 04 CUBOS. MINERA OREX "PROSOL" VAA-865 | E107: GF | F107: 40
B108: 46065 | C108: 1613 | D108: SERVICIO DE AGUA POTABLE 01 CUBOS. ESMERALDA | E108: GF | F108: 10 | G108: =SUM(F106:F108) -> 60
A109: VIERNES | B109: 46066 | C109: 1614 | D109: SERVICIO DE AGUA POTABLE 04 CUBOS. ECTOR TORRES | E109: GF | F109: 20
B110: 46066 | C110: 1615 | D110: SERVICIO DE AGUA POTABLE 06 CUBOS. VICENTE SIVINCHA | E110: GF | F110: 60
B111: 46066 | C111: 1616 | D111: SERVICIO DE AGUA POTABLE 04 CUBOS. DIEGO RAMOS | E111: GF | F111: 40
B112: 46066 | C112: 1617 | D112: SERVICIO DE AGUA POTABLE 04 CUBOS. SOL DE LOS ANDES | E112: GF | F112: 40
B113: 46066 | C113: 1618 | D113: SERVICIO DE AGUA POTABLE 04 CUBOS. SOL E LOS ANDES | E113: GF | F113: 40 | G113: =SUM(F109:F113) -> 200
A114: SABADO | B114: 46067 | C114: 1619 | D114: SERVICIO DE AGUA POTABLE 02 CUBOS. MARCIA | E114: GF | F114: 20
B115: 46067 | C115: 1620 | D115: SERVICIO DE AGUA POTABLE 03 CUBOS. MIGUEL CHALCO | E115: GF | F115: 30
B116: 46067 | C116: 1621 | D116: SERVICIO DE AGUA POTABLE 04 CUBOS. MINERA CORIRE | E116: GF | F116: 40 | G116: =SUM(F114:F116) -> 90
A117: DOMINGO | B117: 46068 | C117: 1622 | D117: SERVICIO DE AGUA POTABLE 04 CUBOS. MARTHA HUAMANI | E117: GF | F117: 40
B118: 46068 | C118: 1623 | D118: SERVICIO DE AGUA POTABLE 04 CUBOS. MINERA OREX PROSOL VAA-865 | E118: GF | F118: 40
B119: 46068 | C119: 1624 | D119: SERVICIO DE AGUA POTABLE 04 CUBOS. VICENTE SIVINCHA | E119: GF | F119: 40 | G119: =SUM(F117:F119) -> 120 | H119: 1170
A120: LUNES | B120: 46069 | C120: 1625 | D120: SERVICIO DE AGUA POTABLE 04 CUBOS. SOL DE LOS ANDES | E120: GF | F120: 40
B121: 46069 | C121: 1626 | D121: SERVICIO DE AGUA POTABLE 03 CUBOS. DIEGO RAMOS | E121: GF | F121: 30
B122: 46069 | C122: 1627 | D122: SERVICIO DE AGUA POTABLE 03 CUBOS. DANIEL | E122: GF | F122: 30
B123: 46069 | C123: 1628 | D123: SERVICIO DE AGUA POTABLE 12 CUBOS. ELOY | E123: GF | F123: 120
B124: 46069 | C124: 1629 | D124: SERVICIO DE AGUA POTABLE 08 CUBOS. RAMIRO | E124: GF | F124: 80
B125: 46069 | C125: 1630 | D125: SERVICIO DE AGUA POTABLE 07 CUBOS. SAYDA QUISPE | E125: GF | F125: 70 | G125: =SUM(F120:F125) -> 370
A126: MARTES | B126: 46070 | C126: 1631 | D126: SERVICIO DE AGUA POTABLE 07 CUBOS. ELOY | E126: GF | F126: 70
B127: 46070 | C127: 1632 | D127: SERVICIO DE AGUA POTABLE 04 CUBOS. ROLANDO | E127: GF | F127: 40
B128: 46070 | C128: 1633 | D128: SERVICIO DE AGUA POTABLE 07 CUBOS. ELOY | E128: GF | F128: 70
B129: 46070 | C129: 1634 | D129: SERVICIO DE AGUA POTABLE 04 CUBOS. ELOY | E129: GF | F129: 120
...

Sheet EGRESOS
B2: EGRESOS DEL MES DE FEBRERO 2026
B3: FECHA | C3: N° REC | D3: DESCRIPCION | E3: COD | F3: MONTO
B4: 46059 | C4: 204 | D4: COMPRA DE 4 SIX PAC DE NEGRITA Y UN PAQUETE DE MEDIO LITRO DE GASEOSA COC COLA PARA PACACHO EN CUYO CUYO | E4: OFI | F4: 179
B5: 46059 | C5: 205 | D5: SE PAGO DE LECTURADO DE LA FECHA 01/02/26 Y 02/2/26. NOEMI MANCILLA VARGAS | E5: LEC | F5: 200
B6: 46063 | C6: 206 | D6: PAGO DE INTERNET. BETSY VILCA TORRES | E6: OFI | F6: 130
B7: 46063 | C7: 207 | D7: COMPRA DE GASOLINA 2.546 GALONES PARA LA CUATRIMOTO. WALTER MAMANI | E7: GS | F7: 42
B8: 46063 | C8: 208 | D8: COMPRA DE SILLON PARA OFICINA. WALTER MAMANI | E8: OFI | F8: 340
B9: 46063 | C9: 209 | D9: COMPRA DE VALVULA FLOTADORA. WALTER MAMANI | E9: OTROS | F9: 250
B10: 46065 | C10: 210 | D10: LECTURADO DE LA FECHA 01/02/26 Y 02/02/26. LUZ USCAMAYTA CHAVEZ | E10: LEC | F10: 200
B11: 46065 | C11: 211 | D11: LECTURADO DE LA FECHA 01/02/26 Y 02/02/26. JAMES TORRES HUASHUAYO | E11: LEC | F11: 200
B12: 46065 | C12: 212 | D12: MANTENIMIENTO DE RED DE AGUA POTABLE 26/01/26 (PEON) PACHAYZA PARTE ALTA. JAMES TORRES HUASHUAYO | E12: MANTENIEMIENTO | F12: 100
B13: 46065 | C13: 213 | D13: MANTENIMIENTO DE RED DE AGUA POTABLE 26/01/26 PACHAYZA PARTE ALTA. JESUS TORRES CHALCO | E13: MANTENIEMIENTO | F13: 200
B14: 46065 | C14: 214 | D14: MANTENIMIENTO DE RED DE AGUA POTABLE 26/01/26 PACHAYZA PARTE ALTA. ALEJANDRO TORRES CHALCO | E14: MANTENIEMIENTO | F14: 200
B15: 46065 | C15: 216 | D15: MANTENIMIENTO DE RED DE AGUA POTABLE 26/01/26 (PEON) PACHAYZA PARTE ALTA. LUISTORRES USCAMAITA | E15: MANTENIEMIENTO | F15: 400
... B37: 46081 | C37: 239 | D37: PAGO DE SUELDO DEL MES DE FEBRERO. BETSY VILCA TORRES | E37: OFI | F37: 1800
D39: TOTAL DE EGRESOS | F39: =SUM(F4:F38) -> 7168.5
B44: EGRESOS DE MOVILIDAD PARA MANTENIMIENTO DEL PETAR Y OTROS. AGOSTO 2025
B45: FECHA | C45: N° REC | D45: DESCRIPCION | E45: COD | F45: MONTO
D60: TOTAL DE EGRESOS | F60: =SUBTOTAL(109,F46:F59) -> 0
D63: COMPRA DE MATERIALES FEBRERO 2026
B64: FECHA | C64: N° | D64: DESCRIPCION | E64: COD | F64: MONTO
D69: TOTAL DE GASTOS | F69: =SUBTOTAL(109,F65:F68) -> 0

Sheet RESUMEN CAJA
D1: RESUMEN DE CAJA CHICA MES FEBRERO 2026
E4: INGRESOS | G4: MONTO
C5: COBRO DE RECIBOS
D6: Chaupi | E6: 94 | F6: 2291 | G6: =SUM(F6:F11) -> 5276.5
D7: Pachayza | E7: 76 | F7: 2237.5
D8: Lucmani | E8: 17 | F8: 451.5
D9: Huaquillo | E9: 15 | F9: 196.5
D10: Ayacucho | E10: 1 | F10: 6.5
D11: Chaupicerca | E11: 5 | F11: 93.5
D12: USUARIOS | E12: =SUM(E6:E11) -> 208
C13: INGRESO VARIABLE (Instalaciones, x construccion, M. O.) | G13: 0
C14: MULTAS (reconexion) | G14: 700
C15: VENTAS DE ACCESORIOS Y TUBOS | G15: 496.3
C16: INGRESO GRIFO DE AGUA | G16: 7860
C17: COPIAS E IMPRESIONES, DOCUMENTOS | G17: 5
F18: INGRESO TOTAL | G18: =SUM(G6:G17) -> 14337.8
E20: EGRESOS | G20: MONTO
C21: ALIMENTACION (directiva, personal y otros) | G21: 315
C22: REMUNERACION (secretaria ) | G22: 1800
C23: HONORARIOS VARIABLES ( X lecturado, personal de apoyo, limpieza buzones desague, otros) | G23: 900
C24: DEVOLUCION POR COMPRA DE VALVULA, ALICATE ,LLAVE, ROTAMARTILO, GUANTES | G24: 583.5
C25: SERVICIOS BASICOS ( internet) | G25: 130
C26: UTILES DE OFICINA Y OTROS (silla de secretaria, cuaderno anillado, millar de recibos ingresos) | G26: 1027
C27: MAQUINARIA (27/01/26) empres tractors maquianria | G27: 558
C28: MANTENIMIENTO DE MATRIZ ( pago a peones) | G28: 1300
C29: TRABAJO DOMINGOS (Cely Torres) | F29: mes febrero dias (01-08-15-22) | G29: 400
C30: MOVILIDAD (Taxi a pachayza para arreglar el agua) | G30: 30
C31: COMBUSTIBLE (gasolina cuatrimoto) | G31: 125
F33: EGRESO TOTAL | G33: =SUM(G21:G31) -> 7168.5
F35: SALDO | G35: =G18-G33 -> 7169.3

Sheet CAJA MAYOR RESUMEN
B2: RESUMEN DE CAJA MAYOR MES ABRIL, MAYO, JUNIO, JULIO, AGOSTO 2025
C5: SALDO AL 31 DE DICIEMBRE | G5: 67908.5
C7: INGRESOS | G7: MONTO
C8: INGRESOS DE CAJA CHICA
C9: MES DE ENERO | F9: 12853.5 | G9: =SUM(F9:F14) -> 24881.1
C10: MES DE FEBRERO | F10: 5632.1
C11: MES DE MARZO | F11: 6395.5
F15: INGRESO TOTAL | G15: =SUM(G9:G14) -> 24881.1
C17: EGRESOS OFICINA ABRIL, MAYO, JUNIO, JULIO, AGOSTO | G17: MONTO
C19: ALIMENTACION (directiva, personal y otros) | G19: 479
C20: REMUNERACION (OPERADOR 03 MESES) | G20: 9000
C21: HONORARIOS VARIABLES ( por trabajos de tentido de maguera Ronal Chanca) | G21: 200
C22: NUEVO SISTEMA DEL CAAPD adelanto | G22: 1100
C23: UTILES DE OFICINA Y OTROS. | G23: 132
C24: CELULAR DE OFICINA compra y comision por deposito. | G24: 495
C25: MOVILIDAD (Taxi a Pachayza para directivos, Taxi por compra de requerimientos en Arequipa) | G25: 60
C26: TANQUES GRIFO DE AGUA (Compra de perforadora (30) , compra de valvula, abrazadera y reducción (305), compra de valvula, tee y enlaces (177), deposito por compra de manguera y otros( 2,500.00), comision por deposito (27), deposito por compra de maguera y otros(2,676.00), comision por deposito(27), deposito para compra de dos tanques( s/21,052.00), comision por deposito de tanques (211), comision por cotizacion(110), compra de manguera (676), comision por deposito (7) | G26: 27878
C27: MANTENIMIENTO CUATROMITO compra de aceite | G27: 64
C28: INAUGURACIÓN DE GRIFO DE AGUA (compra de incencio,cocaruro,kañihua y cinta (24), vino (100), gaseosa,champan, vasos(80), cuetecillos (5). | G28: 209
F29: EGRESO OFICINA TOTAL | G29: =SUM(G19:G28) -> 39617
C33: EGRESOS ABRIL, MAYO, JUNIO, JULIO, AGOSTO FERRETERIA | G33: MONTO
C34: REQUERIMIENTO COMPRA DE ACCESORIOS DE AGUA Y DESAGUE PARA INVENTARIO FERRETERIA | G34: 16757
C35: VIAJES Operador Walter Mamani (Mes de enero pasaje Ispacas-Arequipa para compra de requerimiento de ferreteria (45), pasaje de retorno Arequipa Ispacas (45), ticket de embarque (1.50), Mes de febrero pasaje Ispacas-Arequipa para compra de requerimiento de ferreteria (40), pasaje de retorno Arequipa-Ispacas (40). taxi (80) | G35: 251.5
C36: ALIMENTACIÓN Operador Walter Mamani (Mes de enero almuerzos en Arequipa por compra de requerimiento (30), Mes de febrero almuerzos en Arequipa por compra de requerimiento (30). | G36: 60
C37: EPP PARA EL OPERARIO | G37: 156
C38: TRANSPORTE DE LOS REQUERIMIENTOS DE ACCESORIOS DE AGUA POTABLE Y DESAGUE | G38: 3950
F40: EGRESO FERRETERIA TOTAL | G40: =SUM(G34:G39) -> 21174.5
F43: SALDO | G43: =SUM(G5+G9-G29-G40) -> 31998.1

Sheet MEDI OBS
D1: MEDIDORES OBSEVADOS, SUSPENDIDOS Y CORTADOS
A3: N° CONEXIÓN | B3: N° MEDIDOR | C3: BARRIO | D3: BENEFICIARIO | E3: Dirección | F3: OBSERVACIONES
A4: 000010 | B4: 6659780 | C4: LUCMANI | D4: CHALCO ESCOBAR,REYNA | E4: LUCMANI S/N | F4: CORTADO
A5: 000011 | B5: 6659782 | C5: LUCMANI | D5: CHALCO ESCOBAR,TOMAS | E5: LUCMANI S/N | F5: CORTADO
A6: 000631 | B6: 200039369 | C6: LUCMANI | D6: GUTIERREZ CHALCO RANULFO | E6: CALLE LUCMANI | F6: CORTADO DIC 2024
A7: 000026 | B7: 6578521 | C7: LUCMANI | D7: HUAMANI USCAMAYTA,JAIME F. | E7: LUCMANI S/N | F7: SUPENDIDO
A8: 000048 | B8: 6571643 | C8: LUCMANI | D8: QUISPE ARUTAYPE,ISABEL | E8: LUCMANI S/N | F8: CORTADO
A9: 000324 | B9: 6588594 | C9: CHAUPI | D9: COA AYMARA ,MILAN ESTANISLAO | F9: CORTADO
A10: 000695 | B10: 23015473 | C10: CHAUPI | D10: ESCOBAR DE CASQUINO ROSA | F10: SUPENDIDO
A11: 000459 | B11: 60062463 | C11: CHAUPI | D11: RAMIREZ TORRES ,NERI CRISTINA | E11: AVENIDA AVIACION S/N | F11: CORTADO
A12: 000481 | B12: 60062068 | C12: CHAUPI | D12: TORRES DE RAMIREZ ,ANASTACIA | E12: CALLE SAN SEBASTIAN S/N | F12: CORTADO
A13: 000494 | B13: 6590510 | C13: CHAUPI | D13: TORRES VERA ,IRMA ROSELIA | E13: CALLE 28 DE JULIO S/N | F13: SUPENDIDO
A14: 000518 | B14: 6562282 | C14: CHAUPI | D14: VERA PALOMINO ,FELIPE BENICIO | E14: CALLE 05 DE AGOSTO S/N | F14: CORTADO
A15: 000522 | B15: 60061425 | C15: CHAUPI | D15: VERA TORRES ,ALBERTA ELVIRA | E15: LUCMANI S/N | F15: CORTADO
A16: 000111 | B16: 6659587 | C16: PACHAYZA | D16: CHAUCAYANQUI CHAVEZ ,EDUARDO REY | E16: SANTA ROSA | F16: CORTADO
A17: 000144 | B17: 6590960 | C17: PACHAYZA | D17: GUILLEN MAMANI ,YENI | E17: PAHAYZA | F17: CORTADO
A18: 000602 | B18: 190005348 | C18: PACHAYZA | D18: PALOMINO HUAMANI ,JORGE LEANDRO | E18: PARTE BAJA | F18: SUPENDIDO
A19: 000211 | B19: 6659792 | C19: PACHAYZA | D19: QUISPE CHAUCAYANQUI,SABINA FLORENCIA | E19: PARTE BAJA | F19: OJO
A20: 000223 | B20: 6578357 | C20: PACHAYZA | D20: SET. PACHAYZA " AMIGUITOS DE JESUS" | E20: PARTE BAJA | F20: CORTADO
A21: 000234 | B21: 6593509 | C21: PACHAYZA | D21: TORRES HUASHUAYO JUAN SANTIAGO | E21: PARTE BAJA | F21: CORTADO
A22: 000066 | B22: 6659665 | C22: HUAQUILLO | D22: COA ,ROSA | E22: HUAQUILLO S/N | F22: CONDONADO
A23: 000077 | B23: 6589816 | C23: HUAQUILLO | D23: LOPEZ RAMIEREZ ,PAULINA DONATILA | E23: HUAQUILLO S/N | F23: CONDONADO

Sheet DEUDA
C5: DEUDAS X COBRAR
B7: NOMBRES Y APELLIDOS | C7: DESCRIPCION | D7: IMPORTE
B8: JHON ADALIDTORRES VERA | C8: 01 REDUCCION 6" A 4, 01 CODO DE 45° 6" + ANILLO | D8: 48
B9: GUSTAVO RAUL ZAPANA | C9: 01 CODO 1/2 90°, 01 NIPLE 1/2, 01 CAÑO 1/2, 01 TUBO 1/2 | D9: 60.5
B10: REYNA CASTRO CHAUCAYANQUI | C10: 01 LLAVE DE MEDIDOR 1/2 | D10: 19
B11: FAMILIA SANCHEZ | C11: 02 UNION 1/2, 02 UPR 1/2, 01 UNIVERSAL 1/2, 02 TEFLON + M. O. x X TUBERIA ROTA
C14: TOTAL | D14: =SUM(D8:D13) -> 127.5

Sheet IMPRE
A3: FECHA DE PAGO | B3: N° CONEXIÓN | C3: N° MEDIDOR | D3: BARRIO | E3: BENEFICIARIO | F3: Dirección | G3: MESES | H3: CANT. MES | I3: MONTO
A4: 45664 | B4: 000528 | C4: 6593681 | D4: AYACUCHO | E4: CHAUCAYANQUI ALVAREZ,CLEMENTE | F4: S/N | G4: DICIEMBRE | H4: 1 | I4: 5
A5: 45686 | B5: 000528 | C5: 6593681 | D5: AYACUCHO | E5: CHAUCAYANQUI ALVAREZ,CLEMENTE | F5: S/N | G5: ENERO | H5: 1 | I5: 5
G7: TOTAL | I7: =SUM(I4:I6) -> 10
A9: FECHA DE PAGO | B9: N° CONEXIÓN | C9: N° MEDIDOR | D9: BARRIO | E9: BENEFICIARIO | F9: Dirección | G9: MESES | H9: CANT. MES | I9: MONTO
A10: 45660 | B10: 000712 | C10: 220017320 | D10: CHAUPI | E10: CHUQUIYANQUI DURAN NATY LUZ | G10: AGOSTO-NOVIEMBRE | H10: 4 | I10: 23.5
A11: 45660 | B11: 000339 | C11: 200002898 | D11: CHAUPI | E11: CRUZ MANCILLA ,NOYA SAIDA | F11: AVENIDA AVIACION S/N | G11: OCTUBRE-DICIEMBRE | H11: 3 | I11: 30.5
A12: 45660 | B12: 000340 | C12: 60061410 | D12: CHAUPI | E12: CRUZ MANCILLA ,NOYA SAIDA | F12: AVENIDA AVIACION S/N | G12: OCTUBRE-DICIEMBRE | H12: 3 | I12: 26
A13: 45660 | B13: 000354 | C13: 200005309 | D13: CHAUPI | E13: GUTIERREZ CHALCO ,DARIO | F13: CALLE VIRGEN DE LAS NIEVES S/N | G13: OCTUBRE-DICIEMBRE | H13: 3 | I13: 32.5
A14: 45660 | B14: 000412 | C14: 60062082 | D14: CHAUPI | E14: MANSILLA NAVINTA ,MERCEDES | F14: CALLE 28 DE JULIO S/N | G14: NOVIEMBRE-DICIEMBRE | H14: 2 | I14: 10
A15: 45660 | B15: 000392 | C15: 60062069 | D15: CHAUPI | E15: MANSILLA NAVINTA MERCEDES | F15: PASAJE LA SALLE S/N | G15: NOVIEMBRE-DICIEMBRE | H15: 2 | I15: 18
A16: 45660 | B16: 000332 | C16: 6578564 | D16: CHAUPI | E16: CORIMANYA ARUTAIPE ,ESTEFA AURORA | F16: CALLE 28 DE JULIO S/N | G16: NOVIEMBRE-DICIEMBRE | H16: 2 | I16: 10
A17: 45660 | B17: 000555 | C17: 9090634 | D17: CHAUPI | E17: HUAMANI VERA ,JOSEFA LOURDES | F17: CALLE SAN ISIDRO S/N | G17: DICIEMBRE | H17: 1 | I17: 5
A18: 45660 | B18: 000299 | C18: 6581512 | D18: CHAUPI | E18: CASTRO USCAMITA ,REGINA | F18: CALLE SAN SEBASTIAN S/N | G18: DICIEMBRE | H18: 1 | I18: 11.5
A19: 45660 | B19: 000280 | C19: 60062051 | D19: CHAUPI | E19: ARUTAIPE COA ,CONCEPCION ESTEFA | F19: CALLE 28 DE JULIO S/N | G19: DICIEMBRE | H19: 1 | I19: 5
A20: 45660 | B20: 000390 | C20: 6577445 | D20: CHAUPI | E20: HUAMANI USCAMAITA ,HIPOLITO | F20: CALLE LOS ESTUDIANTES S/N | G20: DICIEMBRE | H20: 1 | I20: 10.5
A21: 45661 | B21: 000577 | C21: 09092524 | D21: CHAUPI | E21: TORRES VERA, ELISABETH | F21: CALLE, LOS ESTUDIANTES S/N | G21: OCTUBRE-DICIEMBRE | H21: 3 | I21: 26.5
A22: 45661 | B22: 000672 | C22: 21003054 | D22: CHAUPI | E22: ANTACHOQUE HERENCIA GENESIS | F22: CALLE 20 DE JULIO | G22: DICIEMBRE | H22: 1 | I22: 5
... A196: 45688 | B196: 000428 | C196: 6558323 | D196: CHAUPI | E196: MORALES FLORES ,TEODORO | F196: CALLE 28 DE JULIO S/N | G196: ENERO | H196: 1 | I196: 5
G198: TOTAL | I198: =SUM(I10:I197) -> 4385.5
A200: FECHA DE PAGO | B200: N° CONEXIÓN | C200: N° MEDIDOR | D200: BARRIO | E200: BENEFICIARIO | F200: Dirección | G200: MESES | H200: CANT. MES | I200: MONTO
A201: 45671 | B201: 000534 | C201: 6593461 | D201: CHAUPICERCA | E201: NEYRA DE USCAMAYTA,MANUELA ANA | F201: CHAUPI CERCA S/N | G201: ENERO | H201: 1 | I201: 5
A202: 45671 | B202: 000536 | C202: 6593726 | D202: CHAUPICERCA | E202: USCAMAYTA NEYRA,DAVID JESUS | F202: CHAUPI CERCA S/N | G202: ENERO | H202: 1 | I202: 5
A203: 45688 | B203: 000704 | C203: 220017513 | D203: CHAUPICERCA | E203: CASTRO USCAMAYTA ELIANA | F203: CHAUPICERCA S/N | G203: NOVIEMBRE-ENERO | H203: 3 | I203: 15
G205: TOTAL | I205: =SUM(I201:I204) -> 25
A207: FECHA DE PAGO | B207: N° CONEXIÓN | C207: N° MEDIDOR | D207: BARRIO | E207: BENEFICIARIO | F207: Dirección | G207: MESES | H207: CANT. MES | I207: MONTO
A208: 45660 | B208: 000074 | C208: 6593585 | D208: HUAQUILLO | E208: HUAMANI VERA ,JOSEFA LOURDES | F208: HUAQUILLO S/N | G208: DICIEMBRE | H208: 1 | I208: 8.5
A209: 45663 | B209: 000671 | C209: 21003047 | D209: HUAQUILLO | E209: GUTIERREZ CASTRO CLENY | F209: SECTOR AYNANI | G209: NOVIEMBRE-DICIEMBRE | H209: 2 | I209: 11.5
A210: 45664 | B210: 000073 | C210: 23015476 | D210: HUAQUILLO | E210: HUAMANI MONTALVO,ROSARIO RUPERTA | F210: HUAQUILLO S/N | G210: DICIEMBRE | H210: 1 | I210: 5
A211: 45666 | B211: 000067 | C211: 6589707 | D211: HUAQUILLO | E211: CORIMANYA CHAVEZ,SERAPIO | F211: HUAQUILLO S/N | G211: DICIEMBRE | H211: 1 | I211: 8.5
A212: 45666 | B212: 000061 | C212: 21003055 | D212: HUAQUILLO | E212: CHALCO HUAMANI,SAIDA | F212: HUAQUILLO S/N | G212: DICIEMBRE | H212: 1 | I212: 5
A213: 45668 | B213: 000080 | C213: 6582208 | D213: HUAQUILLO | E213: MONTALVO TORRES,JUAN FREDY | F213: HUAQUILLO S/N | G213: DICIEMBRE-ENERO | H213: 2 | I213: 10
A214: 45668 | B214: 000085 | C214: 6588057 | D214: HUAQUILLO | E214: TORRES CHALCO,CRISTINA | F214: HUAQUILLO S/N | G214: DICIEMBRE-ENERO | H214: 2 | I214: 15
A215: 45668 | B215: 000069 | C215: 6589759 | D215: HUAQUILLO | E215: GONZALES SOLOISOLO,JUAN | F215: HUAQUILLO S/N | G215: ENERO | H215: 1 | I215: 5
A216: 45671 | B216: 000076 | C216: 6563973 | D216: HUAQUILLO | E216: LOPEZ ,LUCIO JULIAN | F216: HUAQUILLO S/N | G216: ENERO | H216: 1 | I216: 5
A217: 45672 | B217: 000072 | C217: 6563990 | D217: HUAQUILLO | E217: HUAMANI MONTALVO,ISAURO MANUEL | F217: HUAQUILLO S/N | G217: DICIEMBRE-ENERO | H217: 2 | I217: 10
A218: 45672 | B218: 000075 | C218: 6563957 | D218: HUAQUILLO | E218: HUAMANI VERA ,JUSTINA IMELDA | F218: HUAQUILLO S/N | G218: ENERO | H218: 1 | I218: 5
A219: 45672 | B219: 000060 | C219: 220017574 | D219: HUAQUILLO | E219: CHALCO GONZALES,FILOMENA GRIMANESA | F219: HUAQUILLO S/N | G219: ENERO | H219: 1 | I219: 5
... A233: 45688 | B233: 000064 | C233: 61319114 | D233: HUAQUILLO | E233: CHAUCAYANQUI HUAMANI RONAL ALEXANDER | F233: HUAQUILLO S/N | G233: DICIEMBRE-ENERO | H233: 2 | I233: 18
G235: TOTAL | I235: =SUM(I208:I234) -> 247
A237: FECHA DE PAGO | B237: N° CONEXIÓN | C237: N° MEDIDOR | D237: BARRIO | E237: BENEFICIARIO | F237: Dirección | G237: MESES | H237: CANT. MES | I237: MONTO
A238: 45661 | B238: 000013 | C238: 21003043 | D238: LUCMANI | E238: CHUQUIYANQUI HUAMANI,ETELVINA VILMA | F238: LUCMANI S/N | G238: DICIEMBRE | H238: 1 | I238: 13.5
A239: 45661 | B239: 000684 | C239: 200031254 | D239: LUCMANI | E239: ESCOBAR CHUQUIYANQUI LISBET NATALI | G239: DICIEMBRE | H239: 1 | I239: 5
A240: 45661 | B240: 000036 | C240: 200039366 | D240: LUCMANI | E240: MONTALVO ARUTAYPE,MARIA FELICIANA | F240: LUCMANI S/N | G240: DICIEMBRE | H240: 1 | I240: 26.5
A241: 45661 | B241: 000034 | C241: 6593296 | D241: LUCMANI | E241: MANCILLA CASTRO,MIGUEL | F241: LUCMANI S/N | G241: DICIEMBRE | H241: 1 | I241: 5
A242: 45663 | B242: 000035 | C242: 6585587 | D242: LUCMANI | E242: ILATAYPE MANSILLA ABEL MARCO | F242: LUCMANI S/N | G242: SETIEMBRE | H242: 1 | I242: 23.5
A243: 45663 | B243: 000027 | C243: 6587948 | D243: LUCMANI | E243: HUAMANI USCAMAYTA,MELITON GABRIEL | F243: LUCMANI S/N | G243: SETIEMBRE-DICIEMBRE | H243: 4 | I243: 29
A244: 45663 | B244: 000035 | C244: 6585587 | D244: LUCMANI | E244: ILATAYPE MANSILLA ABEL MARCO | F244: LUCMANI S/N | G244: OCTUBRE | H244: 1 | I244: 27.5
A245: 45663 | B245: 000049 | C245: 6591593 | D245: LUCMANI | E245: RAMIREZ HUAMANI,MARIA LETICIA | F245: LUCMANI S/N | G245: OCTUBRE-DICIEMBRE | H245: 3 | I245: 15
A246: 45663 | B246: 000035 | C246: 6585587 | D246: LUCMANI | E246: ILATAYPE MANSILLA ABEL MARCO | F246: LUCMANI S/N | G246: NOVIEMBRE | H246: 1 | I246: 37.5
A247: 45663 | B247: 000669 | C247: 21003048 | D247: LUCMANI | E247: CHAVEZ ANTACHOQUE HENRRY | F247: SECTOR JENCHO | G247: NOVIEMBRE-DICIEMBRE | H247: 2 | I247: 40
A248: 45663 | B248: 000035 | C248: 6585587 | D248: LUCMANI | E248: ILATAYPE MANSILLA ABEL MARCO | F248: LUCMANI S/N | G248: DICIEMBRE | H248: 1 | I248: 49.5
A249: 45663 | B249: 000595 | C249: 19003886 | D249: LUCMANI | E249: NEYRA HUAMANI, BETTY PETRONILA | F249: LUCMANI S/N | G249: DICIEMBRE | H249: 1 | I249: 10.5
A250: 45663 | B250: 000003 | C250: 21003044 | D250: LUCMANI | E250: ANTACHOQUE VERA,DAVID TOMAS | F250: LUCMANI S/N | G250: DICIEMBRE | H250: 1 | I250: 13.5
A251: 45664 | B251: 000020 | C251: 6579093 | D251: LUCMANI | E251: HUAMANI CANDELARIA | F251: LUCMANI S/N | G251: SETIEMBRE | H251: 1 | I251: 30.5
A252: 45664 | B252: 000020 | C252: 6579093 | D252: LUCMANI | E252: HUAMANI CANDELARIA | F252: LUCMANI S/N | G252: OCTUBRE | H252: 1 | I252: 36.5
... A288: 45688 | B288: 000595 | C288: 19003886 | D288: LUCMANI | E288: NEYRA HUAMANI, BETTY PETRONILA | F288: LUCMANI S/N | G288: ENERO | H288: 1 | I288: 10.5
G290: TOTAL | I290: =SUM(I238:I289) -> 1734.9
A292: FECHA DE PAGO | B292: N° CONEXIÓN | C292: N° MEDIDOR | D292: BARRIO | E292: BENEFICIARIO | F292: Dirección | G292: MESES | H292: CANT. MES | I292: MONTO
A293: 45660 | B293: 000728 | C293: 200031258 | D293: PACHAYZA | E293: VERA PALOMINO, REMIGIO MANUEL | F293: SECTOR PACHAYZA - PARTE ALTA | G293: OCTUBRE-DICIEMBRE | H293: 3 | I293: 188.5
A294: 45660 | B294: 000256 | C294: 6570764 | D294: PACHAYZA | E294: URDAY TORRES SILVIA VITALIA | F294: SECTOR PACHAYZA- PARTE ALTA | G294: OCTUBRE-DICIEMBRE | H294: 3 | I294: 40.5
A295: 45660 | B295: 000664 | C295: 200011838 | D295: PACHAYZA | E295: HUAMANI URDAY VICTOR VICENTE | F295: SECTOR PACHAYZA - PARTE BAJA | G295: NOVIEMBRE-DICIEMBRE | H295: 2 | I295: 11.5
A296: 45660 | B296: 000198 | C296: 6586849 | D296: PACHAYZA | E296: MOTTA NEYRA,ABELINA AGEDA | F296: SECTOR PACHAYZA - PUCRO | G296: NOVIEMBRE-DICIEMBRE | H296: 2 | I296: 25
A297: 45660 | B297: 000208 | C297: 9091738 | D297: PACHAYZA | E297: PALOMINO NEYRA ,MAGNO ELISEO | F297: SECTOR PACHAYZA - PARTE ALTA | G297: DICIEMBRE | H297: 1 | I297: 16.5
A298: 45660 | B298: 000191 | C298: 6573820 | D298: PACHAYZA | E298: MONTALVO VERA , LISMINA SUSANA | F298: SECTOR PACHAYZA - PARTE BAJA | G298: DICIEMBRE | H298: 1 | I298: 5
A299: 45660 | B299: 000192 | C299: 6586742 | D299: PACHAYZA | E299: MONTALVO VERA ROY EDSON | F299: SECTOR PACHAYZA - PARTE BAJA | G299: DICIEMBRE | H299: 1 | I299: 5
A300: 45660 | B300: 000596 | C300: 19003881 | D300: PACHAYZA | E300: MONTALVO HUAMANI VALENTIN ABELINO | F300: PACHAYZA-PARTE BAJA | G300: DICIEMBRE | H300: 1 | I300: 5
A301: 45660 | B301: 000200 | C301: 6586927 | D301: PACHAYZA | E301: NAVINTA MONTALVO JESUS EFRAIN | F301: SECTOR PACHAYZA - PARTE BAJA | G301: DICIEMBRE | H301: 1 | I301: 5
A302: 45661 | B302: 000157 | C302: 6584846 | D302: PACHAYZA | E302: HUAMANI ILATAYPE,ATENEA DIVINIDAD | F302: SECTOR PACHAYZA - PARTE BAJA | G302: OCTUBRE-DICIEMBRE | H302: 3 | I302: 16.5
A303: 45663 | B303: 000700 | C303: 21130893 | D303: PACHAYZA | E303: CRUZ CASTRO WILVER | F303: PACHAYZA-TARAPATA | G303: ENERO-DICIEMBRE | H303: 12 | I303: 60
A304: 45663 | B304: 000584 | C304: 09091150 | D304: PACHAYZA | E304: LOPEZ RAMIREZ, FRANCISCA CRISTINA | F304: TARAPATA S/N | G304: JULIO-NOVIEMBRE | H304: 5 | I304: 100
... A464: 45688 | B464: 000133 | C464: 6584533 | D464: PACHAYZA | E464: CORIMANYA HUAMANI ,JUAN | F464: SECTOR PACHAYZA - PARTE BAJA | G464: ENERO | H464: 1 | I464: 31.5
G466: TOTAL | I466: =SUM(I293:I465) -> 4831.5
G468: SUMA TOTAL | I468: =I466+I290+I235+I205+I198+I7 -> 11233.9

Sheet enero
B3: 000527 | C3: 2001887 | D3: AYACUCHO | E3: CHAUCAYANQUI ALVAREZ,CARLOS ALEJO | F3: S/N
B4: 000528 | C4: 6593681 | D4: AYACUCHO | E4: CHAUCAYANQUI ALVAREZ,CLEMENTE | F4: S/N
B5: 000529 | C5: 220014925 | D5: AYACUCHO | E5: SURCO VILLENA,SUSY BETTY | F5: S/N
B6: 000530 | C6: 6563926 | D6: AYACUCHO | E6: TORRES COA,CILA CAMILA | F6: S/N
B7: 000531 | C7: 6563939 | D7: AYACUCHO | E7: TORRES HUAMANI,AMELIA BENITA | F7: S/N
B8: 000704 | C8: 220017513 | D8: CHAUPICERCA | E8: CASTRO USCAMAYTA ELIANA | F8: CHAUPICERCA S/N
B9: 000534 | C9: 6593461 | D9: CHAUPICERCA | E9: NEYRA DE USCAMAYTA,MANUELA ANA | F9: CHAUPI CERCA S/N
B10: 000533 | C10: 6593433 | D10: CHAUPICERCA | E10: ROMERO CHAUCAYANQUI JUSTO MARCELO | F10: CHAUPI CERCA S/N
B11: 000535 | C11: 6563916 | D11: CHAUPICERCA | E11: USCAMAYTA ALCA ,CILA | F11: CHAUPI CERCA S/N
B12: 000536 | C12: 6593726 | D12: CHAUPICERCA | E12: USCAMAYTA NEYRA,DAVID JESUS | F12: CHAUPI CERCA S/N
B13: 000537 | C13: 6593657 | D13: CHAUPICERCA | E13: VERA REVILLA ,MANUEL | F13: CHAUPI CERCA S/N
B14: 000796 | C14: 22392996 | D14: LUCMANI | E14: ALVAREZ CHUQUIYANQUI, MARIBEL NAYELI | F14: AUCAYPATA S/N
... B754: 000272 | C754: 09090152 | D754: PACHAYZA | E754: YLATAIPE VERA,FIDELA | F754: SECTOR PACHAYZA - PARTE BAJA

Sheet corte enero
C1: USUARIOS EN CORTE
C3: CONEXIÓN | D3: N° MEDIDOR | E3: BARRIO | F3: BENEFICIARIO | G3: DIRECCIÓN | H3: OBSERVACIONES
C4: 000704 | D4: 220017513 | E4: CHAUPICERCA | F4: CASTRO USCAMAYTA ELIANA | G4: CHAUPICERCA S/N | H4: nov-dic-ene / S/15.00 corte
C5: 000002 | D5: 6659764 | E5: LUCMANI | F5: ANTACHOQUE MOTA,JUANA HILDA | G5: LUCMANI S/N | H5: nov-dic-ene / S/15.00 corte
C6: 000690 | D6: 2392656 | E6: LUCMANI | F6: CABRERA CARPIO JESUS VICTORIANO | G6: LUCMANI S/N | H6: nov-dic-ene / S/15.00 corte
C7: 000669 | D7: 21003048 | E7: LUCMANI | F7: CHAVEZ ANTACHOQUE HENRRY | G7: SECTOR JENCHO | H7: oct-nov-dic-ene / S/109.00 corte
C8: 000691 | D8: 21000863 | E8: LUCMANI | F8: GUTIERREZ CHALCO REYNALDO ROBERTO | G8: LUCMANI S/N | H8: set-oct-nov-dic-ene/ S/25.00 corte
C9: 000620 | D9: 2001885 | E9: LUCMANI | F9: MONTALVO NEIRA MARTINA DEFILIA | G9: LUCMANI S/N | H9: nov-dic-ene / S/17.50 corte
C10: 000047 | D10: 6660664 | E10: LUCMANI | F10: PALOMINO NEYRA,JUSTINA LUZ | G10: LUCMANI S/N | H10: oct-nov-dic-ene / S/51.00 corte
C11: 000024 | D11: 6572073 | E11: LUCMANI | F11: QUISPE HUAMANI,CLEMENTE EMILIO | G11: LUCMANI S/N | H11: nov-dic-ene / S/15.00 corte
C12: 000049 | D12: 6591593 | E12: LUCMANI | F12: RAMIREZ HUAMANI,MARIA LETICIA | G12: LUCMANI S/N | H12: set-oct-nov-dic-ene/ S/25.00 corte
C13: 000498 | D13: 60062505 | E13: CHAUPI | F13: ALFARO NEYRA DE CHUQUIYANQUI LUCIA POMPEYA | G13: PASAJE SAN ISIDRO S/N | H13: oct-nov-dic-ene / S/20.00 corte
C14: 000467 | D14: 6581492 | E14: CHAUPI | F14: ARUTAYPE CORIMANYA GLENY | G14: LUCMANI S/N | H14: nov-dic-ene / S/22.50 corte
... C97: 000773 | D97: 22392997 | E97: PACHAYZA | F97: VILCA MAMANI ,DELIA | G97: PACHAYZA - PUCRO | H97: nov-dic-ene / S/87.50 corte
F100: usuarios de construccion por uso de agua
C102: CONEXIÓN | D102: N° MEDIDOR | E102: BARRIO | F102: BENEFICIARIO | G102: DIRECCIÓN | H102: OBSERVACIONES
C103: 000043 | D103: 6578514 | E103: LUCMANI | F103: NEIRA DE ROMERO,EDUARDA FERNANDINA | G103: LUCMANI S/N | H103: SET-OCTUBRE- DICIEMBRE 2025
C104: 000694 | D104: 21130885 | E104: CHAUPI | F104: CHAVEZ TORRES CASTOR MILTON | G104: CALLE 5 DE AGOSTO S/N | H104: ENERO 2025
C105: 000340 | D105: 60061410 | E105: CHAUPI | F105: CRUZ MANCILLA ,NOYA SAIDA | G105: AVENIDA AVIACION S/N | H105: ENERO 2025
C106: 000605 | D106: 190005360 | E106: CHAUPI | F106: HUAMANI ESCOBAR AYNETH | G106: CALLE 28 DE JULIO | H106: ENERO 2025
C107: 000363 | D107: 23022175 | E107: CHAUPI | F107: HUAMANI ALVAREZ ,NELIDA LUZ | G107: LUCMANI S/N | H107: SETIEMBRE- OCTUBRE 2025
C108: 000586 | D108: 09093268 | E108: CHAUPI | F108: ANTACHOQUE ESCOBAR, FANY KELIDA | G108: LUCMANI S/N | H108: JUNIO - JULIO 2025
C109: 000290 | D109: 6573791 | E109: CHAUPI | F109: LLERENA MONTALVO DE CARPIO MAXIMILIANA | G109: CALLE LOS ESTUDIANTES S/N | H109: ENERO Y JUNIO 2025
C110: 000705 | D110: 23013263 | E110: CHAUPI | F110: MANCILLA VERA SUSY MARIBEL | G110: CALLE 5 DE AGOSTO S/N | H110: ENERO 2025
C111: 000508 | D111: 60062489 | E111: CHAUPI | F111: USCAMAYTA HUAMANI ,JESUS | G111: CALLE JUAN USCAMAYTA S/N | H111: ENERO 2025
C112: 000558 | D112: 10786 | E112: CHAUPI | F112: HUAMANI HUAMANI,JANETT ANASTACIA | G112: CALLE EL OLVIDO S/N | H112: OCTUBRE-NOVIEMBRE 2025
C113: 000300 | D113: 60061426 | E113: CHAUPI | F113: CATEDRAL DE LA COMUNIDAD DE ISPACAS | G113: CALLE CUYO CUYO S/N | H113: ABRIL-MAYO 2025
... C144: 000190 | D144: 6587891 | E144: PACHAYZA | F144: MONTALVO REVILLA,ESTANISLAO FLAVIO | G144: SECTOR PACHAYZA - TARAPATA | H144: OCTUBRE 2025
C145: 000128 | D145: 6571035 | E145: PACHAYZA | F145: COA HUAHUACONDO ,JUAN CARLOS | G145: SECTOR PACHAYZA - PARTE ALTA | H145: DICIEMBRE 2025 | I145: .
C146: 000791 | D146: 20520454 | E146: PACHAYZA | F146: NEYRA RAMIREZ,WASHINTON LUIGI | G146: PACHAYZA-PUCRO S/N | H146: DICIEMBRE 2025 | I146: .
C147: 000362 | D147: 60061429 | E147: CHAUPI | F147: USCAMAYTA HUAMANI, EDWIN ALEJANDRO | G147: CALLE JUAN USCAMAYTA S/N | H147: DICIEMBRE 2025
C148: 000729 | D148: 220017506 | E148: CHAUPI | F148: USCAMAYTA MONTALVO, MARITA BERNA | G148: CALLE JUAN USCAMAYTA S/N | H148: DICIEMBRE 2025
C149: 000007 | D149: 23015480 | E149: LUCMANI | F149: CABRERA CHAVEZ,ASISCLO | G149: LUCMANI S/N | H149: DICIEMBRE 2025
C150: 000317 | D150: 60062519 | E150: CHAUPI | F150: CHUQUIYANQUI ALFARO ,JORGE LUIS | G150: PASAJE SAN ISIDRO S/N | H150: DICIEMBRE 2025
C151: 000613 | D151: 20102270 | E151: PACHAYZA | F151: CHALCO ESCOBAR ANGELITA CONSTANZA | G151: PACHAYZA-PARTE BAJA | H151: DICIEMBRE 2025 | I151: .
C152: 000259 | D152: 6587730 | E152: PACHAYZA | F152: RAMIREZ USCAMAYTA, JAIME MAURO | G152: SECTOR PACHAYZA -TARAPATA | H152: AGOSTO 2025
E155: USUARIOS CON MEDIDORES ENTERRADOS, SEGUIMIENTO, MALOGRADOS, LIMPIAR MEDIDOR,CAMBIO DE MEDIDOR
C157: CONEXIÓN | D157: N° MEDIDOR | E157: BARRIO | F157: BENEFICIARIO | G157: DIRECCIÓN | H157: OBSERVACIONES
C158: 000741 | D158: 22115452 | E158: CHAUPI | F158: CHALCO MONTALVO, GLORIA VICTORIA | G158: CALLE VIRGEN DE LAS NIEVES S/N | H158: MEDIDOR ENTERRADO
C159: 000654 | D159: 200005319 | E159: CHAUPI | F159: CHALCO MONTALVO, YOBANA DEBORA | G159: CALLE 5 DE AGOSTO | H159: MEDIDOR ENTERRADO
C160: 000770 | D160: 22393000 | E160: CHAUPI | F160: CORTES ZURITA, JUAN FRANSISCO | G160: LUCMANI S/N | H160: MEDIDOR ENTERRADO
C161: 000419 | D161: 6558327 | E161: CHAUPI | F161: MONTALVO HUAMANI ,JANO JUAN | G161: CALLE SAN SEBASTIAN S/N | H161: REGISTRO DE DESAGUE MALOGRADO | L161: LEYENDA | N161: (LIMPIAR MEDIDOR)
C162: 000363 | D162: 23022175 | E162: CHAUPI | F162: HUAMANI ALVAREZ ,NELIDA LUZ | G162: LUCMANI S/N | H162: MEDIDOR ENTERRADO | N162: (MEDIDOR ENTERRADO)
C163: 000508 | D163: 60062489 | E163: CHAUPI | F163: USCAMAYTA HUAMANI ,JESUS | G163: CALLE JUAN USCAMAYTA S/N | H163: MEDIDOR ENTERRADO | N163: (CAMBIAR MEDIDOR)(MEDIDOR MALOGRADO)
C164: 000729 | D164: 220017506 | E164: CHAUPI | F164: USCAMAYTA MONTALVO, MARITA BERNA | G164: CALLE JUAN USCAMAYTA S/N | H164: MEDIDOR ENTERRADO | N164: (MEDIDOR DENTRO DE LA CASA)
C165: 000754 | D165: 22393040 | E165: CHAUPI | F165: HUAMANI , LUZ HAYDE | G165: PSJ VIRGEN DE LAS NIEVES | H165: MEDIDOR ENTERRADO | N165: ( DESAGUE MALOGRADO)
C166: 000638 | D166: 200002890 | E166: CHAUPI | F166: TILLCA MENDOZA YANED | G166: CALLE AVIACION S/N | H166: MEDIDOR ENTERRADO | N166: ( SIN MEDIDOR)
C167: 000590 | D167: 200031257 | E167: CHAUPI | F167: USCAMAYTA HUAMANI, YEDY | G167: CALLE SAN SEBASTIAN S/N | H167: MEDIDOR ENTERRADO
C168: 000620 | D168: 2001885 | E168: LUCMANI | F168: MONTALVO NEIRA MARTINA DEFILIA | G168: LUCMANI S/N | H168: MEDIDOR ENTERRADO
C169: 000133 | D169: 6584533 | E169: PACHAYZA | F169: CORIMANYA HUAMANI ,JUAN | G169: SECTOR PACHAYZA - PARTE BAJA | H169: MEDIDOR ENTERRADO
C170: 000204 | D170: 6585730 | E170: PACHAYZA | F170: PALOMINO HUAMANI VIUDA DE HUAMANI JUANA | G170: PACHAYZA | H170: CAMBIAR MEDIDOR(MEDIDOR ENTERRADO) | I170: .
C171: 000635 | D171: 200039367 | E171: PACHAYZA | F171: GUZMAN TORRES ANYELA LETHY | G171: PACHAYZA - ALTA | H171: MEDIDOR ENTERRADO
C172: 000254 | D172: 6585590 | E172: PACHAYZA | F172: URDAY TORRES ,JESICA NANCY | G172: SECTOR PACHAYZA -PARTE ALTA | H172: MEDIDOR DENTRO DE LA CASA
C173: 000626 | D173: 2001834 | E173: PACHAYZA | F173: GRUPO JAMPRA S.A.C | G173: PACHAYZA-PARTE BAJA | H173: LIMPIAR MEDIDOR
C174: 000648 | D174: 200011827 | E174: PACHAYZA | F174: HUACPI HUAMANI ,DANIA UDELIZ | G174: SECTOR PACHAYZA - PUCRO | H174: CAMBIAR MEDIDOR | I174: . | L174: LEYENDA | N174: (LIMPIAR MEDIDOR)
C175: 000178 | D175: 6593627 | E175: PACHAYZA | F175: MANSILLA CASTRO, EULOGIA LEANDRA | G175: SECTOR PACHAYZA - HUAYCHA | H175: MEDIDOR ENTERRADO | N175: (MEDIDOR ENTERRADO)
C176: 000168 | D176: 6585742 | E176: PACHAYZA | F176: HUAMANI YLATAIPE ,WILSON CHARLES | G176: SECTOR PACHAYZA - PUCRO | H176: MEDIDOR ENTERRADO | N176: (CAMBIAR MEDIDOR)(MEDIDOR MALOGRADO)
C177: 000129 | D177: 240000344 | E177: PACHAYZA | F177: TORRES VERA LEONARDO SALOMON | G177: SECTOR PACHAYZA - PARTE ALTA | H177: MEDIDOR ENTERRADO | N177: (MEDIDOR DENTRO DE LA CASA)
C178: 000128 | D178: 6571035 | E178: PACHAYZA | F178: COA HUAHUACONDO ,JUAN CARLOS | G178: SECTOR PACHAYZA - PARTE ALTA | H178: MEDIDOR ENTERRADO | I178: . | N178: ( DESAGUE MALOGRADO)
C179: 000134 | D179: 6564307 | E179: PACHAYZA | F179: CORIMANYA HUAMANI REYNA PINA | G179: SECTOR PACHAYZA - PARTE ALTA | H179: LIMPIAR MEDIDOR | I179: . | N179: ( SIN MEDIDOR)
C180: 000575 | D180: 09091780 | E180: PACHAYZA | F180: CHAUCAYANQUI GUTIERREZ, JUAN PERCY | G180: TARAPATA | H180: LIMPIAR MEDIDOR | I180: .
C181: 000626 | D181: 2001834 | E181: PACHAYZA | F181: GRUPO JAMPRA S.A.C | G181: PACHAYZA-PARTE BAJA | H181: LIMPIAR MEDIDOR | I181: .
C182: 000621 | D182: 20102242 | E182: PACHAYZA | F182: MONTALVO HUAMANI LINDON | G182: PACHAYZA-PARTE BAJA | H182: MEDIDOR DENTRO DE LA CASA | I182: .
C183: 000185 | D183: 6586638 | E183: PACHAYZA | F183: MONTALVO HUAMANI VALENTIN ABELINO | G183: SECTOR PACHAYZA - PARTE BAJA | H183: MEDIDOR ENTERRADO | I183: .
C184: 000191 | D184: 6573820 | E184: PACHAYZA | F184: MONTALVO VERA , LISMINA SUSANA | G184: SECTOR PACHAYZA - PARTE BAJA | H184: MEDIDOR ENTERRADO | I184: .
C185: 000192 | D185: 6586742 | E185: PACHAYZA | F185: MONTALVO VERA ROY EDSON | G185: SECTOR PACHAYZA - PARTE BAJA | H185: MEDIDOR ENTERRADO | I185: .
C186: 000702 | D186: 003386 | E186: PACHAYZA | F186: MONTALVO VERA URIEL | G186: PACHAYZA-PARTE BAJA | H186: MEDIDOR ENTERRADO | I186: .
C187: 000204 | D187: 6585730 | E187: PACHAYZA | F187: PALOMINO HUAMANI VIUDA DE HUAMANI JUANA | G187: PACHAYZA | H187: MEDIDOR ENTERRADO | I187: .
C188: 000243 | D188: 6578555 | E188: PACHAYZA | F188: TORRES VERA ,ELVER TITO | G188: SECTOR PACHAYZA - PARTE ALTA | H188: MEDIDOR ENTERRADO | I188: .
C189: 000295 | D189: 6590154 | E189: CHAUPI | F189: CASTRO HUAMANI ,LEONCIO | G189: CHAUPI | H189: MEDIDOR MALOGRADO | I189: .
C190: 000256 | D190: 6570764 | E190: PACHAYZA | F190: URDAY TORRES SILVIA VITALIA | G190: SECTOR PACHAYZA- PARTE ALTA | H190: MEDIDOR MALOGRADO | I190: .
C191: 000385 | D191: 6573788 | E191: CHAUPI | F191: HUAMANI RAMIREZ ,SANDRO | G191: CALLE 05 DE AGOSTO S/N | H191: CAMBIAR MEDIDOR | I191: .
... C197: 000780 | D197: 22392865 | E197: PACHAYZA | F197: TORRES VERA, LIBIA MARLENY | G197: SECTOR PACHAYZA - AWINTA S/N | H197: MEDIDOR ENTERRADO | I197: .
C198: 000558 | D198: 10786 | E198: CHAUPI | F198: HUAMANI HUAMANI,JANETT ANASTACIA | G198: CALLE EL OLVIDO S/N | H198: MEDIDOR MALOGRADO-MEDIDOR ENTERRADO
C199: 000681 | D199: 21006532 | E199: CHAUPI | F199: MONTALVO HUAMANI GIANELLA DIANA | G199: CALLE 28 DE JULIO | H199: MEDIDOR ENTERRADO
C200: 000439 | D200: 20017511 | E200: CHAUPI | F200: NEIRA LOPEZ ,JULIAN TEODORO | G200: LUCMANI S/N | H200: MEDIDOR ENTERRADO
C201: 000246 | D201: 6585536 | E201: PACHAYZA | F201: TORRES VERA,VICTOR GAMALIEL | G201: SECTOR PACHAYZA - PARTE BAJA | H201: MEDIDOR ENTERRADO
