Workbook

Sheet RECIBOS
A3: FECHA DE PAGO | B3: N° CONEXIÓN | C3: N° MEDIDOR | D3: BARRIO | E3: BENEFICIARIO | F3: Dirección | G3: lect. Ant | I3: lect. Actual | J3: MESES | K3: CANT. MES | L3: MONTO | M3: TOTAL - DIA
A4: 46174 | B4: 000779 | C4: 20209138 | D4: CHAUPI | E4: NEYRA SIVINCHA, NORMA YSABEL | F4: LUCMANI S/N | J4: abril-mayo | K4: 2 | L4: 32
A5: 46174 | B5: 000079 | C5: 6658956 | D5: HUAQUILLO | E5: NEYRA SIVINCHA, NORMA YSABEL | F5: HUAQUILLO S/N | J5: abril-mayo | K5: 2 | L5: 28 | P5: 000527 | Q5: 2001887 | R5: AYACUCHO | S5: CHAUCAYANQUI ALVAREZ,CARLOS ALEJO | T5: S/N
A6: 46174 | B6: 000607 | C6: 190005356 | D6: PACHAYZA | E6: TORRES CABRERA MERY | F6: CALLE SOLEDAD | J6: marzo-abril-mayo | K6: 3 | L6: 92 | P6: 000528 | Q6: 6593681 | R6: AYACUCHO | S6: CHAUCAYANQUI ALVAREZ,CLEMENTE | T6: S/N
A7: 46174 | B7: 000171 | C7: 6585525 | D7: PACHAYZA | E7: I.E. ANDRES AVELINO CACERES | F7: SECTOR PACHAYZA - PARTE ALTA | J7: febrero/mayo | K7: 4 | L7: 99 | P7: 000529 | Q7: 220014925 | R7: AYACUCHO | S7: SURCO VILLENA,SUSY BETTY | T7: S/N
A8: 46174 | B8: 000172 | C8: 6578765 | D8: PACHAYZA | E8: I.E. ANDRES AVELINO CACERES | F8: SECTOR PACHAYZA-PARTE ALTA | J8: febrero/mayo | K8: 4 | L8: 65 | P8: 000530 | Q8: 6563926 | R8: AYACUCHO | S8: TORRES COA,CILA CAMILA | T8: S/N
A9: 46174 | B9: 000696 | C9: 21130896 | D9: PACHAYZA | E9: HUAMANI CHALCO GENOVEVA ESTELITA | F9: SECTOR PUCRO | J9: abril-mayo | K9: 2 | L9: 18 | P9: 000531 | Q9: 6563939 | R9: AYACUCHO | S9: TORRES HUAMANI,AMELIA BENITA | T9: S/N
A10: 46174 | B10: 000199 | C10: 101745489 | D10: PACHAYZA | E10: NAVINTA CORIMANYA, VICO NICOLAS | F10: SECTOR PACHAYZA - PARTE ALTA | J10: mayo | K10: 1 | L10: 5 | P10: 000704 | Q10: 220017513 | R10: CHAUPICERCA | S10: CASTRO USCAMAYTA ELIANA | T10: CHAUPICERCA S/N
A11: 46174 | B11: 000236 | C11: 135304 | D11: PACHAYZA | E11: TORRES MONTALVO ,SONIA YENI | F11: SECTOR PACHAYZA - PARTE ALTA | J11: mayo | K11: 1 | L11: 10.5 | P11: 000534 | Q11: 6593461 | R11: CHAUPICERCA | S11: NEYRA DE USCAMAYTA,MANUELA ANA | T11: CHAUPI CERCA S/N
A12: 46174 | B12: 000305 | C12: 6577360 | D12: CHAUPI | E12: CHALCO TORRES ,JUANA | F12: PASAJE EL OLVIDO S/N | J12: abril-mayo | K12: 2 | L12: 10 | P12: 000533 | Q12: 6593433 | R12: CHAUPICERCA | S12: ROMERO CHAUCAYANQUI JUSTO MARCELO | T12: CHAUPI CERCA S/N
A13: 46174 | B13: 000453 | C13: 60061357 | D13: CHAUPI | E13: RAMIREZ CHAUCAYANQUI ,SILVIO HUILE | F13: CALLE 28 DE JULIO S/N | J13: abril-mayo | K13: 2 | L13: 10 | P13: 000535 | Q13: 6563916 | R13: CHAUPICERCA | S13: USCAMAYTA ALCA ,CILA | T13: CHAUPI CERCA S/N
A14: 46174 | B14: 000720 | C14: 220017512 | D14: PACHAYZA | E14: RAMIREZ CHAUCAYANQUI, ROSA ALEJANDRINA | F14: PACHAYZA-PARTE ALTA | J14: mayo | K14: 1 | L14: 5 | P14: 000536 | Q14: 6593726 | R14: CHAUPICERCA | S14: USCAMAYTA NEYRA,DAVID JESUS | T14: CHAUPI CERCA S/N
A15: 46174 | B15: 000220 | C15: 6586825 | D15: PACHAYZA | E15: RAMIREZ CHAUCAYANQUI ZENON ROMULO | F15: SECTOR PACHAYZA - PARTE ALTA | J15: mayo | K15: 1 | L15: 5 | P15: 000537 | Q15: 6593657 | R15: CHAUPICERCA | S15: VERA REVILLA ,MANUEL | T15: CHAUPI CERCA S/N
A16: 46174 | B16: 000724 | C16: 220017314 | D16: PACHAYZA | E16: RAMIREZ CHAUCAYANQUI, ZENON ROMULO | F16: SECTOR PACHAYZA - HUERTA | J16: mayo | K16: 1 | L16: 5 | P16: 000796 | Q16: 22392996 | R16: LUCMANI | S16: ALVAREZ CHUQUIYANQUI, MARIBEL NAYELI | T16: AUCAYPATA S/N
... A28: 46174 | B28: 000352 | C28: 6577458 | D28: CHAUPI | E28: GONSALES PALOMINO ,ADOLFO PEDRO | F28: PASAJE LA SALLE S/N | J28: mayo | K28: 1 | L28: 5 | P28: 000010 | Q28: 6659780 | R28: LUCMANI | S28: CHALCO ESCOBAR,REYNA | T28: LUCMANI S/N
A29: 46174 | B29: 000656 | C29: 21006534 | D29: PACHAYZA | E29: ALFARO ESCOBAR EDWIN YHON | F29: PACHAYZA-PARTE BAJA | J29: mayo | K29: 1 | L29: 14.5 | M29: =SUM(L4:L29) -> 506 | P29: 000011 | Q29: 6659782 | R29: LUCMANI | S29: CHALCO ESCOBAR,TOMAS | T29: LUCMANI S/N
A30: 46175 | B30: 000735 | C30: 23022723 | D30: PACHAYZA | E30: COA TORRES, ALEXANDER REY | F30: SECTOR TARAPATA | J30: septiembre/mayo | K30: 9 | L30: 45 | P30: 000669 | Q30: 21003048 | R30: LUCMANI | S30: CHAVEZ ANTACHOQUE HENRRY | T30: SECTOR JENCHO
A31: 46175 | B31: 000202 | C31: 23022177 | D31: PACHAYZA | E31: NEYRA TORRES, ELIZABETH YENY | F31: SECTOR PACHAYZA - PARTE BAJA | J31: abril-mayo | K31: 2 | L31: 97 | P31: 000012 | Q31: 21130894 | R31: LUCMANI | S31: CHUQUIYANQUI CHALCO,ELIDA | T31: LUCMANI S/N
A32: 46175 | B32: 000101 | C32: 6564131 | D32: PACHAYZA | E32: CASTRO CORIMANYA,ANDREA | F32: SECTOR PACHAYZA - TARAPATA | J32: abril-mayo | K32: 2 | L32: 13.5 | P32: 000013 | Q32: 21003043 | R32: LUCMANI | S32: CHUQUIYANQUI HUAMANI,ETELVINA VILMA | T32: LUCMANI S/N
A33: 46175 | B33: 000446 | C33: 60062060 | D33: CHAUPI | E33: PUGA HUAHUACONDO ,FRANKLIN | F33: LUCMANI S/N | J33: abril-mayo | K33: 2 | L33: 89 | P33: 000014 | Q33: 6578450 | R33: LUCMANI | S33: CORIMANYA DE ARUTAYPE ,SUNILDA MAGDALENA | T33: LUCMANI S/N
A34: 46175 | B34: 000262 | C34: 6584520 | D34: PACHAYZA | E34: VEGA HUAMANI , LORENZA | F34: SECTOR PACHAYZA - PARTE BAJA | J34: mayo | K34: 1 | L34: 10.5 | P34: 000686 | Q34: 200031259 | R34: LUCMANI | S34: ESCOBAR ANTACHOQUE SOLEDAD | T34: LUCMANI S/N
A35: 46175 | B35: 000600 | C35: 190005359 | D35: PACHAYZA | E35: CASTRO CORIMANYA WALTER | F35: PACHAYZA - ALTA | J35: mayo | K35: 1 | L35: 20.5 | P35: 000684 | Q35: 200031254 | R35: LUCMANI | S35: ESCOBAR CHUQUIYANQUI LISBET NATALI | T35: SECTOR GABINAYOC
A36: 46175 | B36: 000633 | C36: 200039364 | D36: PACHAYZA | E36: TORRES VEGA NILA LIZETH | F36: PACHAYZA-PARTE BAJA | J36: mayo | K36: 1 | L36: 13.5 | P36: 000548 | Q36: 09092433 | R36: LUCMANI | S36: ESCOBAR MANCILLA WALTER | T36: AUCAYPATA
A37: 46175 | B37: 000599 | C37: 19003898 | D37: CHAUPI | E37: USCAMAITA CHAVEZ, OTO LUDWIN | F37: CHAUPI | J37: mayo | K37: 1 | L37: 5 | P37: 000017 | Q37: 6582818 | R37: LUCMANI | S37: ESCOBAR MONTALVO CELSO CELESTINO | T37: LUCMANI S/N
A38: 46175 | B38: 000073 | C38: 23015476 | D38: HUAQUILLO | E38: HUAMANI MONTALVO,ROSARIO RUPERTA | F38: HUAQUILLO S/N | J38: mayo | K38: 1 | L38: 5 | P38: 000685 | Q38: 200031244 | R38: LUCMANI | S38: FLORES QUISPE ROSA | T38: SECTOR GABINAYOC
A39: 46175 | B39: 000528 | C39: 6593681 | D39: AYACUCHO | E39: CHAUCAYANQUI ALVAREZ,CLEMENTE | F39: S/N | J39: mayo | K39: 1 | L39: 6.5 | P39: 000631 | Q39: 200039369 | R39: LUCMANI | S39: GUTIERREZ CHALCO RANULFO | T39: CALLE LUCMANI
A40: 46175 | B40: 000670 | C40: 21003051 | D40: CHAUPI | E40: VERA MONTALVO DE NAVINTA APOLONIA | F40: CALLE 28 DE JULIO | J40: abril-mayo | K40: 2 | L40: 14 | P40: 000691 | Q40: 21000863 | R40: LUCMANI | S40: GUTIERREZ CHALCO REYNALDO ROBERTO | T40: LUCMANI S/N
A41: 46175 | B41: 000273 | C41: 6590427 | D41: CHAUPI | E41: RAMIREZ CHAUCAYANQUI VITALIA LUZ | F41: CALLE 05 DE AGOSTO S/N | J41: mayo | K41: 1 | L41: 59.5 | P41: 000019 | Q41: 6590708 | R41: LUCMANI | S41: GUZMAN CHAUCAYANQUI ,NANCY | T41: LUCMANI S/N
A42: 46175 | B42: 000723 | C42: 220017571 | D42: PACHAYZA | E42: ALVAREZ RAMIREZ, KEVIN JHASMANY | F42: SECTOR PACHAYZA - HUERTA | J42: mayo | K42: 1 | L42: 14.5 | P42: 000020 | Q42: 6579093 | R42: LUCMANI | S42: HUAMANI CANDELARIA | T42: LUCMANI S/N
A43: 46175 | B43: 791 | C43: 20520454 | D43: PACHAYZA | E43: NEYRA RAMIREZ,WASHINTON LUIGI | F43: PACHAYZA-PUCRO S/N | J43: mayo | K43: 1 | L43: 5 | P43: 000021 | Q43: 6579096 | R43: LUCMANI | S43: HUAMANI CARPIO,CIRILO | T43: LUCMANI S/N
A44: 46175 | B44: 000697 | C44: 220017509 | D44: PACHAYZA | E44: CORIMANYA YGNACIO, YASSER RENE | F44: PACHAYZA-PARTE ALTA | J44: mayo | K44: 1 | L44: 14.5 | P44: 000022 | Q44: 6590942 | R44: LUCMANI | S44: HUAMANI COA ,FIDELA CARMEN | T44: LUCMANI S/N
A45: 46175 | B45: 000536 | C45: 6593726 | D45: CHAUPICERCA | E45: USCAMAYTA NEYRA,DAVID JESUS | F45: CHAUPI CERCA S/N | J45: mayo | K45: 1 | L45: 5 | P45: 000023 | Q45: 21000864 | R45: LUCMANI | S45: HUAMANI COA,LUCIO INGNACIO | T45: LUCMANI S/N
A46: 46175 | B46: 000534 | C46: 6593461 | D46: CHAUPICERCA | E46: NEYRA DE USCAMAYTA,MANUELA ANA | F46: CHAUPI CERCA S/N | J46: mayo | K46: 1 | L46: 5 | M46: =SUM(L30:L46) -> 423 | P46: 000589 | Q46: 200005311 | R46: LUCMANI | S46: HUAMANI LUQUE CLEDY | T46: LUCMANI S/N
A47: 46176 | B47: 000174 | C47: 23022179 | D47: PACHAYZA | E47: LAZARO USCAMAYTA CIRO | F47: SECTOR PACHAYZA - PARTE BAJA | J47: marzo-abril-mayo | K47: 3 | L47: 15 | P47: 000703 | Q47: 23015475 | R47: LUCMANI | S47: HUAMANI MALVA MARIA | T47: LUCMANI S/N
A48: 46176 | B48: 000645 | C48: 200005302 | D48: PACHAYZA | E48: MONTALVO NEYRA SUSY EVELIN | F48: PACHAYZA-PARTE BAJA | J48: mayo | K48: 1 | L48: 5 | P48: 000025 | Q48: 6593473 | R48: LUCMANI | S48: HUAMANI TORRES CORINA VALERIANA | T48: LUCMANI S/N
A49: 46176 | B49: 000287 | C49: 60061416 | D49: CHAUPI | E49: CARPIO ARROYO ,BERTILDA | F49: CALLE CUYO CUYO S/N | J49: abril-mayo | K49: 2 | L49: 45 | P49: 000027 | Q49: 6587948 | R49: LUCMANI | S49: HUAMANI USCAMAYTA,MELITON GABRIEL | T49: LUCMANI S/N
A50: 46176 | B50: 000316 | C50: 60062520 | D50: CHAUPI | E50: CHAVEZ USCAMAYTA ,JACINTO | F50: CALLE CUYO CUYO S/N | J50: mayo | K50: 1 | L50: 5 | P50: 000035 | Q50: 6585587 | R50: LUCMANI | S50: ILATAYPE MANSILLA ABEL MARCO | T50: LUCMANI S/N
A51: 46176 | B51: 000663 | C51: 200005306 | D51: PACHAYZA | E51: CHAVEZ ALLCA OLIVA CLORENTINA | F51: PACHAYZA-PARTE BAJA | J51: mayo | K51: 1 | L51: 12.5 | P51: 000028 | Q51: 23015478 | R51: LUCMANI | S51: LOPEZ CHALCO,BETTY MARIA | T51: LUCMANI S/N
A52: 46176 | B52: 000390 | C52: 6577445 | D52: CHAUPI | E52: HUAMANI USCAMAITA ,HIPOLITO | F52: CALLE LOS ESTUDIANTES S/N | J52: mayo | K52: 1 | L52: 12.5 | P52: 000029 | Q52: 6572058 | R52: LUCMANI | S52: LOPEZ MANCILLA,GLORIA | T52: LUCMANI S/N
A53: 46176 | B53: 000773 | C53: 22392997 | D53: PACHAYZA | E53: VILCA MAMANI ,DELIA | F53: PACHAYZA - PUCRO | J53: mayo | K53: 1 | L53: 25.5 | M53: =SUM(L47:L53) -> 120.5 | P53: 000030 | Q53: 6578558 | R53: LUCMANI | S53: LUQUE ARUTAYPE, JOSEFA ANGELITA | T53: LUCMANI S/N
A54: 46177 | B54: 000787 | C54: 21089863 | D54: CHAUPI | E54: NEYRA HUAMANI VICTORIA CELINA | F54: CHAUPI S/N | J54: mayo | K54: 1 | L54: 5 | P54: 000031 | Q54: 23015468 | R54: LUCMANI | S54: LUQUE RAMIREZ,GARY LUZ | T54: LUCMANI S/N
A55: 46177 | B55: 000417 | C55: 60062515 | D55: CHAUPI | E55: MONTALVO HUAMANI ,EFRAIN BLAS | F55: CALLE LOS ESTUDIANTES S/N | J55: mayo | K55: 1 | L55: 40.5 | P55: 000032 | Q55: 6572092 | R55: LUCMANI | S55: LUQUE VERA,ELISA LURDES | T55: LUCMANI S/N
A56: 46177 | B56: 000435 | C56: 6577466 | D56: CHAUPI | E56: NEIRA HUAMANI ,REDY | F56: CALLE CUYO CUYO S/N | J56: enero/mayo | K56: 5 | L56: 63.5 | P56: 000033 | Q56: 21130890 | R56: LUCMANI | S56: LUQUE VERA,URCLANIEL JANIOR | T56: LUCMANI S/N
A57: 46177 | B57: 000436 | C57: 6581229 | D57: CHAUPI | E57: NEIRA HUAMANI ,REDY | F57: PASAJE SAN ISIDRO S/N | J57: enero/mayo | K57: 5 | L57: 64.5 | P57: 000762 | Q57: 22392844 | R57: LUCMANI | S57: LYNDA KEYVI , USCAMAYTA CHALCO | T57: CARRETERA PRINCIPAL S/N
A58: 46177 | B58: 000193 | C58: 2001872 | D58: PACHAYZA | E58: MONTALVO VERA,MARY LILIANA | F58: SECTOR PACHAYZA - PARTE BAJA | J58: febrero/mayo | K58: 4 | L58: 48 | P58: 000034 | Q58: 6593296 | R58: LUCMANI | S58: MANCILLA CASTRO,MIGUEL | T58: LUCMANI S/N
A59: 46177 | B59: 000739 | C59: 23022174 | D59: PACHAYZA | E59: NEYRA TORRES, GELVER FRANKLIN | F59: PACHAYZA-PARTE BAJA-AHUINTA | J59: mayo | K59: 1 | L59: 13.5 | P59: 000036 | Q59: 200039366 | R59: LUCMANI | S59: MONTALVO ARUTAYPE,MARIA FELICIANA | T59: LUCMANI S/N
A60: 46177 | B60: 000238 | C60: 6583797 | D60: PACHAYZA | E60: TORRES SULLAYME , AURELIA | F60: SECTOR PACHAYZA - PARTE ALTA | J60: mayo | K60: 1 | L60: 7.5 | P60: 000037 | Q60: 6571879 | R60: LUCMANI | S60: MONTALVO HUAMANI,FORTUNATO YGNACIO | T60: LUCMANI S/N
A61: 46177 | B61: 000455 | C61: 60062083 | D61: CHAUPI | E61: RAMIREZ HUAMANI , ESMERALDA ARIENDA | F61: CALLE 28 DE JULIO S/N | J61: mayo | K61: 1 | L61: 22.5 | P61: 000038 | Q61: 6585795 | R61: LUCMANI | S61: MONTALVO HUAMANI,NELLY PAULA | T61: LUCMANI S/N
A62: 46177 | B62: 000357 | C62: 60061385 | D62: CHAUPI | E62: NEYRA HUAMANI, NONATA | F62: CALLE CUYO CUYO S/N | J62: abril-mayo | K62: 2 | L62: 10 | M62: =SUM(L54:L62) -> 275 | P62: 000620 | Q62: 2001885 | R62: LUCMANI | S62: MONTALVO NEIRA MARTINA DEFILIA | T62: LUCMANI S/N
A63: 46178 | B63: 000052 | C63: 6580285 | D63: LUCMANI | E63: USCAMAYTA NEYRA,MIJAIL GUSMAN | F63: LUCMANI S/N | J63: abril-mayo | K63: 2 | L63: 19.5 | P63: 000039 | Q63: 6660649 | R63: LUCMANI | S63: MONTALVO TORRES,JUAN BAUTISTA | T63: LUCMANI S/N
A64: 46178 | B64: 000385 | C64: 6573788 | D64: CHAUPI | E64: HUAMANI RAMIREZ ,SANDRO | F64: CALLE 05 DE AGOSTO S/N | J64: mayo | K64: 1 | L64: 5 | P64: 000040 | Q64: 20102672 | R64: LUCMANI | S64: MONTALVO TORRES,MANUELA | T64: LUCMANI S/N
A65: 46178 | B65: 000560 | C65: 9092373 | D65: PACHAYZA | E65: HUAMANI RAMIREZ ,SANDRO | F65: PACHAYZA- PARTE BAJA | J65: mayo | K65: 1 | L65: 23.5 | P65: 000041 | Q65: 6571820 | R65: LUCMANI | S65: NAVINTA VDA DE ANTACHOQUE,JULIA | T65: LUCMANI S/N
A66: 46178 | B66: 000730 | C66: 23022769 | D66: PACHAYZA | E66: HUAMANI RAMIREZ, HEYNER SANDRO | F66: PACHAYZA-PARTE BAJA | J66: mayo | K66: 1 | L66: 5
A67: 46178 | B67: 000389 | C67: 21000862 | D67: CHAUPI | E67: AYMARA ALFARO YENY VITALIA | F67: CALLE 28 DE JULIO S/N | J67: mayo | K67: 1 | L67: 13.5 | P67: 000043 | Q67: 6578514 | R67: LUCMANI | S67: NEIRA DE ROMERO,EDUARDA FERNANDINA | T67: LUCMANI S/N
A68: 46178 | B68: 000367 | C68: 60062470 | D68: CHAUPI | E68: HUAMANI CHALCO DE VALERIO ,CATALINA LOLA | F68: PASAJE LA SALLE S/N | J68: abril-mayo | K68: 2 | L68: 14 | P68: 000044 | Q68: 200039368 | R68: LUCMANI | S68: NEYRA DE USCAMAYTA,NOLASCA JULIA | T68: LUCMANI S/N
A69: 46178 | B69: 000745 | C69: 23015477 | D69: CHAUPI | E69: CARPIO VERA, BERLIN | F69: CL 28 DE JULIO S/N | J69: abril-mayo | K69: 2 | L69: 10 | P69: 000045 | Q69: 200031260 | R69: LUCMANI | S69: NEYRA GUTIERREZ,ENRIQUE REY | T69: LUCMANI S/N
A70: 46178 | B70: 000230 | C70: 23022184 | D70: PACHAYZA | E70: TORRES HUAMANI ,CARLOS ANDRES | F70: SECTOR PACHAYZA - PARTE ALTA | J70: abril-mayo | K70: 2 | L70: 128 | P70: 000595 | Q70: 19003886 | R70: LUCMANI | S70: NEYRA HUAMANI, BETTY PETRONILA | T70: LUCMANI S/N
A71: 46178 | B71: 000239 | C71: 6583804 | D71: PACHAYZA | E71: TORRES SULLAYME, ANDRES ABELINO | F71: SECTOR PACHAYZA - PARTE ALTA | J71: abril-mayo | K71: 2 | L71: 80 | P71: 000047 | Q71: 6660664 | R71: LUCMANI | S71: PALOMINO NEYRA,JUSTINA LUZ | T71: LUCMANI S/N
A72: 46178 | B72: 000429 | C72: 6558314 | D72: CHAUPI | E72: MORALES FLORES ,TEODORO | F72: CALLE 28 DE JULIO S/N | J72: mayo | K72: 1 | L72: 7.5 | P72: 000048 | Q72: 6571643 | R72: LUCMANI | S72: QUISPE ARUTAYPE,ISABEL | T72: LUCMANI S/N
A73: 46178 | B73: 000428 | C73: 6558323 | D73: CHAUPI | E73: MORALES FLORES ,TEODORO | F73: CALLE 28 DE JULIO S/N | J73: mayo | K73: 1 | L73: 5 | P73: 000024 | Q73: 6572073 | R73: LUCMANI | S73: QUISPE HUAMANI,CLEMENTE EMILIO | T73: LUCMANI S/N
A74: 46178 | B74: 000571 | C74: 9093208 | D74: CHAUPI | E74: MORALES FLORES ,TEODORO | F74: CALLE 28 DE JULIO S/N | J74: mayo | K74: 1 | L74: 8.5 | P74: 000049 | Q74: 6591593 | R74: LUCMANI | S74: RAMIREZ HUAMANI,MARIA LETICIA | T74: LUCMANI S/N
A75: 46178 | B75: 000675 | C75: 19003894 | D75: HUAQUILLO | E75: CHALCO DE ARUTAYPE ADELA FELICITAS | F75: AYNANI | J75: febrero/mayo | K75: 4 | L75: 76.5 | M75: =SUM(L63:L75) -> 396 | P75: 000050 | Q75: 6593289 | R75: LUCMANI | S75: SIVINCHA DE CHAVEZ,MARIA SANTOS | T75: LUCMANI S/N
A76: 46179 | B76: 000726 | C76: 21000873 | D76: CHAUPI | E76: QUISPE USCAMAYTA, ZILPA LEVI | F76: CALLE JUAN USCMAYTA S/N | J76: abril-mayo | K76: 2 | L76: 25 | P76: 000651 | Q76: 22392656 | R76: LUCMANI | S76: TORRES CABRERA, ROSMEL VICTOR | T76: CALLE LUCMANI S/N
A77: 46179 | B77: 000794 | C77: 24261119 | D77: PACHAYZA | E77: MARTINEZ ZAMBRANO,GIAN FRANCO | F77: PACHAYZA-PUCRO S/N | J77: mayo | K77: 1 | L77: 18.5 | P77: 000051 | Q77: 6659885 | R77: LUCMANI | S77: TORRES LOPEZ,JULIANA | T77: LUCMANI S/N
A78: 46179 | B78: 000362 | C78: 60061429 | D78: CHAUPI | E78: USCAMAYTA HUAMANI, EDWIN ALEJANDRO | F78: CALLE JUAN USCAMAYTA S/N | J78: diciembre/mayo | K78: 5 | L78: 150 | P78: 000630 | Q78: 200011823 | R78: LUCMANI | S78: USCAMAYTA NAVINTA YSAURO SABINO | T78: CALLE LUCMANI
A79: 46179 | B79: 000514 | C79: 6577482 | D79: CHAUPI | E79: VERA DE TORRES ,VICENTA | F79: CALLE LOS ESTUDIANTES S/N | J79: abril-mayo | K79: 2 | L79: 21 | M79: =SUM(L76:L79) -> 214.5 | P79: 000052 | Q79: 6580285 | R79: LUCMANI | S79: USCAMAYTA NEYRA,MIJAIL GUSMAN | T79: LUCMANI S/N
A80: 46181 | B80: 000376 | C80: 6577380 | D80: CHAUPI | E80: HUAMANI HUAMANI ,ALEJANDRA NELLY | F80: PASAJE LA SALLE S/N | J80: mayo | K80: 1 | L80: 5 | P80: 000053 | Q80: 6571989 | R80: LUCMANI | S80: VERA DE LUQUE,REYNA PETRONILA | T80: LUCMANI S/N
A81: 46181 | B81: 000153 | C81: 6585712 | D81: PACHAYZA | E81: NEYRA HUAMANI VICTORIA CELINA | F81: SECTOR PACHAYZA -TARAPATA | J81: febrero/mayo | K81: 4 | L81: 28 | P81: 000054 | Q81: 6591590 | R81: LUCMANI | S81: VERA REVILLA ,FIDELISA | T81: LUCMANI S/N
A82: 46181 | B82: 000781 | C82: 21086217 | D82: PACHAYZA | E82: NEIRA USCAMAYTA, BEGONIA GABRIELA | F82: PACHAYZA - PUCRO S/N | J82: enero/mayo | K82: 5 | L82: 97.5 | P82: 000756 | Q82: 22393037 | R82: LUCMANI | S82: ZAPANA MANSILLA , GUSTAVO RAUL | T82: AUCAYPATA
A83: 46181 | B83: 000371 | C83: 6562328 | D83: CHAUPI | E83: HUAMANI CORIMANYA ,RAFO AQUILES | F83: PASAJE EL OLVIDO S/N | J83: mayo | K83: 1 | L83: 5 | P83: 000498 | Q83: 60062505 | R83: CHAUPI | S83: ALFARO NEYRA DE CHUQUIYANQUI LUCIA POMPEYA | T83: PASAJE SAN ISIDRO S/N
A84: 46181 | B84: 000151 | C84: 6585733 | D84: PACHAYZA | E84: HUAMANI CORIMANYA, RAFO AQUILES | F84: SECTOR PACHAYZA -TARAPATA | J84: mayo | K84: 1 | L84: 5 | P84: 000308 | Q84: 60062454 | R84: CHAUPI | S84: ALFARO TORREZ, TATIANA PAOLA | T84: pasaje VIRGEN DE LAS NIEVES
A85: 46181 | B85: 000072 | C85: 6563990 | D85: HUAQUILLO | E85: HUAMANI MONTALVO,ISAURO MANUEL | F85: HUAQUILLO S/N | J85: mayo | K85: 1 | L85: 5 | P85: 000549 | Q85: 18052517 | R85: CHAUPI | S85: ALFARO TORREZ, TATIANA PAOLA | T85: CALLE CUYO CUYO
A86: 46181 | B86: 000105 | C86: 6564196 | D86: PACHAYZA | E86: CHALCO COA, JUAN CARLOS | F86: SECTOR PACHAYZA - PARTE BAJA | J86: febrero-marzo-abril | K86: 3 | L86: 65.5 | P86: 000274 | Q86: 09174 | R86: CHAUPI | S86: ALVAREZ VERA LELIS SOLNA | T86: PASAJE EL OLVIDO S/N
A87: 46181 | B87: 000776 | C87: 21146464 | D87: PACHAYZA | E87: CRUZ NEYRA ,YENCY ELIDA | F87: PACHAYZA - PUCRO | J87: abril-mayo | K87: 2 | L87: 15.5 | P87: 000746 | Q87: 23022187 | R87: CHAUPI | S87: ANGULO ESCOBAR, JEISVER ANTONIO | T87: CALLE EL OLVIDO S/N
A88: 46181 | B88: 000341 | C88: 6562305 | D88: CHAUPI | E88: CRUZ NEYRA ,YENCY ELIDA | F88: CALLE 05 DE AGOSTO S/N | J88: abril-mayo | K88: 2 | L88: 10 | P88: 000753 | Q88: 22393036 | R88: CHAUPI | S88: ANTACHOQUE ESCOBAR , FANY KELIDA | T88: CALLE LUCMANI S/N
A89: 46181 | B89: 000440 | C89: 6577422 | D89: CHAUPI | E89: NEIRA VERA ,ALEJANDRO TEODORO | F89: CALLE SAN SEBASTIAN S/N | J89: mayo | K89: 1 | L89: 9.5 | P89: 000276 | Q89: 60062119 | R89: CHAUPI | S89: ANTACHOQUE ESCOBAR ,AMELIA | T89: LUCMANI S/N
A90: 46181 | B90: 000462 | C90: 60062024 | D90: CHAUPI | E90: ROCA MAMANI ,ESTEBAN | F90: LUCMANI S/N | J90: marzo-abril-mayo | K90: 3 | L90: 40.5 | P90: 000586 | Q90: 09093268 | R90: CHAUPI | S90: ANTACHOQUE ESCOBAR, FANY KELIDA | T90: LUCMANI S/N
A91: 46181 | B91: 000047 | C91: 6660664 | D91: LUCMANI | E91: PALOMINO NEYRA,JUSTINA LUZ | F91: LUCMANI S/N | J91: marzo-abril-mayo | K91: 3 | L91: 45.5 | P91: 000672 | Q91: 21003054 | R91: CHAUPI | S91: ANTACHOQUE HERENCIA GENESIS | T91: CALLE 28 DE JULIO
A92: 46181 | B92: 000575 | C92: 09091780 | D92: PACHAYZA | E92: CHAUCAYANQUI GUTIERREZ, JUAN PERCY | F92: TARAPATA | J92: abril-mayo | K92: 2 | L92: 10 | P92: 000277 | Q92: 21133410 | R92: CHAUPI | S92: ANTACHOQUE MANCILLA JUANA | T92: LUCMANI S/N
A93: 46181 | B93: 000226 | C93: 6590880 | D93: PACHAYZA | E93: TICONA SUAQUITA,NALDA MARIZA | F93: PACHAYZA | J93: mayo | K93: 1 | L93: 17.5 | M93: =SUM(L80:L93) -> 359.5 | P93: 000275 | Q93: 6590170 | R93: CHAUPI | S93: ANTACHOQUE MANCILLA,ANTONIO MARCELINO | T93: CALLE VIRGEN DEL CARMEN S/N
A94: 46182 | B94: 000132 | C94: 6586605 | D94: PACHAYZA | E94: CORIMANYA HUAMANI ,ESTELA CATALINA | F94: SECTOR PACHAYZA - PUCRO | J94: enero/mayo | K94: 5 | L94: 25 | P94: 000278 | Q94: 60062464 | R94: CHAUPI | S94: ANTACHOQUE NAVINTA ,LETDY EVANIA | T94: CALLE CUYO CUYO S/N
A95: 46182 | B95: 000133 | C95: 6584533 | D95: PACHAYZA | E95: CORIMANYA HUAMANI ,JUAN | F95: SECTOR PACHAYZA - PARTE BAJA | J95: abril-mayo | K95: 2 | L95: 16.5 | P95: 000551 | Q95: 9090209 | R95: CHAUPI | S95: APFATA MONTALVO JAIME RAUL | T95: PASAJE SAN ISIDRO S/N
A96: 46182 | B96: 000035 | C96: 6585587 | D96: LUCMANI | E96: ILATAYPE MANSILLA ABEL MARCO | F96: LUCMANI S/N | J96: febrero/mayo | K96: 4 | L96: 20 | P96: 000279 | Q96: 20102295 | R96: CHAUPI | S96: ARROYO CARPIO ,JUAN | T96: LUCMANI S/N
A97: 46182 | B97: 000388 | C97: 6562293 | D97: CHAUPI | E97: HUAMANI URDAY ,JORGE ISRAEL | F97: CALLE 05 DE AGOSTO S/N | J97: diciembre/mayo | K97: 6 | L97: 129.5 | P97: 000280 | Q97: 60062051 | R97: CHAUPI | S97: ARUTAIPE COA ,CONCEPCION ESTEFA | T97: CALLE 28 DE JULIO S/N
A98: 46182 | B98: 000408 | C98: 6562535 | D98: CHAUPI | E98: MANCILLA HILATAIPE ,BERNARDINA LORENZA | F98: CALLE 28 DE JULIO S/N | J98: marzo-abril-mayo | K98: 3 | L98: 84.5 | P98: 000467 | Q98: 6581492 | R98: CHAUPI | S98: ARUTAYPE CORIMANYA GLENY | T98: LUCMANI S/N
A99: 46182 | B99: 000638 | C99: 200002890 | D99: CHAUPI | E99: TILLCA MENDOZA YANED | F99: CALLE AVIACION S/N | J99: marzo-abril-mayo | K99: 3 | L99: 62.5
A100: 46182 | B100: 000509 | C100: 60061389 | D100: CHAUPI | E100: USCAMAITA HUAMANI ELISEO BACILIO | F100: CALLE 28 DE JULIO S/N | J100: febrero/mayo | K100: 4 | L100: 203.5 | P100: 000281 | Q100: 6577450 | R100: CHAUPI | S100: ARUTAYPE HUAMANI ,MELITON | T100: CALLE 28 DE JULIO S/N
A101: 46182 | B101: 000203 | C101: 6587962 | D101: PACHAYZA | E101: NOVA MONTALVO,MAYKOL | F101: SECTOR PACHAYZA - PARTE BAJA | J101: abril-mayo | K101: 2 | L101: 10 | P101: 000283 | Q101: 6562501 | R101: CHAUPI | S101: AYMARA ALFARO ,FROILAN ANDRES | T101: CALLE 28 DE JULIO S/N
A102: 46182 | B102: 000248 | C102: 6585751 | D102: PACHAYZA | E102: TORREZ USCAMAITA, JUSTINO JULIO | F102: SECTOR PACHAYZA- PARTE BAJA | J102: mayo | K102: 1 | L102: 36.5 | P102: 000546 | Q102: 60062456 | R102: CHAUPI | S102: AYMARA ALFARO ,FROILAN ANDRES | T102: PASAJE SAN ISIDRO
A103: 46182 | B103: 000296 | C103: 6562563 | D103: CHAUPI | E103: CASTRO HUAMANI ,MARISOL | F103: LUCMANI S/N | J103: mayo | K103: 1 | L103: 35.5 | P103: 000389 | Q103: 21000862 | R103: CHAUPI | S103: AYMARA ALFARO YENY VITALIA | T103: CALLE 28 DE JULIO S/N
A104: 46182 | B104: 000595 | C104: 19003886 | D104: LUCMANI | E104: NEYRA HUAMANI, BETTY PETRONILA | F104: LUCMANI S/N | J104: mayo | K104: 1 | L104: 13.5 | P104: 000286 | Q104: 6581494 | R104: CHAUPI | S104: AYMARA ALFARO, YENY VITALIA | T104: CALLE JUAN USCAMAYTA S/N
A105: 46182 | B105: 000524 | C105: 6580013 | D105: CHAUPI | E105: VILCA RAMIREZ ,CELIA IGNACIA | F105: CALLE CUYO CUYO S/N | J105: mayo | K105: 1 | L105: 5 | P105: 000284 | Q105: 6573777 | R105: CHAUPI | S105: AYMARA HUAMANI DE HUAMANI ,CASIMIRA ADRIANA | T105: CALLE VIRGEN DE LAS NIEVES S/N
A106: 46182 | B106: 000228 | C106: 6579494 | D106: PACHAYZA | E106: TORRES CHUQUIYANQUI, DONICIO ELEUTERIO | F106: SECTOR PACHAYZA - PARTE ALTA | J106: mayo | K106: 1 | L106: 5 | P106: 000583 | Q106: 19002267 | R106: CHAUPI | S106: AYMARA HUAMANI DE HUAMANI, VIVIANA ESTEFA | T106: CALLE, LOS ESTUDIANTES S/N
A107: 46182 | B107: 000312 | C107: 60061417 | D107: CHAUPI | E107: CHAVEZ DE TORRES ,JESUSA | F107: CALLE CUYO CUYO S/N | J107: mayo | K107: 1 | L107: 5 | M107: =SUM(L94:L107) -> 652 | P107: 000285 | Q107: 6580027 | R107: CHAUPI | S107: AYMARA LOPEZ ,JUAN CANCIO | T107: CALLE 28 DE JULIO S/N
A108: 46183 | B108: 000406 | C108: 60061415 | D108: CHAUPI | E108: MANCILLA ALLCA ,JESUS CEBASTIAN | F108: CALLE 28 DE JULIO S/N | J108: mayo | K108: 1 | L108: 5 | P108: 000337 | Q108: 60062061 | R108: CHAUPI | S108: CACSIRE VERA CRISTINA MARILU | T108: LUCMANI S/N
A109: 46183 | B109: 000163 | C109: 6659580 | D109: PACHAYZA | E109: HUAMANI URDAY, MARIA FELIPA | F109: SECTOR PACHAYZA- SANTA ROSA | J109: marzo/junio | K109: 4 | L109: 43 | P109: 000287 | Q109: 60061416 | R109: CHAUPI | S109: CARPIO ARROYO ,BERTILDA | T109: CALLE CUYO CUYO S/N
A110: 46183 | B110: 000235 | C110: 18052547 | D110: PACHAYZA | E110: TORRES HUASHUAYO, MARIA MAGDALENA | F110: SECTOR PACHAYZA - PARTE BAJA | J110: marzo/junio | K110: 4 | L110: 20 | P110: 000288 | Q110: 6580018 | R110: CHAUPI | S110: CARPIO HUAMANI ,AMELIO RUFINO | T110: CALLE 28 DE JULIO S/N
A111: 46183 | B111: 000383 | C111: 60061413 | D111: CHAUPI | E111: HUAMANI RAMIREZ ,JOEL FROILAN | F111: PASAJE 10 S/N | J111: abril-mayo-junio | K111: 3 | L111: 15 | P111: 000289 | Q111: 6558317 | R111: CHAUPI | S111: CARPIO NAVINTA ,HECTOR SIMON | T111: CALLE 28 DE JULIO S/N
A112: 46183 | B112: 000233 | C112: 6593618 | D112: PACHAYZA | E112: TORRES HUASHUAYO ,JUAN NICOLAS | F112: SECTOR PACHAYZA - PARTE BAJA | J112: marzo/junio | K112: 4 | L112: 20 | P112: 000745 | Q112: 23015477 | R112: CHAUPI | S112: CARPIO VERA, BERLIN | T112: CL 28 DE JULIO S/N
A113: 46183 | B113: 000103 | C113: 6584505 | D113: PACHAYZA | E113: CASTRO DE BEDOYA, GUILLERMINA | F113: SECTOR PACHAYZA - PARTE BAJA | J113: junio | K113: 1 | L113: 29.5 | P113: 000292 | Q113: 6558343 | R113: CHAUPI | S113: CASQUINO MANSILLA ,MARIANO ASUNTO | T113: LUCMANI S/N
...

Sheet CAJA
C3: CAJA MES DE JUNIO DEL 2025
A6: FECHA | B6: INGRESO RECIBOS | C6: INGRESOS VARIABLES | D6: GRIFO DE AGUA | E6: INGRESOS MULTAS | F6: VENTA DE ACCESORIOS | G6: MOVILIDAD PETAR | H6: EGRESO TOTAL | I6: SALDO TOTAL
A7: 46174 | B7: =SUMIFS(RECIBOS!$L$4:$L$822,RECIBOS!$A$4:$A$822,CAJA!A7) -> 506 | C7: =SUMIFS(INGRESOS!$F$13:$F$33,INGRESOS!$B$13:$B$33,CAJA!A7) -> 1071 | D7: =SUMIFS(INGRESOS!$F$39:$F$155,INGRESOS!$B$39:$B$155,CAJA!A7) -> 150 | E7: =SUMIFS(INGRESOS!$F$161:$F$165,INGRESOS!$B$161:$B$165,CAJA!A7) -> 0 | F7: {=SUMIFS(INGRESOS!F170:F188,INGRESOS!B170:B188,CAJA!A7:A37)} -> 0 | G7: =SUMIFS(EGRESOS!$F$85:$F$100,EGRESOS!$B$85:$B$100,CAJA!A7) -> 0 | H7: =SUMIFS(EGRESOS!$F$4:$F$77,EGRESOS!$B$4:$B$77,CAJA!A7) -> 114.4 | I7: =(B7+C7+D7+F7)-H7 -> 1612.6
A8: 46175 | B8: =SUMIFS(RECIBOS!$L$4:$L$822,RECIBOS!$A$4:$A$822,CAJA!A8) -> 423 | C8: =SUMIFS(INGRESOS!$F$13:$F$33,INGRESOS!$B$13:$B$33,CAJA!A8) -> 0 | D8: =SUMIFS(INGRESOS!$F$39:$F$155,INGRESOS!$B$39:$B$155,CAJA!A8) -> 160 | E8: =SUMIFS(INGRESOS!$F$161:$F$165,INGRESOS!$B$161:$B$165,CAJA!A8) -> 0 | F8: 0 | G8: =SUMIFS(EGRESOS!$F$85:$F$100,EGRESOS!$B$85:$B$100,CAJA!A8) -> 0 | H8: =SUMIFS(EGRESOS!$F$4:$F$77,EGRESOS!$B$4:$B$77,CAJA!A8) -> 0 | I8: =(I7+B8+C8+D8+H8+F8)-H8 -> 2195.6
A9: 46176 | B9: =SUMIFS(RECIBOS!$L$4:$L$822,RECIBOS!$A$4:$A$822,CAJA!A9) -> 120.5 | C9: =SUMIFS(INGRESOS!$F$13:$F$33,INGRESOS!$B$13:$B$33,CAJA!A9) -> 0 | D9: =SUMIFS(INGRESOS!$F$39:$F$155,INGRESOS!$B$39:$B$155,CAJA!A9) -> 190 | E9: =SUMIFS(INGRESOS!$F$161:$F$165,INGRESOS!$B$161:$B$165,CAJA!A9) -> 0 | F9: 0 | G9: =SUMIFS(EGRESOS!$F$85:$F$100,EGRESOS!$B$85:$B$100,CAJA!A9) -> 0 | H9: =SUMIFS(EGRESOS!$F$4:$F$77,EGRESOS!$B$4:$B$77,CAJA!A9) -> 825 | I9: =(I8+B9+C9+D9+H9+F9)-H9 -> 2506.1
A10: 46177 | B10: =SUMIFS(RECIBOS!$L$4:$L$822,RECIBOS!$A$4:$A$822,CAJA!A10) -> 275 | C10: =SUMIFS(INGRESOS!$F$13:$F$33,INGRESOS!$B$13:$B$33,CAJA!A10) -> 135 | D10: =SUMIFS(INGRESOS!$F$39:$F$155,INGRESOS!$B$39:$B$155,CAJA!A10) -> 180 | E10: =SUMIFS(INGRESOS!$F$161:$F$165,INGRESOS!$B$161:$B$165,CAJA!A10) -> 0 | F10: 0 | G10: =SUMIFS(EGRESOS!$F$85:$F$100,EGRESOS!$B$85:$B$100,CAJA!A10) -> 0 | H10: =SUMIFS(EGRESOS!$F$4:$F$77,EGRESOS!$B$4:$B$77,CAJA!A10) -> 0 | I10: =(I9+B10+C10+D10+F10)-H10 -> 3096.1
A11: 46178 | B11: =SUMIFS(RECIBOS!$L$4:$L$822,RECIBOS!$A$4:$A$822,CAJA!A11) -> 396 | C11: =SUMIFS(INGRESOS!$F$13:$F$33,INGRESOS!$B$13:$B$33,CAJA!A11) -> 0 | D11: =SUMIFS(INGRESOS!$F$39:$F$155,INGRESOS!$B$39:$B$155,CAJA!A11) -> 140 | E11: =SUMIFS(INGRESOS!$F$161:$F$165,INGRESOS!$B$161:$B$165,CAJA!A11) -> 0 | F11: 0 | G11: =SUMIFS(EGRESOS!$F$85:$F$100,EGRESOS!$B$85:$B$100,CAJA!A11) -> 0 | H11: =SUMIFS(EGRESOS!$F$4:$F$77,EGRESOS!$B$4:$B$77,CAJA!A11) -> 42.5 | I11: =(I10+B11+C11+D11+F11)-H11 -> 3589.6
A12: 46179 | B12: =SUMIFS(RECIBOS!$L$4:$L$822,RECIBOS!$A$4:$A$822,CAJA!A12) -> 214.5 | C12: =SUMIFS(INGRESOS!$F$13:$F$33,INGRESOS!$B$13:$B$33,CAJA!A12) -> 8.5 | D12: =SUMIFS(INGRESOS!$F$39:$F$155,INGRESOS!$B$39:$B$155,CAJA!A12) -> 90 | E12: =SUMIFS(INGRESOS!$F$161:$F$165,INGRESOS!$B$161:$B$165,CAJA!A12) -> 0 | F12: 0 | G12: =SUMIFS(EGRESOS!$F$85:$F$100,EGRESOS!$B$85:$B$100,CAJA!A12) -> 0 | H12: =SUMIFS(EGRESOS!$F$4:$F$77,EGRESOS!$B$4:$B$77,CAJA!A12) -> 0 | I12: =(I11+B12+C12+D12+F12)-H12 -> 3902.6
A13: 46180 | B13: =SUMIFS(RECIBOS!$L$4:$L$822,RECIBOS!$A$4:$A$822,CAJA!A13) -> 0 | C13: =SUMIFS(INGRESOS!$F$13:$F$33,INGRESOS!$B$13:$B$33,CAJA!A13) -> 0 | D13: =SUMIFS(INGRESOS!$F$39:$F$155,INGRESOS!$B$39:$B$155,CAJA!A13) -> 70 | E13: =SUMIFS(INGRESOS!$F$161:$F$165,INGRESOS!$B$161:$B$165,CAJA!A13) -> 0 | F13: 0 | G13: =SUMIFS(EGRESOS!$F$85:$F$100,EGRESOS!$B$85:$B$100,CAJA!A13) -> 0 | H13: =SUMIFS(EGRESOS!$F$4:$F$77,EGRESOS!$B$4:$B$77,CAJA!A13) -> 0 | I13: =(I12+B13+C13+D13+F13)-H13 -> 3972.6
A14: 46181 | B14: =SUMIFS(RECIBOS!$L$4:$L$822,RECIBOS!$A$4:$A$822,CAJA!A14) -> 359.5 | C14: =SUMIFS(INGRESOS!$F$13:$F$33,INGRESOS!$B$13:$B$33,CAJA!A14) -> 0 | D14: =SUMIFS(INGRESOS!$F$39:$F$155,INGRESOS!$B$39:$B$155,CAJA!A14) -> 130 | E14: =SUMIFS(INGRESOS!$F$161:$F$165,INGRESOS!$B$161:$B$165,CAJA!A14) -> 0 | F14: 0 | G14: =SUMIFS(EGRESOS!$F$85:$F$100,EGRESOS!$B$85:$B$100,CAJA!A14) -> 0 | H14: =SUMIFS(EGRESOS!$F$4:$F$77,EGRESOS!$B$4:$B$77,CAJA!A14) -> 1148.5 | I14: =(I13+B14+C14+D14+F14)-H14 -> 3313.6
A15: 46182 | B15: =SUMIFS(RECIBOS!$L$4:$L$822,RECIBOS!$A$4:$A$822,CAJA!A15) -> 652 | C15: =SUMIFS(INGRESOS!$F$13:$F$33,INGRESOS!$B$13:$B$33,CAJA!A15) -> 285 | D15: =SUMIFS(INGRESOS!$F$39:$F$155,INGRESOS!$B$39:$B$155,CAJA!A15) -> 80 | E15: =SUMIFS(INGRESOS!$F$161:$F$165,INGRESOS!$B$161:$B$165,CAJA!A15) -> 0 | F15: 0 | G15: =SUMIFS(EGRESOS!$F$85:$F$100,EGRESOS!$B$85:$B$100,CAJA!A15) -> 0 | H15: =SUMIFS(EGRESOS!$F$4:$F$77,EGRESOS!$B$4:$B$77,CAJA!A15) -> 1010 | I15: =(I14+B15+C15+D15+F15)-H15 -> 3320.6
A16: 46183 | B16: =SUMIFS(RECIBOS!$L$4:$L$822,RECIBOS!$A$4:$A$822,CAJA!A16) -> 204 | C16: =SUMIFS(INGRESOS!$F$13:$F$33,INGRESOS!$B$13:$B$33,CAJA!A16) -> 551 | D16: =SUMIFS(INGRESOS!$F$39:$F$155,INGRESOS!$B$39:$B$155,CAJA!A16) -> 40 | E16: =SUMIFS(INGRESOS!$F$161:$F$165,INGRESOS!$B$161:$B$165,CAJA!A16) -> 0 | F16: 0 | G16: =SUMIFS(EGRESOS!$F$85:$F$100,EGRESOS!$B$85:$B$100,CAJA!A16) -> 0 | H16: =SUMIFS(EGRESOS!$F$4:$F$77,EGRESOS!$B$4:$B$77,CAJA!A16) -> 490 | I16: =(I15+B16+C16+D16+F16)-H16 -> 3625.6
A17: 46184 | B17: =SUMIFS(RECIBOS!$L$4:$L$822,RECIBOS!$A$4:$A$822,CAJA!A17) -> 277.5 | C17: =SUMIFS(INGRESOS!$F$13:$F$33,INGRESOS!$B$13:$B$33,CAJA!A17) -> 150 | D17: =SUMIFS(INGRESOS!$F$39:$F$155,INGRESOS!$B$39:$B$155,CAJA!A17) -> 70 | E17: =SUMIFS(INGRESOS!$F$161:$F$165,INGRESOS!$B$161:$B$165,CAJA!A17) -> 0 | F17: 0 | G17: =SUMIFS(EGRESOS!$F$85:$F$100,EGRESOS!$B$85:$B$100,CAJA!A17) -> 0 | H17: =SUMIFS(EGRESOS!$F$4:$F$77,EGRESOS!$B$4:$B$77,CAJA!A17) -> 130 | I17: =(I16+B17+C17+D17+F17)-H17 -> 3993.1
A18: 46185 | B18: =SUMIFS(RECIBOS!$L$4:$L$822,RECIBOS!$A$4:$A$822,CAJA!A18) -> 656.5 | C18: =SUMIFS(INGRESOS!$F$13:$F$33,INGRESOS!$B$13:$B$33,CAJA!A18) -> 958 | D18: =SUMIFS(INGRESOS!$F$39:$F$155,INGRESOS!$B$39:$B$155,CAJA!A18) -> 100 | E18: =SUMIFS(INGRESOS!$F$161:$F$165,INGRESOS!$B$161:$B$165,CAJA!A18) -> 0 | F18: 0 | G18: =SUMIFS(EGRESOS!$F$85:$F$100,EGRESOS!$B$85:$B$100,CAJA!A18) -> 0 | H18: =SUMIFS(EGRESOS!$F$4:$F$77,EGRESOS!$B$4:$B$77,CAJA!A18) -> 2350 | I18: =(I17+B18+C18+D18+F18)-H18 -> 3357.6
A19: 46186 | B19: =SUMIFS(RECIBOS!$L$4:$L$822,RECIBOS!$A$4:$A$822,CAJA!A19) -> 93 | C19: =SUMIFS(INGRESOS!$F$13:$F$33,INGRESOS!$B$13:$B$33,CAJA!A19) -> 1113 | D19: =SUMIFS(INGRESOS!$F$39:$F$155,INGRESOS!$B$39:$B$155,CAJA!A19) -> 120 | E19: =SUMIFS(INGRESOS!$F$161:$F$165,INGRESOS!$B$161:$B$165,CAJA!A19) -> 0 | F19: 0 | G19: =SUMIFS(EGRESOS!$F$85:$F$100,EGRESOS!$B$85:$B$100,CAJA!A19) -> 0 | H19: =SUMIFS(EGRESOS!$F$4:$F$77,EGRESOS!$B$4:$B$77,CAJA!A19) -> 1320 | I19: =(I18+B19+C19+D19+F19)-H19 -> 3363.6
A20: 46187 | B20: =SUMIFS(RECIBOS!$L$4:$L$822,RECIBOS!$A$4:$A$822,CAJA!A20) -> 0 | C20: =SUMIFS(INGRESOS!$F$13:$F$33,INGRESOS!$B$13:$B$33,CAJA!A20) -> 0 | D20: =SUMIFS(INGRESOS!$F$39:$F$155,INGRESOS!$B$39:$B$155,CAJA!A20) -> 160 | E20: =SUMIFS(INGRESOS!$F$161:$F$165,INGRESOS!$B$161:$B$165,CAJA!A20) -> 0 | F20: 0 | G20: =SUMIFS(EGRESOS!$F$85:$F$100,EGRESOS!$B$85:$B$100,CAJA!A20) -> 0 | H20: =SUMIFS(EGRESOS!$F$4:$F$77,EGRESOS!$B$4:$B$77,CAJA!A20) -> 0 | I20: =(I19+B20+C20+D20+F20)-H20 -> 3523.6
A21: 46188 | B21: =SUMIFS(RECIBOS!$L$4:$L$822,RECIBOS!$A$4:$A$822,CAJA!A21) -> 486 | C21: =SUMIFS(INGRESOS!$F$13:$F$33,INGRESOS!$B$13:$B$33,CAJA!A21) -> 0 | D21: =SUMIFS(INGRESOS!$F$39:$F$155,INGRESOS!$B$39:$B$155,CAJA!A21) -> 250 | E21: =SUMIFS(INGRESOS!$F$161:$F$165,INGRESOS!$B$161:$B$165,CAJA!A21) -> 0 | F21: 0 | G21: =SUMIFS(EGRESOS!$F$85:$F$100,EGRESOS!$B$85:$B$100,CAJA!A21) -> 0 | H21: =SUMIFS(EGRESOS!$F$4:$F$77,EGRESOS!$B$4:$B$77,CAJA!A21) -> 65 | I21: =(I20+B21+C21+D21+F21)-H21 -> 4194.6
... A36: 46203 | B36: =SUMIFS(RECIBOS!$L$4:$L$822,RECIBOS!$A$4:$A$822,CAJA!A36) -> 0 | C36: =SUMIFS(INGRESOS!$F$13:$F$33,INGRESOS!$B$13:$B$33,CAJA!A36) -> 0 | D36: =SUMIFS(INGRESOS!$F$39:$F$155,INGRESOS!$B$39:$B$155,CAJA!A36) -> 170 | E36: =SUMIFS(INGRESOS!$F$161:$F$165,INGRESOS!$B$161:$B$165,CAJA!A36) -> 0 | F36: 0 | G36: =SUMIFS(EGRESOS!$F$85:$F$100,EGRESOS!$B$85:$B$100,CAJA!A36) -> 0 | H36: =SUMIFS(EGRESOS!$F$4:$F$77,EGRESOS!$B$4:$B$77,CAJA!A36) -> 4580 | I36: =(I35+B36+C36+D36+F36)-H36 -> 3295.1
B37: =SUMIFS(RECIBOS!$L$4:$L$822,RECIBOS!$A$4:$A$822,CAJA!A37) -> 0 | C37: =SUMIFS(INGRESOS!$F$13:$F$33,INGRESOS!$B$13:$B$33,CAJA!A37) -> 0 | D37: =SUMIFS(INGRESOS!$F$39:$F$155,INGRESOS!$B$39:$B$155,CAJA!A37) -> 0 | E37: =SUMIFS(INGRESOS!$F$161:$F$165,INGRESOS!$B$161:$B$165,CAJA!A37) -> 0 | F37: 0 | G37: =SUMIFS(EGRESOS!$F$85:$F$100,EGRESOS!$B$85:$B$100,CAJA!A37) -> 0 | H37: =SUMIFS(EGRESOS!$F$4:$F$77,EGRESOS!$B$4:$B$77,CAJA!A37) -> 0 | I37: =(I36+B37+C37+D37+F37)-H37 -> 3295.1
A38: SUMA TOTAL | B38: =SUM(B7:B37) -> 8875 | C38: =SUM(C7:C37) -> 4351.5 | D38: =SUM(D7:D37) -> 4230 | E38: =SUM(E7:E37) -> 0 | F38: =SUM(F7:F37) -> 0 | G38: =SUM(G7:G37) -> 0 | H38: =SUM(H7:H37) -> 14986.4 | I38: =I37 -> 3295.1
A40: COPIAS/IMPRESIONES | C40: 56 | K40: CAJA DE | L40: COPIAS
C42: =B38+C38+D38+E38+F38+C40 -> 17512.5 | G42: =G38 -> 0 | H42: =H38 -> 14986.4 | I42: =C42-H42-G42 -> 2526.1
C43: INGRESO TOTAL | H43: EGRESO TOTAL | I43: SALDO FINAL
A46: CAJA INICIAL DEL MES | I46: 58.2
H48: TOTAL | I48: =I42+I46 -> 2584.3

Sheet INGRESOS
D1: INGRESO X COBRO DE RECIBOS DICIEMBRE 2025
D2: DESCRIPCION | F2: MONTO
B3: BARRIO | C3: =COUNTIF(RECIBOS!$D$4:$D$822,INGRESOS!D3) -> 147 | D3: CHAUPI | F3: =SUMIF(RECIBOS!D$4:D$822,"CHAUPI",RECIBOS!L$4:L$822) -> 4397.5
B4: BARRIO | C4: =COUNTIF(RECIBOS!$D$4:$D$822,INGRESOS!D4) -> 132 | D4: PACHAYZA | F4: =SUMIF(RECIBOS!D$4:D$822,"PACHAYZA",RECIBOS!L$4:L$822) -> 3615.5
B5: BARRIO | C5: =COUNTIF(RECIBOS!$D$4:$D$822,INGRESOS!D5) -> 25 | D5: LUCMANI | F5: =SUMIF(RECIBOS!D$4:D$822,"LUCMANI",RECIBOS!L$4:L$822) -> 604
B6: BARRIO | C6: =COUNTIF(RECIBOS!$D$4:$D$822,INGRESOS!D6) -> 11 | D6: HUAQUILLO | F6: =SUMIF(RECIBOS!D$4:D$822,"HUAQUILLO",RECIBOS!L$4:L$822) -> 214
B7: BARRIO | C7: =COUNTIF(RECIBOS!$D$4:$D$822,INGRESOS!D7) -> 1 | D7: AYACUCHO | F7: =SUMIF(RECIBOS!D$4:D$822,"AYACUCHO",RECIBOS!L$4:L$822) -> 6.5
B8: BARRIO | C8: =COUNTIF(RECIBOS!$D$4:$D$822,INGRESOS!D8) -> 4 | D8: CHAUPICERCA | F8: =SUMIF(RECIBOS!D$4:D$822,"CHAUPICERCA",RECIBOS!L$4:L$822) -> 37.5
C9: =SUM(C3:C8) -> 320 | D9: SUMA TOTAL | F9: =SUM(F3:F8) -> 8875
D11: INGRESOS VARIABLES (INSTALACION, CONSTRUCCION Y M.O.) JUNIO2026
B12: FECHA | C12: N° REC. | D12: DESCRIPCION | E12: COD | F12: MONTO
B13: 46174 | C13: 1375 | D13: AMANDA USCAMNAYTA HUAMANI. COMPRA DE TUBO1/2 DE AGUA POTABLE | E13: VA | F13: 23
B14: 46174 | C14: 1376 | D14: EUSEBIA USCAMNAYTA HUAMANI. COMPRA DE TUBO1/2 DE AGUA POTABLE | E14: VA | F14: 23
B15: 46174 | C15: 1377 | D15: HERMOGENES USCAMAYTA VERA.ISTALACION DE AGUA POTABLE | E15: IST | F15: 425
B16: 46174 | C16: 1378 | D16: JANEPP ANASTACIA HUAMANI. PAGO POR CONSTRUCCION DE ENERO A JUNIO | E16: CONS | F16: 600
B17: 46177 | C17: 1379 | D17: EFRAIN BLAS MONTALVO. COMPRA DE UN MEDIDOR | E17: VA | F17: 135 | J17: =SUM(F13+F14+F17+F19+F20+F23+F30+F31) -> 422.5
B18: 46178 | C18: 1380 | D18: NULO | E18: NULO | F18: 0
B19: 46179 | C19: 1381 | D19: GIAN MARTINEZ ZAMBRANO. COMPRA DE UN CODO 1/2. UNIVERSAL 1/2 90° Y UN TEFLON | E19: VA | F19: 8.5 | J19: =SUM(F15+INGRESOS!F16+INGRESOS!F22+INGRESOS!F25+INGRESOS!F26+INGRESOS!F27+INGRESOS!F28+INGRESOS!F29) -> 3629
B20: 46182 | C20: 1382 | D20: MARISOL CASTRO HUAMANI. COMPRA DE MEDIDOR | E20: VA | F20: 135
B21: 46182 | C21: 1383 | D21: JORGE HUAMANI URDAY.PAGO POR RECONEXCION DE AGUA POTABLE | E21: RC | F21: 150 | J21: =SUM(F21+F24) -> 300
B22: 46183 | C22: 1384 | D22: YULI TORRES ARUTAYPE. INSTALACION DE DESAGUE | E22: IST | F22: 533
B23: 46183 | C23: 1385 | D23: FAUSTINA MASEDO. COMPRA DE DESAGUE | E23: VA | F23: 18
B24: 46184 | C24: 1386 | D24: YEDY USCAMAYTA. PAGO POR RECONEXION DE AGUA POTABLE | E24: RC | F24: 150 | J24: =SUM(J17+J19+J21) -> 4351.5
B25: 46185 | C25: 1387 | D25: FAUSTINACHUQUIYANQUI. PAGO POR INSTALACION DE AGUA POTABLE | E25: IST | F25: 425
B26: 46185 | C26: 1388 | D26: FAUSTINA CHUQUIYANQUI. PAGO POR INSTALACION DE DESAGUE | E26: IST | F26: 533
B27: 46186 | C27: 1389 | D27: VALENTIN MONTALVO. PAGO POR INSTALACION DE AGUA POTABLE (SIN EL MEDIDOR) | E27: IST | F27: 290
B28: 46186 | C28: 1390 | D28: FAUSTINA CHUQUIYANQUI. PAGO POR INSTALACION DE AGUA POTABLE (SIN EL MEDIDOR) | E28: IST | F28: 290
B29: 46186 | C29: 1391 | D29: VALENTIN MONTALVO. PAGO POR INSTALACION DE DESAGUE | E29: IST | F29: 533
B30: 46189 | C30: 1392 | D30: JUANA SANCHEZ. COMPRA DE CAJA DE MEDIDOR MAS TAPA | E30: VA | F30: 55
B31: 46198 | C31: 1393 | D31: CECILIA FLORES PAGO POR SERVICIO DE AGUA DESDE ENERO HASTA MAYO | E31: VA | F31: 25
F34: =SUM(F13:F33) -> 4351.5
D37: INGRESOS POR GRIFO DE AGUA (JUNIO 2026)
B38: FECHA | C38: N° REC. | D38: DESCRIPCIÓN | E38: COD | F38: MONTO
A39: LUNES | B39: 46174 | C39: 2089 | D39: SERVICIO DE AGUA POTABLE 4 CUBOS. MINERA ORION | E39: GF | F39: 40
B40: 46174 | C40: 2090 | D40: SERVICIO DE AGUA POTABLE 4 CUBOS. MARTHA | E40: GF | F40: 40
B41: 46174 | C41: 2091 | D41: SERVICIO DE AGUA POTABLE 4 CUBOS. MINERA ORION | E41: GF | F41: 40
B42: 46174 | C42: 2092 | D42: SERVICIO DE AGUA POTABLE 3 CUBOS. AGUSTO | E42: GF | F42: 30 | G42: =SUM(F39:F42) -> 150
A43: MARTES | B43: 46175 | C43: 2093 | D43: SERVICIO DE AGUA POTABLE 4 CUBOS. COMEDOR | E43: GF | F43: 40
B44: 46175 | C44: 2094 | D44: SERVICIO DE AGUA POTABLE 4 CUBOS. ORION | E44: GF | F44: 40
B45: 46175 | C45: 2095 | D45: SERVICIO DE AGUA POTABLE 4 CUBOS. MINERA ORION | E45: GF | F45: 40
B46: 46175 | C46: 2096 | D46: SERVICIO DE AGUA POTABLE 4 CUBOS. EMERSON MOLLO | E46: GF | F46: 40 | G46: =SUM(F43:F46) -> 160
A47: MIERCOLES | B47: 46176 | C47: 2097 | D47: SERVICIO DE AGUA POTABLE 5 CUBOS. EMERSON MOLLO | E47: GF | F47: 50
B48: 46176 | C48: 2098 | D48: SERVICIO DE AGUA POTABLE 4 CUBOS. SOL DE LOS ANDES | E48: GF | F48: 40
B49: 46176 | C49: 2099 | D49: SERVICIO DE AGUA POTABLE 4 CUBOS. SOL DE LOS ANDES | E49: GF | F49: 40
B50: 46176 | C50: 2100 | D50: SERVICIO DE AGUA POTABLE 4 CUBOS. SOL DE LOS ANDES | E50: GF | F50: 40
B51: 46176 | C51: 2201 | D51: SERVICIO DE AGUA POTABLE 2 CUBOS. SOL DE LOS ANDES | E51: GF | F51: 20 | G51: =SUM(F47:F51) -> 190
A52: JUEVES | B52: 46177 | C52: 2202 | D52: SERVICIO DE AGUA POTABLE 4 CUBOS. MARTHA | E52: GF | F52: 40
B53: 46177 | C53: 2203 | D53: SERVICIO DE AGUA POTABLE 4 CUBOS. MINERA ORION | E53: GF | F53: 40
B54: 46177 | C54: 2204 | D54: SERVICIO DE AGUA POTABLE 4 CUBOS. JHONSON | E54: GF | F54: 40
B55: 46177 | C55: 2205 | D55: SERVICIO DE AGUA POTABLE 2 CUBOS. JHONSON | E55: GF | F55: 20
B56: 46177 | C56: 2206 | D56: SERVICIO DE AGUA POTABLE 4 CUBOS. KATY | E56: GF | F56: 40 | G56: =SUM(F52:F56) -> 180
A57: VIERNES | B57: 46178 | C57: 2207 | D57: SERVICIO DE AGUA POTABLE 4 CUBOS. COMEDOR | E57: GF | F57: 40
B58: 46178 | C58: 2208 | D58: SERVICIO DE AGUA POTABLE 4 CUBOS. ORION | E58: GF | F58: 40
B59: 46178 | C59: 2209 | D59: SERVICIO DE AGUA POTABLE 3 CUBOS. JHONSON | E59: GF | F59: 30
B60: 46178 | C60: 2210 | D60: SERVICIO DE AGUA POTABLE 3 CUBOS. BRAYAN HUASHUAYO | E60: GF | F60: 30 | G60: =SUM(F57:F60) -> 140
A61: SABADO | B61: 46179 | C61: 2211 | D61: SERVICIO DE AGUA POTABLE 4 CUBOS. MINERA ORION | E61: GF | F61: 40
B62: 46179 | C62: 2212 | D62: SERVICIO DE AGUA POTABLE 2 CUBOS. MARTHA | E62: GF | F62: 20
B63: 46179 | C63: 2213 | D63: SERVICIO DE AGUA POTABLE 2 CUBOS. COMEDOR SHARELI | E63: GF | F63: 20
B64: 46179 | C64: 2214 | D64: SERVICIO DE AGUA POTABLE 1 CUBOS. KATY | E64: GF | F64: 10 | G64: =SUM(F61:F64) -> 90
A65: DOMINGO | B65: 46180 | C65: 2215 | D65: SERVICIO DE AGUA POTABLE 4 CUBOS. COMEDOR SHARELI | E65: GF | F65: 40
B66: 46180 | C66: 2216 | D66: SERVICIO DE AGUA POTABLE 2 CUBOS. MINERA ORION | E66: GF | F66: 20
B67: 46180 | C67: 2217 | D67: SERVICIO DE AGUA POTABLE 1 CUBOS. KATY | E67: GF | F67: 10 | G67: =SUM(F65:F67) -> 70 | I67: =SUM(G42+G46+G51+G56+G60+G64+G67) -> 980
A68: LUNES | B68: 46181 | C68: 2218 | D68: SERVICIO DE AGUA POTABLE 2 CUBOS. COMEDOR SHARELI | E68: GF | F68: 20
B69: 46181 | C69: 2219 | D69: SERVICIO DE AGUA POTABLE 5 CUBOS. CECAR MOLLO | E69: GF | F69: 50
B70: 46181 | C70: 2220 | D70: SERVICIO DE AGUA POTABLE 6 CUBOS. EMERSON | E70: GF | F70: 60 | G70: =SUM(F68:F70) -> 130
A71: MARTES | B71: 46182 | C71: 2221 | D71: SERVICIO DE AGUA POTABLE 4 CUBOS. MARTHA | E71: GF | F71: 40
B72: 46182 | C72: 2222 | D72: SERVICIO DE AGUA POTABLE 4 CUBOS. COMEDOR AUGUSTO | E72: GF | F72: 40 | G72: =SUM(F71:F72) -> 80
A73: MIERCOLES | B73: 46183 | C73: 2223 | D73: SERVICIO DE AGUA POTABLE 4 CUBOS. COMPANIA CIMARS | E73: GF | F73: 40 | G73: =SUM(F73) -> 40
A74: JUEVES | B74: 46184 | C74: 2224 | D74: SERVICIO DE AGUA POTABLE 2 CUBOS. COMEDOR | E74: GF | F74: 20
B75: 46184 | C75: 2225 | D75: SERVICIO DE AGUA POTABLE 1 CUBOS. HECTOR TORRES | E75: GF | F75: 10
B76: 46184 | C76: 2226 | D76: SERVICIO DE AGUA POTABLE 1 CUBOS. FAUSTO HUAMANI | E76: GF | F76: 10
B77: 46184 | C77: 2227 | D77: SERVICIO DE AGUA POTABLE 3 CUBOS. COMEDOR AUGUSTO | E77: GF | F77: 30 | G77: =SUM(F74:F77) -> 70
A78: VIERNES | B78: 46185 | C78: 2228 | D78: SERVICIO DE AGUA POTABLE 3 CUBOS. COMEDOR | E78: GF | F78: 30
B79: 46185 | C79: 2229 | D79: SERVICIO DE AGUA POTABLE 1 CUBO. DESI SIVINCHA | E79: GF | F79: 10
B80: 46185 | C80: 2230 | D80: SERVICIO DE AGUA POTABLE 6 CUBOS. EMERSON | E80: GF | F80: 60 | G80: =SUM(F78:F80) -> 100
A81: SABADO | B81: 46186 | C81: 2231 | D81: SERVICIO DE AGUA POTABLE 1 CUBO. ROLO ESCOBAR | E81: GF | F81: 10
B82: 46186 | C82: 2232 | D82: SERVICIO DE AGUA POTABLE 3 CUBOS. COMEDOR | E82: GF | F82: 30
B83: 46186 | C83: 2233 | D83: SERVICIO DE AGUA POTABLE 4 CUBOS. COMEDOR | E83: GF | F83: 40
B84: 46186 | C84: 2234 | D84: SERVICIO DE AGUA POTABLE 4 CUBOS. EMERSON | E84: GF | F84: 40 | G84: =SUM(F81:F84) -> 120
A85: DOMINGO | B85: 46187 | C85: 2235 | D85: SERVICIO DE AGUA POTABLE 4 CUBOS. CERRITO PECOY VICTOR | E85: GF | F85: 40
B86: 46187 | C86: 2236 | D86: SERVICIO DE AGUA POTABLE 4 CUBOS. COMEDOR | E86: GF | F86: 40
B87: 46187 | C87: 2237 | D87: SERVICIO DE AGUA POTABLE 4 CUBOS. JHONSON ARAGON | E87: GF | F87: 40
B88: 46187 | C88: 2238 | D88: SERVICIO DE AGUA POTABLE 4 CUBOS. COMEDOR SHARELI | E88: GF | F88: 40 | G88: =SUM(F85:F88) -> 160 | I88: =SUM(G70+G72+G73+G77+G80+G84+G88) -> 700
A89: LUNES | B89: 46188 | C89: 2239 | D89: SERVICIO DE AGUA POTABLE 4 CUBOS. COMEDOR | E89: GF | F89: 40
B90: 46188 | C90: 2240 | D90: SERVICIO DE AGUA POTABLE 2 CUBOS. MINERA ORION | E90: GF | F90: 20
B91: 46188 | C91: 2241 | D91: SERVICIO DE AGUA POTABLE 7 CUBOS. MINERA SOL DE LOS ANDES | E91: GF | F91: 70
B92: 46188 | C92: 2242 | D92: SERVICIO DE AGUA POTABLE 5 CUBOS. CECAR MOLLO | E92: GF | F92: 50
B93: 46188 | C93: 2243 | D93: SERVICIO DE AGUA POTABLE 7 CUBOS. SOL DE LOS ANDES | E93: GF | F93: 70 | G93: =SUM(F89:F93) -> 250
A94: MARTES | B94: 46189 | C94: 2244 | D94: SERVICIO DE AGUA POTABLE 4 CUBOS. COMEDOR | E94: GF | F94: 40
B95: 46189 | C95: 2245 | D95: SERVICIO DE AGUA POTABLE 4 CUBOS. COMEDOR SHARELI | E95: GF | F95: 40
B96: 46189 | C96: 2246 | D96: SERVICIO DE AGUA POTABLE 7 CUBOS. MINERA OREX | E96: GF | F96: 70
B97: 46189 | C97: 2247 | D97: SERVICIO DE AGUA POTABLE 2 CUBOS. RICHAR | E97: GF | F97: 20
B98: 46189 | C98: 2248 | D98: SERVICIO DE AGUA POTABLE 1 CUBO. JUAN | E98: GF | F98: 10 | G98: =SUM(F94:F98) -> 180
A99: MIERCOLES | B99: 46190 | C99: 2249 | D99: SERVICIO DE AGUA POTABLE 4 CUBOS. JHONSON ARAGON | E99: GF | F99: 40
B100: 46190 | C100: 2250 | D100: SERVICIO DE AGUA POTABLE 4 CUBOS. COMEDOR | E100: GF | F100: 40
B101: 46190 | C101: 2251 | D101: SERVICIO DE AGUA POTABLE 2 CUBOS. JHONSON ESCOBAR | E101: GF | F101: 20
B102: 46190 | C102: 2252 | D102: SERVICIO DE AGUA POTABLE 3 CUBOS. JHONSON ESCOBAR | E102: GF | F102: 30 | G102: =SUM(F99:F102) -> 130
A103: JUEVES | B103: 46191 | C103: 2253 | D103: SERVICIO DE AGUA POTABLE 3 CUBOS. JHONSON ARAGON | E103: GF | F103: 30 | G103: =SUM(F103) -> 30
A104: VIERNES | B104: 46192 | C104: 2254 | D104: SERVICIO DE AGUA POTABLE 4 CUBOS. MARTHA | E104: GF | F104: 40
B105: 46192 | C105: 2255 | D105: SERVICIO DE AGUA POTABLE 3 CUBOS. JHONSON ESCOBAR | E105: GF | F105: 30
...

Sheet EGRESOS
B2: EGRESOS DEL MES DE JUNIO 2026
B3: FECHA | C3: N° REC | D3: DESCRIPCION | E3: COD | F3: MONTO
B4: 46174 | C4: 321 | D4: REY HUAMANI ALVARES. DEVOLUCION DE RECIBO N°533055 Y N°56260 | E4: MO | F4: 37
B5: 46174 | C5: 3605140 | D5: PAGO DE LUZ SEAL POR EL MES DE ABRIL Y MARZO 2026 | E5: SB | F5: 77.4
B6: 46176 | C6: BOL. | D6: ESTACIONES SUR ANDINA. GASOLINA | E6: CT | F6: 50
B7: 46176 | C7: REC | D7: COMUNICADO SOBRE CIERRE DE VIA DESDE GRAS SINTETICO HASTA MOYKEY POR AMPLIACION DE RED DE AGUA POTABLE | E7: RD | F7: 75
B8: 46176 | C8: N/P | D8: 2 GASEOSAS . 1 AGUA | E8: MO | F8: 35
B9: 46176 | C9: REC | D9: COMUNICADO SOBRE CIERRE DE VIA DESDE RADIO CARISMA HACIE ARRIBA POR REPARACION DE AVERIA DE TUBERIA | E9: RD | F9: 15
B10: 46176 | C10: 322 | D10: TAXI CRISTIAN NAVINTA. TRASLADO DE EQUIPOS ALQUILADOS GENERADOR.ROTOMATILLO | E10: TX | F10: 50 | J10: AL | L10: =SUM(F13+F19+F41+F43+F60) -> 589.5
B11: 46176 | C11: 323 | D11: TAXI CRISTIAN NAVINTA. TRASLADO DE PERSONAL ASILLO 25-05-2026 Y RECOJO DE PERSONAL DE SANTA ROSA TURNO NOCHE 01-06-2026 | E11: TX | F11: 200 | J11: CT | L11: =SUM(F6+F25+F38) -> 135
B12: 46176 | C12: 324 | D12: GARY SALAR DONMIGEZ. PAGO DE PERSONAL POR PURGAR AGUA DE ASILLO 25-05-2026 Y 01-06-2026 | E12: SC | F12: 400 | J12: TX | L12: =SUM(F10+F11+F14+F16+F27+F32+F39+F49+F52+F55+F57+F58+F62+F63+F65+F66+F68+F70+F72+F76) -> 1025
B13: 46178 | C13: N/P | D13: 1 AGUA DE 3LT. GASEOSA DE 3LT | E13: AL | F13: 22.5 | J13: RE | L13: =SUM(F35) -> 2000
B14: 46178 | C14: 325 | D14: TAXI ELVIS TORRES. TRASLADO DE HERRAMIENTAS PACHAYZA A OFICCINA CAAPD | E14: TX | F14: 20
B15: 46181 | C15: N/P | D15: ALIMENTACION POR CONSUMO DE TRABAJADORES PARA EL MANTENIMIENTO DEL PTAR | E15: AL | F15: 695
B16: 46181 | C16: 326 | D16: TAXI YORDI LIBAQUE. PARA EL TRASLADO DE MATERIALES OFICINA A PACHAYZA | E16: TX | F16: 15 | J16: LC | L16: =SUM(F21+F28+F29+F34) -> 800
B17: 46181 | C17: 327 | D17: CARLOS CHAUCAYANQUI. PAGO A PERSONAL POR ARREGLO DE TUBERIA EN EL SECTOR DE PACHAYZA | E17: SC | F17: 100 | J17: SC | L17: =SUM(F12+F17+F18+F23+F26+F31+F37+F46+F47+F48+F50+F53+F64+F67+F71+F74+F75) -> 7440
B18: 46181 | C18: 328 | D18: GARY SALAR DONMIGEZ. PAGO DE PERSONAL POR ARREGLODE TUBERIA EN EL SECTOR DE PACHAYZA | E18: SC | F18: 100 | J18: OF | L18: =SUM(F4+F8+F20+F40+F42+F44+F51+F54+F56+F61) -> 644.5
B19: 46181 | C19: BOL. | D19: 2 ALMUERZOS. POR ARREGLO DE TUBERIA | E19: AL | F19: 20 | J19: M | L19: =SUM(F24+F59+F73) -> 1270
B20: 46181 | C20: BOL. | D20: 1 GASEOSA.1PQTE DE GALLETAS.1 ENCENDEDOR | E20: MO | F20: 18.5 | J20: RD | L20: =SUM(F7+F9+F69) -> 180
B21: 46181 | C21: 329 | D21: LECTURADO DEL MES DE MAYO.YOBANA USCAMAYTA 01-06-26 Y 02-06-2026 | E21: LC | F21: 200 | J21: SB | L21: =SUM(F5+F30) -> 207.4
B22: 46182 | C22: 330 | D22: NULO | E22: NULO | F22: 0
B23: 46182 | C23: 331 | D23: GARY MACOY PAGO A PERSONAL (2) POR DESCARGAR MATERIALES Y ACCESORIOS | E23: SC | F23: 160 | L23: =SUM(L10:L21) -> 14291.4
B24: 46182 | C24: REC | D24: PAGO POR HORAS DE MAQUINARIA (4H) RETRO420 | E24: M | F24: 800
B25: 46182 | C25: BOL. | D25: COMPRA DE GASOLINA PARA LA CUATRIMOTO | E25: CT | F25: 50
B26: 46183 | C26: 332 | D26: PAGO A PERSONAL POR ESCARBO DE MEDIDOR (CORTE) | E26: SC | F26: 50
B27: 46183 | C27: 333 | D27: TAXI KENJI LIBAQUE. TRASLADO DE MATERIALES (FIERROS Y ALAMBRES) PARA CONSTRUCCION DE ROMPEPRESION | E27: TX | F27: 40
B28: 46183 | C28: 334 | D28: LECTURADO DEL MES DE MAYO.LUIS TORRES 01-06-26 Y 02-06-2026 | E28: LC | F28: 200
B29: 46183 | C29: 335 | D29: LECTURADO DEL MES DE MAYO.NELSON TORRES 01-06-26 Y 02-06-2026 | E29: LC | F29: 200
B30: 46184 | C30: BOL. | D30: PAGO DEL SERVICIO DE INTERNET MES DE MAYO | E30: SB | F30: 130
B31: 46185 | C31: 336 | D31: CARLOS CHAUCAYANQUI. PAGO A PERSONAL POR PURGAR LA RED MATRIZ DE ASILLO | E31: SC | F31: 50
B32: 46185 | C32: 337 | D32: TAXI JORGE.TRASLADO IDA Y VUELTA DE PERSONAL PARA PURGAR EL AGUA DE LA RED MATRIZ DE ASILLO | E32: TX | F32: 100
B33: 46185 | C33: 338 | D33: NULO | E33: NULO | F33: 0
B34: 46185 | C34: 339 | D34: LECTURADO DEL MES DE MAYO.JAMES TORRES 01-06-26 Y 02-06-2026 | E34: LC | F34: 200
B35: 46185 | C35: 340 | D35: REMUNERACION SECRETRARIA MES DE MAYO | E35: RE | F35: 2000
B36: 46186 | C36: 341 | D36: NULO | E36: NULO | F36: 0
B37: 46186 | C37: 342 | D37: CARLOS CHAUCAYANQUI. PAGO A POR AMPLIACION DE LA RED DE MATRIZ PACHAYZA 25/05/26 AL 05/06/26 11 DIAS | E37: SC | F37: 1320
B38: 46188 | C38: BOL. | D38: GASOLINA PARA CUATRIMOTO | E38: CT | F38: 35
B39: 46188 | C39: N/P | D39: TAXI TRASLADO DE PERSONAL HACIA LUCMANI PARA REVISAR RED MATRIZ | E39: TX | F39: 30
B40: 46189 | C40: N/P | D40: 1 PAQ DE AGUA 600ML | E40: MO | F40: 24
B41: 46189 | C41: N/P | D41: 4 ALMUERZOS. 1 COCA COLA 3L. 1 COCA COLA DE 1LT. POR ARREGLO DE TUBERIA EN PACHAYZA | E41: AL | F41: 60
B42: 46189 | C42: N/P | D42: CLAVOS DE 2 Y 4 . PARA TRABAJOS DE ROMPE PRESION | E42: MO | F42: 39
B43: 46190 | C43: N/P | D43: 3 ALMUERZO. GASEOSA | E43: AL | F43: 43
B44: 46190 | C44: N/P | D44: 2 LAMPA TROMONTINA. 2K CALVO3.2K CLAVO4 | E44: MO | F44: 112
B45: 46191 | C45: 343 | D45: NULO | E45: NULO | F45: 0
B46: 46191 | C46: 344 | D46: CARLOS CHAUCAYANQUI PAGO A PERSONAL POR ARREGLAR TUBERIA 15-06-26, 16-06-26 Y 17-06-26 | E46: SC | F46: 340
B47: 46192 | C47: 345 | D47: EDGAR YANQUI QUISPE. TRASLADO DE TUBERIA Y FIERROS IDA Y VUELTA DE OFICINA A PACHAYZA Y PACHAYZA A OFICINA | E47: SC | F47: 70
B48: 46192 | C48: 346 | D48: WALTER MAMANI ALE. ALQUILER DE ROTOMARTILLO 15-06-26 | E48: SC | F48: 70
B49: 46195 | C49: 347 | D49: TAXI ANTHONY SILVA TRASLADO DE OFICINA A PACHAYZA PARTE BAJA VERIFICACION DE AGUA 19-06-26 | E49: TX | F49: 30
B50: 46196 | C50: 348 | D50: PAGO A PERSONAL DE LIMPIEZA. MES DE MAYO LIVIA SURCO ANCCO | E50: SC | F50: 320 | H50: 640
B51: 46197 | C51: BOL. | D51: 1 GALON DE PINTURA SOTINADO ARDICO MOTIZADO | E51: MO | F51: 70
B52: 46197 | C52: 349 | D52: TAXI LUIS COA HUAMANI TRASLADO PARA PACHAYZA PARTE BAJA Y RESERVORIO | E52: TX | F52: 40
B53: 46197 | C53: 350 | D53: PAGO POR AMPLIACION DE LA RED DE MATRIZ PACHAYZA 25/05/26-03/06/26-05/06/26 3 DIAS | E53: SC | F53: 360
B54: 46198 | C54: N/P | D54: TOMA CORRIENTE. CORTA CABLE . ENCHUFE .30MT DE CABLE #14. UN DESTORNILLADOR | E54: MO | F54: 273
B55: 46198 | C55: 351 | D55: TAXI GROBER CASTILLO YOGA. TARAPATA PARA OFICINA. OFICINA A TARAPATA Y ESPERA DE 1H | E55: TX | F55: 60
B56: 46198 | C56: N/P | D56: 2GASEOSAS. 1 AGUA PARA ARREGLO EN PACHAYZA | E56: MO | F56: 33
B57: 46198 | C57: 352 | D57: TAXI PARA TRASLADAR MATERIALES DE OFICINA A PACHAYZA TARAPATA ARREGLO DE TUBERIA. JESUS CABRERA | E57: TX | F57: 30
B58: 46198 | C58: 353 | D58: TAXI PACHAYZA PARTE BAJA A PLAZA IDA Y VUELTA. GROBER CASTILLO | E58: TX | F58: 30
B59: 46198 | C59: 354 | D59: ALQUILER DE MAQUINARIA 2H 27-05-26. CELI TORRES | E59: M | F59: 400
B60: 46198 | C60: 355 | D60: ALMUERZOS POR AMPLIACION DE MATRIZ EN PACHAYZA 26-05.26 AL 05-06-26 | E60: AL | F60: 444
B61: 46198 | C61: N/P | D61: COMPRA DE PRODUCTO DE LIMPIEZA | E61: MO | F61: 3
B62: 46199 | C62: 356 | D62: TAXI PARA TRASLADAR MATERIALES Y COMPRA DE CEMENTO . CRISTIAN | E62: TX | F62: 50
B63: 46199 | C63: 357 | D63: TAXI PARA TRASLADO DE PERSONAL Y MATERIALES PALAS TUBO PARA OFICINA | E63: TX | F63: 10
B64: 46203 | C64: 358 | D64: PAGO A PERSONAL POR AYUDANTE DE ESCARBO DE SANJA EN PAMPA 25-06-26 Y 26-06-26 | E64: SC | F64: 220
B65: 46203 | C65: 359 | D65: TAXI IDA Y VUELTA HACIA HUAQUILLO PARA INTALACION CON ESPERA | E65: TX | F65: 30
B66: 46203 | C66: 360 | D66: TAXI TRASLADO DE PERSONAL PARA VERIFICAR NUEVA RED DE AGUA POTABLE EN LUCMANI | E66: TX | F66: 15
B67: 46203 | C67: 361 | D67: PAGO A PERSONAL POR AMPLIACION DE NUEVA MATRIZ DE AGUA POTABLE EN PACHAYZA 25-05-26 AL 05-06-26 (MENOS DOS DIAS) | E67: SC | F67: 1500
B68: 46203 | C68: 362 | D68: TAXI PARA TARAPATA TRASLADO DE MATERIALES IDA Y VUELTA MAS ESPERA | E68: TX | F68: 40
B69: 46203 | C69: REC | D69: COMUNICADO PARA ASAMBLEA GENERAL EL DIA 28-06-26 | E69: RD | F69: 90
B70: 46203 | C70: 363 | D70: TAXI TRASLADO DE PERSONAL PARA PURGAR AGUA EN ASILLO 27-06-26 | E70: TX | F70: 100
B71: 46203 | C71: 364 | D71: PAGO A PERSONAL (2 PERSONAS) POR PURGAR AGUA DE ASILLO 26-06-26 Y 27-06-206 | E71: SC | F71: 280
B72: 46203 | C72: 365 | D72: TAXI PARA TRASLADO DE PERSONAL PARA PURGAR AGUA EN ASILLO 26-06-26 | E72: TX | F72: 100
B73: 46203 | C73: 366 | D73: ALQUILER DE ROTOMARTILLO PARA SANJA EN PACHAYZA ARREGO DE TUBERIA 25-06-26 | E73: M | F73: 70
B74: 46203 | C74: 367 | D74: PAGO A PERSONAL POR AMPLIACION DE NUEVA MATRIZ DE AGUA POTABLE EN PACHAYZA 25-05-26 AL 05-06-26 (10 DIAS) | E74: SC | F74: 1800
B75: 46203 | C75: 368 | D75: MAMTEMIMIENTO DE BUZON DE DESAGUE EN PACHAYZA 07-06-26 | E75: SC | F75: 300
B76: 46203 | C76: 369 | D76: TAXI PARA TRASNPOTARTAR (PARLANTE, MESAS, SILLAS) PARA REUNION GENERAL IDA Y VUELTA PACHAYZA A OFICINA 28-06-26 | E76: TX | F76: 35
D78: TOTAL DE EGRESOS | F78: =SUM(F4:F77) -> 14986.4
B83: EGRESOS DE MOVILIDAD PARA MANTENIMIENTO DEL PETAR Y OTROS. JUNIO 2026
B84: FECHA | C84: N° REC | D84: DESCRIPCION | E84: COD | F84: MONTO
D101: TOTAL DE EGRESOS | F101: =SUM(F85:F100) -> 0
D104: COMPRA DE MATERIALES 2024
B105: FECHA | C105: N° | D105: DESCRIPCION | F105: MONTO
D110: TOTAL DE GASTOS | F110: =SUBTOTAL(109,F106:F109) -> 0

Sheet RESUMEN JUNIO
D1: RESUMEN DE CAJA CHICA MES JUNIO 2026
E4: INGRESOS | G4: MONTO | I4: rellenar
C5: COBRO DE RECIBOS
D6: Chaupi | E6: 147 | F6: 4397.5 | G6: =F5+F6+F7+F8+F9+F10+F11 -> 8875
D7: Pachayza | E7: 132 | F7: 3615.5
D8: Lucmani | E8: 25 | F8: 604
D9: Huaquillo | E9: 11 | F9: 214
D10: Ayacucho | E10: 1 | F10: 6.5
D11: Chaupicerca | E11: 4 | F11: 37.5
D12: USUARIOS | E12: =SUM(E6:E11) -> 320
C13: INGRESO VARIABLE (Instalaciones, x construccion, M. O.) | G13: 3629
C14: MULTAS (reconexion) | G14: 300
C15: VENTAS DE ACCESORIOS Y TUBOS | G15: 422.5
C16: INGRESO GRIFO DE AGUA | G16: 4230
C17: COPIAS E IMPRESIONES, DOCUMENTOS | G17: 56
F18: INGRESO TOTAL | G18: =SUM(G6:G17) -> 17512.5
E20: EGRESOS | G20: MONTO
C21: ALIMENTACION (directiva, personal y otros) | G21: 1284.5
C22: CUATRIMOTO (gasolina ) | G22: 135
C23: MATERIALES Y/O ACCESORIOS (lampara, toma corriente y otros) | G23: 644.5
C24: MOVILIDAD (servicio de taxis) | G24: 1025
C25: MAQUINARIA ( alquiler de retro excabadora, rotomartillo ) | G25: 1270
C26: REMUNERACION (secretaria ) | G26: 2000
C27: LECTURADOS (pago a personal) | G27: 800
C28: SERVICIOS CONTRATADOS ( personal de apoyo,peones, servicio de limpieza, otros) | G28: 7440
C29: SERVICIOS BASICOS ( luz,internet ) | G29: 207.4
C30: COMUNICADOS EN LA RADIO | G30: 180
F32: EGRESO TOTAL | G32: =SUM(G21:G30) -> 14986.4
F34: SALDO | G34: =G18-G32 -> 2526.1

Sheet CORTE
A1: USUARIOS EN CORTE
A3: CONEXIÓN | B3: N° MEDIDOR | C3: BARRIO | D3: BENEFICIARIO | E3: DIRECCIÓN | F3: OBSERVACIONES
A4: 000531 | B4: 6563939 | C4: AYACUCHO | D4: TORRES HUAMANI,AMELIA BENITA | E4: S/N | F4: OCT-NOV-DIC S/21.00 CORTE | H4: CORTE
A5: 000669 | B5: 21003048 | C5: LUCMANI | D5: CHAVEZ ANTACHOQUE HENRRY | E5: SECTOR JENCHO | F5: OCT-NOV-DIC S/78.50 CORTE | H5: CORTE
A6: 000691 | B6: 21000863 | C6: LUCMANI | D6: GUTIERREZ CHALCO REYNALDO ROBERTO | E6: LUCMANI S/N | F6: SET-OCT-NOV-DIC S/20.00 CORTE | H6: CORTE
A7: 000023 | B7: 21000864 | C7: LUCMANI | D7: HUAMANI COA,LUCIO INGNACIO | E7: LUCMANI S/N | F7: OCT-NOV-DIC S/65.50 CORTE | H7: CORTE
A8: 000032 | B8: 6572092 | C8: LUCMANI | D8: LUQUE VERA,ELISA LURDES | E8: LUCMANI S/N | F8: OCT-NOV-DIC S/31.00 CORTE | H8: CORTE
A9: 000047 | B9: 6660664 | C9: LUCMANI | D9: PALOMINO NEYRA,JUSTINA LUZ | E9: LUCMANI S/N | F9: OCT-NOV-DIC S/34.50 CORTE | H9: CORTE
A10: 000049 | B10: 6591593 | C10: LUCMANI | D10: RAMIREZ HUAMANI,MARIA LETICIA | E10: LUCMANI S/N | F10: SET-OCT-NOV-DIC S/20.00 CORTE | H10: CORTE
A11: 000498 | B11: 60062505 | C11: CHAUPI | D11: ALFARO NEYRA DE CHUQUIYANQUI LUCIA POMPEYA | E11: PASAJE SAN ISIDRO S/N | F11: OCT-NOV-DIC S/15.00 CORTE | H11: CORTE
A12: 000278 | B12: 60062464 | C12: CHAUPI | D12: ANTACHOQUE NAVINTA ,LETDY EVANIA | E12: CALLE CUYO CUYO S/N | F12: SET-OCT-NOV-DIC S/20.00 CORTE | H12: CORTE
A13: 000283 | B13: 6562501 | C13: CHAUPI | D13: AYMARA ALFARO ,FROILAN ANDRES | E13: CALLE 28 DE JULIO S/N | F13: OCT-NOV-DIC S/114.50 CORTE | H13: CORTE
A14: 000300 | B14: 60061426 | C14: CHAUPI | D14: CATEDRAL DE LA COMUNIDAD DE ISPACAS | E14: CALLE CUYO CUYO S/N | F14: SET-OCT-NOV-DIC S/ 132.00 CORTE | H14: CORTE
A15: 000301 | B15: 6562439 | C15: CHAUPI | D15: CHALCO ESCOBAR ,CALIXTO EUGENIO | E15: LUCMANI S/N | F15: OCT-NOV-DIC S/15.00 CORTE | H15: CORTE
... A95: 000740 | B95: 23022182 | C95: PACHAYZA | D95: VERA SIVINCHA, ANDRES PEDRO | E95: AHUINTA-PACHAYZA | F95: OCT-NOV-DIC S/65.50 CORTE | H95: CORTE
A97: USUARIOS EN CONSTRUCCIÓN POR USO DE AGUA
A99: CONEXIÓN | B99: N° MEDIDOR | C99: BARRIO | D99: BENEFICIARIO | E99: DIRECCIÓN | F99: OBSERVACIONES
A100: 000043 | B100: 6578514 | C100: LUCMANI | D100: NEIRA DE ROMERO,EDUARDA FERNANDINA | E100: LUCMANI S/N | F100: CONSTRUCCION SET-OCTUBRE
A101: 000694 | B101: 21130885 | C101: CHAUPI | D101: CHAVEZ TORRES CASTOR MILTON | E101: CALLE 5 DE AGOSTO S/N | F101: CONSTRUCCION MES DE ENERO
A102: 000340 | B102: 60061410 | C102: CHAUPI | D102: CRUZ MANCILLA ,NOYA SAIDA | E102: AVENIDA AVIACION S/N | F102: CONSTRUCCION MES DE ENERO
A103: 000605 | B103: 190005360 | C103: CHAUPI | D103: HUAMANI ESCOBAR AYNETH | E103: CALLE 28 DE JULIO | F103: CONSTRUCCION MES DE ENERO
A104: 000363 | B104: 23022175 | C104: CHAUPI | D104: HUAMANI ALVAREZ ,NELIDA LUZ | E104: LUCMANI S/N | F104: COSTRUCCIÓN SETIEMBRE OCTUBRE
A105: 000586 | B105: 09093268 | C105: CHAUPI | D105: ANTACHOQUE ESCOBAR, FANY KELIDA | E105: LUCMANI S/N | F105: CONSTRUCCIÓN MES DE JUNIO - JULIO
A106: 000290 | B106: 6573791 | C106: CHAUPI | D106: LLERENA MONTALVO DE CARPIO MAXIMILIANA | E106: CALLE LOS ESTUDIANTES S/N | F106: CONSTRUCCION MES SOLO ENERO, SOLO JUNIO.
A107: 000705 | B107: 23013263 | C107: CHAUPI | D107: MANCILLA VERA SUSY MARIBEL | E107: CALLE 5 DE AGOSTO S/N | F107: CONSTRUCCION MES DE ENERO
A108: 000508 | B108: 60062489 | C108: CHAUPI | D108: USCAMAYTA HUAMANI ,JESUS | E108: CALLE JUAN USCAMAYTA S/N | F108: CONSTRUCCION MES DE ENERO
A109: 000295 | B109: 6590154 | C109: CHAUPI | D109: CASTRO HUAMANI ,LEONCIO | E109: CHAUPI | F109: CONSTRUCCION
A110: 000558 | B110: 10786 | C110: CHAUPI | D110: HUAMANI HUAMANI,JANETT ANASTACIA | E110: CALLE EL OLVIDO S/N | F110: CONSTRUCCION MES DE OCTUBRE,NOVIEMBRE
... A137: 000259 | B137: 6587730 | C137: PACHAYZA | D137: RAMIREZ USCAMAYTA, JAIME MAURO | E137: SECTOR PACHAYZA -TARAPATA | F137: CONSTRUCCIÓN AGOSTO
A140: USUARIOS CON MEDIDORES ENTERRADOS, SEGUIMIENTO, MALOGRADOS, LIMPIAR MEDIDOR,CAMBIO DE MEDIDOR
A142: CONEXIÓN | B142: N° MEDIDOR | C142: BARRIO | D142: BENEFICIARIO | E142: DIRECCIÓN | F142: OBSERVACIONES | G142: RESP.
A143: 000741 | B143: 22115452 | C143: CHAUPI | D143: CHALCO MONTALVO, GLORIA VICTORIA | E143: CALLE VIRGEN DE LAS NIEVES S/N | F143: ENTERRADO
A144: 000654 | B144: 200005319 | C144: CHAUPI | D144: CHALCO MONTALVO, YOBANA DEBORA | E144: CALLE 5 DE AGOSTO | F144: ENTERRADO
A145: 000770 | B145: 22393000 | C145: CHAUPI | D145: CORTES ZURITA, JUAN FRANSISCO | E145: LUCMANI S/N | F145: ENTERRADO
A146: 000419 | B146: 6558327 | C146: CHAUPI | D146: MONTALVO HUAMANI ,JANO JUAN | E146: CALLE SAN SEBASTIAN S/N | F146: REGISTRO DE DESAGUE MALOGRADO
A147: 000363 | B147: 23022175 | C147: CHAUPI | D147: HUAMANI ALVAREZ ,NELIDA LUZ | E147: LUCMANI S/N | F147: ENTERRADO
A148: 000508 | B148: 60062489 | C148: CHAUPI | D148: USCAMAYTA HUAMANI ,JESUS | E148: CALLE JUAN USCAMAYTA S/N | F148: ENTERRADO
A149: 000729 | B149: 220017506 | C149: CHAUPI | D149: USCAMAYTA MONTALVO, MARITA BERNA | E149: CALLE JUAN USCAMAYTA S/N | F149: ENTERRADO
A150: 000754 | B150: 22393040 | C150: CHAUPI | D150: HUAMANI , LUZ HAYDE | E150: PSJ VIRGEN DE LAS NIEVES | F150: ENTERRADO
A151: 000638 | B151: 200002890 | C151: CHAUPI | D151: TILLCA MENDOZA YANED | E151: CALLE AVIACION S/N | F151: ENTERRADO
A152: 000590 | B152: 200031257 | C152: CHAUPI | D152: USCAMAYTA HUAMANI, YEDY | E152: CALLE SAN SEBASTIAN S/N | F152: ENTERRADO
A153: 000620 | B153: 2001885 | C153: LUCMANI | D153: MONTALVO NEIRA MARTINA DEFILIA | E153: LUCMANI S/N | F153: ENTERRADO
A154: 000133 | B154: 6584533 | C154: PACHAYZA | D154: CORIMANYA HUAMANI ,JUAN | E154: SECTOR PACHAYZA - PARTE BAJA | F154: MEDIDOR ENTERRADO(SIEMPRE)
... A159: 000626 | B159: 2001834 | C159: PACHAYZA | D159: GRUPO JAMPRA S.A.C | E159: PACHAYZA-PARTE BAJA | F159: MEDIDOR ENTERRADO-LIMPIAR
A160: 000648 | B160: 200011827 | C160: PACHAYZA | D160: HUACPI HUAMANI ,DANIA UDELIZ | E160: SECTOR PACHAYZA - PUCRO | F160: CAMBIAR MEDIDOR | G160: JAMES
A161: 000178 | B161: 6593627 | C161: PACHAYZA | D161: MANSILLA CASTRO, EULOGIA LEANDRA | E161: SECTOR PACHAYZA - HUAYCHA | F161: MEDIDOR ENTERRADO(LEVANTAR MEDIDOR PARA QUE SE PUEDA LECTURAR) | G161: JAMES
A162: 000168 | B162: 6585742 | C162: PACHAYZA | D162: HUAMANI YLATAIPE ,WILSON CHARLES | E162: SECTOR PACHAYZA - PUCRO | F162: ENTERRADO | G162: JAMES
A163: 000129 | B163: 240000344 | C163: PACHAYZA | D163: TORRES VERA LEONARDO SALOMON | E163: SECTOR PACHAYZA - PARTE ALTA | F163: ENTERRADO
A164: 000246 | B164: 6585536 | C164: PACHAYZA | D164: TORRES VERA,VICTOR GAMALIEL | E164: SECTOR PACHAYZA - PARTE BAJA | F164: MEDIDOR ENTERRADO | G164: JAMES
A166: USUARIOS FALTA FIRMAR Y ENTREGAR CONTRATO DE INSTALACIÓN DE AGUA Y DESAGUE
A168: CONEXIÓN | B168: N° MEDIDOR | C168: BARRIO | D168: BENEFICIARIO | E168: DIRECCIÓN | F168: OBSERVACIONES | G168: CHEC
A169: 000756 | B169: 22393037 | C169: LUCMANI | D169: ZAPANA MANSILLA , GUSTAVO RAUL | E169: AUCAYPATA | F169: FALTA FIRMAR POR EL TITULAR Y ENTREGAR.
A170: 000760 | B170: 22392839 | C170: PACHAYZA | D170: CHUQUIYANQUI ALFARO , NILTON | E170: PACHAYZA | F170: FALTA FIRMAR POR EL TITULAR Y LUIS, ENTREGAR.
A171: 000761 | B171: 22392838 | C171: PACHAYZA | D171: MENESES ANTACHOQUE , DAMARIS THAID | E171: JARACHINE | F171: FALTA FIRMAR POR EL TITULAR Y LUIS, ENTREGAR.
A172: 000186 | B172: 6593442 | C172: PACHAYZA | D172: MONTALVO HUAMANI PEREGRINA | E172: SECTOR PACHAYZA -TARAPATA | F172: PREGUNTAR A LUIS,POR QUE FALTA CONTRATO.
A173: …... | B173: 22393039 | C173: CHAUPI | D173: SILVIA GLADYS HUAMANI HUAMANI | E173: PASAJE VIRGEN DE LAS NIEVES | F173: FALTA FIRMARPOR EL TITULAR Y ENTREGAR.
A174: 000759 | B174: 22392840 | C174: CHAUPI | D174: LOPEZ RAMIREZ , JULIA FELICIANA | E174: CALLE 28 DE JULIO S/N | F174: FALTA FIRMAR POR EL TITULAR Y ENTREGAR
A175: 000244 | B175: 6578308 | C175: PACHAYZA | D175: TORRES VERA,JHON ADALID | E175: SECTOR PACHAYZA | F175: FALTA FIRMAR CONTRATO DE DESAGUE Y ENTREGAR
B176: 22392865 | C176: PACHAYZA | D176: TORRES VERA, LIBIA MARLENY | E176: AWINTA S/N | F176: FALTA FIRMAR POR EL TITULAR Y ENTREGAR
C177: CHAUPI | D177: CARMEN QUISPE ALLCA. | E177: CHAUPI | F177: FALTA FIRMAR POR EL TITULAR Y ENTREGAR
B178: 22393003 | C178: PACHAYZA | D178: PILAR AMERICA NAVINTA ALFARO | E178: AWINTA S/N | F178: CONTRATO DE AGUA Y DESAGUE, ENTREGAR Y FIRMAR
A179: 000774 | B179: 21090242 | C179: CHAUPI | D179: ESCOBAR CORIMANYA, VICENTE PAUL | E179: CALLE 28 DE JULIO | F179: FALTA FIRMAR POR EL TITULAR Y ENTREGAR
A180: 000771 | B180: 23020875 | C180: CHAUPI | D180: SILLOCA HUAMANI, MARLENI ELIANA | E180: CALLE LUCMANI S/N | F180: FALTA SUBSANAR Y FIRMAR POR EL PRESIDENTE
A181: 000772 | B181: 22260480 | C181: PACHAYZA | D181: HUAMANI CORIMANYA ANYELA | E181: PACHAYZA - PARTE BAJA | F181: FALTA FIRMAR POR EL TITULAR Y ENTREGAR
A182: 000766 | B182: 22392758 | C182: PACHAYZA | D182: CHAUCAYANQUI URDAY, JORGE LUIS | E182: SECTOR PACHAYZA - PUCRO | F182: FALTA FIRMAR POR EL TITULAR Y ENTREGAR
A183: 000768 | B183: 22392764 | C183: LUCMANI | D183: ANTACHOQUE VERA,DAVID TOMAS | E183: LUCMANI S/N | F183: FALTA FIRMAR POR EL TITULAR Y ENTREGAR
